Workbook
Name _2Excel_BuiltIn_Print_Titles_2_1: (#REF!,#REF!)
Name _2Excel_BuiltIn_Print_Titles_2_1: (#REF!,#REF!)
Name _2Excel_BuiltIn_Print_Titles_2_1: (#REF!,#REF!)
Name _2Excel_BuiltIn_Print_Titles_2_1: (#REF!,#REF!)
Name _2Excel_BuiltIn_Print_Titles_2_1: (#REF!,#REF!)
Name _2Excel_BuiltIn_Print_Titles_2_1: (#REF!,#REF!)
Name _2Excel_BuiltIn_Print_Titles_2_1: (#REF!,#REF!)
Name _2Excel_BuiltIn_Print_Titles_2_1: (#REF!,#REF!)
Name _2Excel_BuiltIn_Print_Titles_2_1: (#REF!,#REF!)
Name _2Excel_BuiltIn_Print_Titles_2_1: (#REF!,#REF!)
Name _2Excel_BuiltIn_Print_Titles_2_1: (#REF!,#REF!)
Name _2Excel_BuiltIn_Print_Titles_2_1: (#REF!,#REF!)
Name _2Excel_BuiltIn_Print_Titles_2_1: (#REF!,#REF!)
Name _2Excel_BuiltIn_Print_Titles_2_1: (#REF!,#REF!)
Name _2Excel_BuiltIn_Print_Titles_2_1: (#REF!,#REF!)
Name _2Excel_BuiltIn_Print_Titles_2_1: (#REF!,#REF!)
Name _2Excel_BuiltIn_Print_Titles_2_1: (#REF!,#REF!)
Name _2Excel_BuiltIn_Print_Titles_2_1: (#REF!,#REF!)
Name _2Excel_BuiltIn_Print_Titles_2_1: (#REF!,#REF!)
Name _2Excel_BuiltIn_Print_Titles_2_1: (#REF!,#REF!)
Name _2Excel_BuiltIn_Print_Titles_2_1: (#REF!,#REF!)
Name _2Excel_BuiltIn_Print_Titles_2_1: (#REF!,#REF!)
Name _2Excel_BuiltIn_Print_Titles_2_1: (#REF!,#REF!)
Name _2Excel_BuiltIn_Print_Titles_2_1: (#REF!,#REF!)
Name _2Excel_BuiltIn_Print_Titles_2_1: (#REF!,#REF!)
Name _2Excel_BuiltIn_Print_Titles_2_1: (#REF!,#REF!)
Name _2Excel_BuiltIn_Print_Titles_2_1: (#REF!,#REF!)
Name _2Excel_BuiltIn_Print_Titles_2_1: (#REF!,#REF!)
Name _IN002010: #REF!
Name _IN002010: #REF!
Name _IN002010: #REF!
Name _IN002010: #REF!
Name _IN002010: #REF!
Name _IN002010: #REF!
Name _IN002010: #REF!
Name _IN002010: #REF!
Name _IN002010: #REF!
Name _IN002010: #REF!
Name _IN002010: #REF!
Name _IN002010: #REF!
Name _IN002010: #REF!
Name _IN002010: #REF!
Name _IN002010: #REF!
Name _IN002010: #REF!
Name _IN002010: #REF!
Name _IN002010: #REF!
Name _IN002010: #REF!
Name _IN002010: #REF!
Name _IN002010: #REF!
Name _IN002010: #REF!
Name _IN002010: #REF!
Name _IN002010: #REF!
Name _IN002010: #REF!
Name _IN002010: #REF!
Name _IN002010: #REF!
Name _IN002010: #REF!
Name _IN002040: #REF!
Name _IN002040: #REF!
Name _IN002040: #REF!
Name _IN002040: #REF!

Sheet Pricing Structure
B2: PRICING STRUCTURE | L2: Approved | T2: Approved | AB2: Approved
F3: GSS LOKAL 40 | N3: IIP LOKAL 40 | V3: IHAG LOKAL 40
B5: General Info | C5: Type | F5: (Existing) | H5: Scenario 1 | J5: Scenario 2 | L5: Scenario 3 | N5: (Existing) | P5: Scenario 1 | R5: Scenario 2 | T5: Scenario 3 | V5: (Existing) | X5: Scenario 1 | Z5: Scenario 2 | AB5: Scenario 3
C6: Flavour Matcode | F6: GSS LOKAL 40 | H6: =F6 -> GSS LOKAL 40 | J6: =F6 -> GSS LOKAL 40 | L6: =F6 -> GSS LOKAL 40 | N6: IIP LOKAL 40 | P6: =N6 -> IIP LOKAL 40 | R6: =N6 -> IIP LOKAL 40 | T6: =N6 -> IIP LOKAL 40 | V6: IHAG LOKAL 40 | X6: =V6 -> IHAG LOKAL 40 | Z6: =V6 -> IHAG LOKAL 40 | AB6: =V6 -> IHAG LOKAL 40
C7: CIF | F7: CURRENT (CIF $5.6/crtn) | N7: CURRENT (CIF $5.6/crtn) | V7: CURRENT (CIF $5.6/crtn)
C8: Disc | F8: TP $0.47/ctn, MF $1.1/ctn | H8: TP $0.47/ctn, MF $1.1/ctn | J8: TP $0.47/ctn, MF $0.90/ctn | L8: TP $0.40/ctn, MF $1/ctn | N8: TP $0.47/ctn, MF $0.9/ctn | P8: TP $0.47/ctn, MF $0.9/ctn | R8: TP $0.47/ctn, MF $0.60/ctn | T8: TP $0.40/ctn, MF $0.75/ctn | V8: TP $0.47/ctn | X8: TP $0.47/ctn | Z8: TP $0.47/ctn | AB8: TP $0.40/ctn
C9: Content | F9: 40 | G9: =+F9 -> 40 | H9: 40 | I9: =+H9 -> 40 | J9: 40 | K9: =+J9 -> 40 | L9: 40 | M9: =+L9 -> 40 | N9: 40 | O9: =+N9 -> 40 | P9: 40 | Q9: =+P9 -> 40 | R9: 40 | S9: =+R9 -> 40 | T9: 40 | U9: =+T9 -> 40 | V9: 40 | W9: =+V9 -> 40 | X9: 40 | Y9: =+X9 -> 40 | Z9: 40 | AA9: =+Z9 -> 40 | AB9: 40 | AC9: =+AB9 -> 40
C10: Currency | F10: KHR | G10: USD | H10: =F10 -> KHR | I10: USD | J10: =H10 -> KHR | K10: USD | L10: =J10 -> KHR | M10: USD | N10: KHR | O10: USD | P10: =N10 -> KHR | Q10: USD | R10: =P10 -> KHR | S10: USD | T10: =R10 -> KHR | U10: USD | V10: KHR | W10: USD | X10: =V10 -> KHR | Y10: USD | Z10: =X10 -> KHR | AA10: USD | AB10: =Z10 -> KHR | AC10: USD
C11: Exchange rate per- | D11: 44217 | F11: 4080 | H11: =F11 -> 4080 | J11: =H11 -> 4080 | L11: =J11 -> 4080 | N11: 4080 | P11: =N11 -> 4080 | R11: =P11 -> 4080 | T11: =R11 -> 4080 | V11: 4080 | X11: =V11 -> 4080 | Z11: =X11 -> 4080 | AB11: =Z11 -> 4080
B14: Consumer | C14: CBP with VAT - per pack | F14: 1000 | G14: =+F14/$H$11 -> 0.24509804 | H14: 1000 | I14: =+H14/$H$11 -> 0.24509804 | J14: =H14 -> 1000 | K14: =+J14/$H$11 -> 0.24509804 | L14: =J14 -> 1000 | M14: =+L14/$H$11 -> 0.24509804 | N14: 1000 | O14: =+N14/$H$11 -> 0.24509804 | P14: 1000 | Q14: =+P14/$H$11 -> 0.24509804 | R14: =P14 -> 1000 | S14: =+R14/$H$11 -> 0.24509804 | T14: =R14 -> 1000 | U14: =+T14/$H$11 -> 0.24509804 | V14: 1000 | W14: =+V14/$H$11 -> 0.24509804 | X14: 1000 | Y14: =+X14/$H$11 -> 0.24509804 | Z14: =X14 -> 1000 | AA14: =+Z14/$H$11 -> 0.24509804 | AB14: =Z14 -> 1000 | AC14: =+AB14/$H$11 -> 0.24509804
C15: CBP with VAT - per carton | F15: =+F14*F9 -> 40000 | G15: =+G14*G9 -> 9.8039216 | H15: =+H14*H9 -> 40000 | I15: =+I14*I9 -> 9.8039216 | J15: =+J14*J9 -> 40000 | K15: =+K14*K9 -> 9.8039216 | L15: =+L14*L9 -> 40000 | M15: =+M14*M9 -> 9.8039216 | ... AC15: =+AC14*AC9 -> 9.8039216
C16: VAT | D16: - per pack | F16: 0 | G16: 0 | H16: 0 | I16: 0 | J16: 0 | K16: 0 | L16: 0 | M16: 0 | N16: 0 | O16: 0 | P16: 0 | Q16: 0 | R16: 0 | S16: 0 | T16: 0 | U16: 0 | V16: 0 | W16: 0 | X16: 0 | Y16: 0 | Z16: 0 | AA16: 0 | AB16: 0 | AC16: 0
C17: VAT % | F17: 0 | G17: 0 | H17: 0 | I17: 0 | J17: 0 | K17: 0 | L17: 0 | M17: 0 | N17: 0 | O17: 0 | P17: 0 | Q17: 0 | R17: 0 | S17: 0 | T17: 0 | U17: 0 | V17: 0 | W17: 0 | X17: 0 | Y17: 0 | Z17: 0 | AA17: 0 | AB17: 0 | AC17: 0
C18: CBP without VAT - per pack | F18: =F14-F16 -> 1000 | G18: =G14-G16 -> 0.24509804 | H18: =H14-H16 -> 1000 | I18: =I14-I16 -> 0.24509804 | J18: =J14-J16 -> 1000 | K18: =K14-K16 -> 0.24509804 | L18: =L14-L16 -> 1000 | M18: =M14-M16 -> 0.24509804 | ... AC18: =AC14-AC16 -> 0.24509804
C19: CBP without VAT - per carton | F19: =1/(1+F17)*F15 -> 40000 | G19: =1/(1+G17)*G15 -> 9.8039216 | H19: =1/(1+H17)*H15 -> 40000 | I19: =1/(1+I17)*I15 -> 9.8039216 | J19: =1/(1+J17)*J15 -> 40000 | K19: =1/(1+K17)*K15 -> 9.8039216 | L19: =1/(1+L17)*L15 -> 40000 | M19: =1/(1+M17)*M15 -> 9.8039216 | ... AC19: =1/(1+AC17)*AC15 -> 9.8039216
B21: Retailer
C22: Retailers' margin (%) | F22: =F23/F19 -> 0.19 | G22: =G23/G19 -> 0.19 | H22: =H23/H19 -> 0.19 | I22: =I23/I19 -> 0.19 | J22: =J23/J19 -> 0.19 | K22: =K23/K19 -> 0.19 | L22: =L23/L19 -> 0.19 | M22: =M23/M19 -> 0.19 | ... AC22: =AC23/AC19 -> 0.19
C23: Retailers' margin | F23: =F19-F25 -> 7600 | G23: =G19-G25 -> 1.8627451 | H23: =H19-H25 -> 7600 | I23: =I19-I25 -> 1.8627451 | J23: =J19-J25 -> 7600 | K23: =K19-K25 -> 1.8627451 | L23: =L19-L25 -> 7600 | M23: =M19-M25 -> 1.8627451 | ... AC23: =AC19-AC25 -> 1.8627451
C24: Retailers' Buying Price per carton +VAT | F24: =F25 -> 32400 | G24: =G25 -> 7.9411765 | H24: =H25 -> 32400 | I24: =I25 -> 7.9411765 | J24: =J25 -> 32400 | K24: =K25 -> 7.9411765 | L24: =L25 -> 32400 | M24: =M25 -> 7.9411765 | ... AC24: =AC25 -> 7.9411765
C25: Retailers' Buying Price (ctn) | F25: 32400 | G25: =+F25/$H$11 -> 7.9411765 | H25: =F25 -> 32400 | I25: =+H25/$H$11 -> 7.9411765 | J25: =H25 -> 32400 | K25: =+J25/$H$11 -> 7.9411765 | L25: =J25 -> 32400 | M25: =+L25/$H$11 -> 7.9411765 | N25: 32400 | O25: =+N25/$H$11 -> 7.9411765 | P25: =N25 -> 32400 | Q25: =+P25/$H$11 -> 7.9411765 | R25: =P25 -> 32400 | S25: =+R25/$H$11 -> 7.9411765 | T25: =R25 -> 32400 | U25: =+T25/$H$11 -> 7.9411765 | V25: 32400 | W25: =+V25/$H$11 -> 7.9411765 | X25: =V25 -> 32400 | Y25: =+X25/$H$11 -> 7.9411765 | Z25: =X25 -> 32400 | AA25: =+Z25/$H$11 -> 7.9411765 | AB25: =Z25 -> 32400 | AC25: =+AB25/$H$11 -> 7.9411765
B27: Wholesaler
C28: Wholesalers' margin (%) | F28: =F29/F25 -> 0.071541433 | G28: =G29/G25 -> 0.071541433 | H28: =H29/H25 -> 0.071541433 | I28: =I29/I25 -> 0.071541433 | J28: =J29/J25 -> 0.071541433 | K28: =K29/K25 -> 0.071541433 | L28: =L29/L25 -> 0.071541433 | M28: =M29/M25 -> 0.071541433 | ... AC28: =AC29/AC25 -> 0.071541433
C29: Wholesalers' margin | F29: =F25-F31 -> 2317.9424 | G29: =G25-G31 -> 0.56812315 | H29: =H25-H31 -> 2317.9424 | I29: =I25-I31 -> 0.56812315 | J29: =J25-J31 -> 2317.9424 | K29: =K25-K31 -> 0.56812315 | L29: =L25-L31 -> 2317.9424 | M29: =M25-M31 -> 0.56812315 | ... AC29: =AC25-AC31 -> 0.56812315
C30: Wholesalers' Buying Price per carton +VAT | F30: =+F31 -> 30082.058 | G30: =G31 -> 7.3730533 | H30: =+H31 -> 30082.058 | I30: =I31 -> 7.3730533 | J30: =+J31 -> 30082.058 | K30: =K31 -> 7.3730533 | L30: =+L31 -> 30082.058 | M30: =M31 -> 7.3730533 | N30: =+N31 -> 30082.058 | O30: =O31 -> 7.3730533 | P30: =+P31 -> 30082.058 | Q30: =Q31 -> 7.3730533 | R30: =+R31 -> 30082.058 | S30: =S31 -> 7.3730533 | T30: =+T31 -> 30082.058 | U30: =U31 -> 7.3730533 | V30: =+V31 -> 30082.058 | W30: =W31 -> 7.3730533 | X30: =+X31 -> 30082.058 | Y30: =Y31 -> 7.3730533 | Z30: =+Z31 -> 30082.058 | AA30: =AA31 -> 7.3730533 | AB30: =+AB31 -> 30082.058 | AC30: =AC31 -> 7.3730533
C31: Wholesalers' Buying Price (ctn) | F31: 30082.058 | G31: =+F31/$H$11 -> 7.3730533 | H31: 30082.058 | I31: =+H31/$H$11 -> 7.3730533 | J31: 30082.058 | K31: =+J31/$H$11 -> 7.3730533 | L31: 30082.058 | M31: =+L31/$H$11 -> 7.3730533 | N31: 30082.058 | O31: =+N31/$H$11 -> 7.3730533 | P31: 30082.058 | Q31: =+P31/$H$11 -> 7.3730533 | R31: 30082.058 | S31: =+R31/$H$11 -> 7.3730533 | T31: 30082.058 | U31: =+T31/$H$11 -> 7.3730533 | V31: 30082.058 | W31: =+V31/$H$11 -> 7.3730533 | X31: 30082.058 | Y31: =+X31/$H$11 -> 7.3730533 | Z31: 30082.058 | AA31: =+Z31/$H$11 -> 7.3730533 | AB31: 30082.058 | AC31: =+AB31/$H$11 -> 7.3730533
B33: Distributor
C34: Distributors' margin (%) | F34: =+F35/F31 -> 0.13332703 | G34: =+G35/G31 -> 0.13332703 | H34: =+H35/H31 -> 0.1098293 | I34: =+I35/I31 -> 0.1098293 | J34: =+J35/J31 -> 0.13332703 | K34: =+K35/K31 -> 0.13332703 | L34: =+L35/L31 -> 0.12236142 | M34: =+M35/M31 -> 0.12236142 | ... AC34: =+AC35/AC31 -> 0.11664246
C35: Distributors' margin | F35: =+F31-F36 -> 4010.7513 | G35: =+G31-G36 -> 0.98302729 | H35: =+H31-H36 -> 3303.8913 | I35: =+I31-I36 -> 0.80977729 | J35: =+J31-J36 -> 4010.7513 | K35: =+K31-K36 -> 0.98302729 | L35: =+L31-L36 -> 3680.8833 | M35: =+M31-M36 -> 0.90217729 | ... AC35: =+AC31-AC36 -> 0.86001107
C36: Distributors' Buying Price | F36: =+G40*F11 -> 26071.306 | G36: =+G40 -> 6.390026 | H36: =+I40*H11 -> 26778.166 | I36: =+I40 -> 6.563276 | J36: =+K40*J11 -> 26071.306 | K36: =+K40 -> 6.390026 | L36: =+M40*L11 -> 26401.174 | M36: =+M40 -> 6.470876 | N36: =+O40*N11 -> 26010.612 | O36: =+O40 -> 6.37515 | P36: =+Q40*P11 -> 26717.472 | Q36: =+Q40 -> 6.5484 | R36: =+S40*R11 -> 26010.612 | S36: =+S40 -> 6.37515 | T36: =+U40*T11 -> 26340.48 | U36: =+U40 -> 6.456 | V36: =+W40*V11 -> 26243.344 | W36: =+W40 -> 6.4321923 | X36: =+Y40*X11 -> 26950.204 | Y36: =+Y40 -> 6.6054423 | Z36: =+AA40*Z11 -> 26243.344 | AA36: =+AA40 -> 6.4321923 | AB36: =+AC40*AB11 -> 26573.212 | AC36: =+AC40 -> 6.5130423
C37: Additional cost In Land trucking | F37: 0 | H37: 0 | J37: 0 | L37: 0 | N37: 0 | P37: 0 | R37: 0 | T37: 0 | V37: 0 | X37: 0 | Z37: 0 | AB37: 0
B38: Importer / Distributor
C39: Landed Cost in pack | E39: USD | F39: =+F40/F9 -> 651.78266 | G39: =+G40/G9 -> 0.15975065 | H39: =+H40/H9 -> 669.45416 | I39: =+I40/I9 -> 0.1640819 | J39: =+J40/J9 -> 651.78266 | K39: =+K40/K9 -> 0.15975065 | L39: =+L40/L9 -> 660.02936 | M39: =+M40/M9 -> 0.1617719 | ... AC39: =+AC40/AC9 -> 0.16282606
C40: Landed Cost in carton | E40: USD | F40: =+G40*F11 -> 26071.306 | G40: =+G41+G43+G47+G45 -> 6.390026 | H40: =+I40*H11 -> 26778.166 | I40: =+I41+I43+I47+I45 -> 6.563276 | J40: =+K40*J11 -> 26071.306 | K40: =+K41+K43+K47+K45 -> 6.390026 | L40: =+M40*L11 -> 26401.174 | M40: =+M41+M43+M47+M45 -> 6.470876 | N40: =+O40*N11 -> 26010.612 | O40: =+O41+O43+O47+O45 -> 6.37515 | P40: =+Q40*P11 -> 26717.472 | Q40: =+Q41+Q43+Q47+Q45 -> 6.5484 | R40: =+S40*R11 -> 26010.612 | S40: =+S41+S43+S47+S45 -> 6.37515 | T40: =+U40*T11 -> 26340.48 | U40: =+U41+U43+U47+U45 -> 6.456 | V40: =+W40*V11 -> 26243.344 | W40: =+W41+W43+W47+W45 -> 6.4321923 | X40: =+Y40*X11 -> 26950.204 | Y40: =+Y41+Y43+Y47+Y45 -> 6.6054423 | Z40: =+AA40*Z11 -> 26243.344 | AA40: =+AA41+AA43+AA47+AA45 -> 6.4321923 | AB40: =+AC40*AB11 -> 26573.212 | AC40: =+AC41+AC43+AC47+AC45 -> 6.5130423
C41: Import duty rate - 5% | E41: USD | G41: =+G42*G47 -> 0.2565 | I41: =+I42*I47 -> 0.264 | K41: =+K42*K47 -> 0.2565 | M41: =+M42*M47 -> 0.26 | O41: =+O42*O47 -> 0.2565 | Q41: =+Q42*Q47 -> 0.264 | S41: =+S42*S47 -> 0.2565 | U41: =+U42*U47 -> 0.26 | W41: =+W42*W47 -> 0.2565 | Y41: =+Y42*Y47 -> 0.264 | AA41: =+AA42*AA47 -> 0.2565 | AC41: =+AC42*AC47 -> 0.26
C42: Import duty % | G42: 0.05 | I42: =G42 -> 0.05 | K42: =I42 -> 0.05 | M42: =K42 -> 0.05 | O42: 0.05 | Q42: =O42 -> 0.05 | S42: =Q42 -> 0.05 | U42: =S42 -> 0.05 | W42: 0.05 | Y42: =W42 -> 0.05 | AA42: =Y42 -> 0.05 | AC42: =AA42 -> 0.05
C43: Other charges - Clearance cost | E43: USD | G43: =$D$44/G56 -> 0.46487603 | I43: =$D$44/I56 -> 0.46487603 | K43: =$D$44/K56 -> 0.46487603 | M43: =$D$44/M56 -> 0.46487603 | O43: =$D$44/O56 -> 0.45 | Q43: =$D$44/Q56 -> 0.45 | S43: =$D$44/S56 -> 0.45 | U43: =$D$44/U56 -> 0.45 | W43: =$D$44/W56 -> 0.50704225 | Y43: =$D$44/Y56 -> 0.50704225 | AA43: =$D$44/AA56 -> 0.50704225 | AC43: =$D$44/AC56 -> 0.50704225
C44: Other charges % | D44: 1800 | G44: =G43/G47 -> 0.09061911 | I44: =I43/I47 -> 0.088044703 | K44: =K43/K47 -> 0.09061911 | M44: =M43/M47 -> 0.089399237 | O44: =O43/O47 -> 0.087719298 | Q44: =Q43/Q47 -> 0.085227273 | S44: =S43/S47 -> 0.087719298 | U44: =U43/U47 -> 0.086538462 | W44: =W43/W47 -> 0.098838646 | Y44: =Y43/Y47 -> 0.09603073 | AA44: =AA43/AA47 -> 0.098838646 | AC44: =AC43/AC47 -> 0.097508126
C45: VAT in | G45: =(G46*(G47+G41)) -> 0.53865 | I45: =(I46*(I47+I41)) -> 0.5544 | K45: =(K46*(K47+K41)) -> 0.53865 | M45: =(M46*(M47+M41)) -> 0.546 | O45: =(O46*(O47+O41)) -> 0.53865 | Q45: =(Q46*(Q47+Q41)) -> 0.5544 | S45: =(S46*(S47+S41)) -> 0.53865 | U45: =(U46*(U47+U41)) -> 0.546 | W45: =(W46*(W47+W41)) -> 0.53865 | Y45: =(Y46*(Y47+Y41)) -> 0.5544 | AA45: =(AA46*(AA47+AA41)) -> 0.53865 | AC45: =(AC46*(AC47+AC41)) -> 0.546
C46: VAT in (% from CIF + Import duty) | G46: 0.1 | I46: 0.1 | K46: 0.1 | M46: 0.1 | O46: 0.1 | Q46: 0.1 | S46: 0.1 | U46: 0.1 | W46: 0.1 | Y46: 0.1 | AA46: 0.1 | AC46: 0.1
C47: CIF price after support & Freight Surcharge | E47: USD | G47: =G51-G48+G49 -> 5.13 | I47: =I51-I48+I49 -> 5.28 | K47: =K51-K48+K49 -> 5.13 | M47: =M51-M48+M49 -> 5.2 | O47: =O51-O48+O49 -> 5.13 | Q47: =Q51-Q48+Q49 -> 5.28 | S47: =S51-S48+S49 -> 5.13 | U47: =U51-U48+U49 -> 5.2 | W47: =W51-W48+W49 -> 5.13 | Y47: =Y51-Y48+Y49 -> 5.28 | AA47: =AA51-AA48+AA49 -> 5.13 | AC47: =AC51-AC48+AC49 -> 5.2
C48: PROMO SUPPORT | E48: =+E47 -> USD | G48: 0.47 | I48: =G48 -> 0.47 | K48: 0.47 | M48: 0.4 | O48: 0.47 | Q48: =O48 -> 0.47 | S48: 0.47 | U48: 0.4 | W48: 0.47 | Y48: =W48 -> 0.47 | AA48: 0.47 | AC48: 0.4
C49: FREIGHT SURCHARGE | E49: =+E48 -> USD | G49: 0 | I49: 0 | K49: 0 | M49: 0 | O49: 0 | Q49: 0 | S49: 0 | U49: 0 | W49: 0 | Y49: 0 | AA49: 0 | AC49: 0
C50: FOB + FREIGHT + INSURANCE | E50: USD | G50: =+G53+G55+G57 -> 5.60308 | I50: =+I53+I55+I57 -> 5.7531625 | K50: =+K53+K55+K57 -> 5.60308 | M50: =+M53+M55+M57 -> 5.60308 | O50: =+O53+O55+O57 -> 5.60308 | Q50: =+Q53+Q55+Q57 -> 5.7531625 | S50: =+S53+S55+S57 -> 5.60308 | U50: =+U53+U55+U57 -> 5.60308 | W50: =+W53+W55+W57 -> 5.60308 | Y50: =+Y53+Y55+Y57 -> 5.7531625 | AA50: =+AA53+AA55+AA57 -> 5.60308 | AC50: =+AC53+AC55+AC57 -> 5.60308
C51: CIF price | E51: USD | G51: 5.6 | I51: 5.75 | K51: 5.6 | M51: 5.6 | O51: 5.6 | Q51: 5.75 | S51: 5.6 | U51: 5.6 | W51: 5.6 | Y51: 5.75 | AA51: 5.6 | AC51: 5.6
C52: COST :
C53: Insurance | E53: per carton USD | G53: =0.055/100*(G57+(G54/G56)) -> 0.00308 | I53: =0.055/100*(I57+(I54/I56)) -> 0.0031625 | K53: =0.055/100*(K57+(K54/K56)) -> 0.00308 | M53: =0.055/100*(M57+(M54/M56)) -> 0.00308 | O53: =0.055/100*(O57+(O54/O56)) -> 0.00308 | Q53: =0.055/100*(Q57+(Q54/Q56)) -> 0.0031625 | S53: =0.055/100*(S57+(S54/S56)) -> 0.00308 | U53: =0.055/100*(U57+(U54/U56)) -> 0.00308 | W53: =0.055/100*(W57+(W54/W56)) -> 0.00308 | Y53: =0.055/100*(Y57+(Y54/Y56)) -> 0.0031625 | AA53: =0.055/100*(AA57+(AA54/AA56)) -> 0.00308 | AC53: =0.055/100*(AC57+(AC54/AC56)) -> 0.00308
C54: Freight cost | D54: - 40 HI-CUBE | G54: 620 | I54: =G54 -> 620 | K54: =I54 -> 620 | M54: =K54 -> 620 | O54: 620 | Q54: =O54 -> 620 | S54: =Q54 -> 620 | U54: =S54 -> 620 | W54: 620 | Y54: =W54 -> 620 | AA54: =Y54 -> 620 | AC54: =AA54 -> 620
C55: =+C54 -> Freight cost | E55: =+E53 -> per carton USD | G55: =+G54/G56 -> 0.16012397 | I55: =+I54/I56 -> 0.16012397 | K55: =+K54/K56 -> 0.16012397 | M55: =+M54/M56 -> 0.16012397 | O55: =+O54/O56 -> 0.155 | Q55: =+Q54/Q56 -> 0.155 | S55: =+S54/S56 -> 0.155 | U55: =+U54/U56 -> 0.155 | W55: =+W54/W56 -> 0.17464789 | Y55: =+Y54/Y56 -> 0.17464789 | AA55: =+AA54/AA56 -> 0.17464789 | AC55: =+AC54/AC56 -> 0.17464789
C56: Container load | E56: per carton USD | G56: 3872 | I56: =G56 -> 3872 | K56: =I56 -> 3872 | M56: =K56 -> 3872 | O56: 4000 | Q56: =O56 -> 4000 | S56: =Q56 -> 4000 | U56: =S56 -> 4000 | W56: 3550 | Y56: =W56 -> 3550 | AA56: =Y56 -> 3550 | AC56: =AA56 -> 3550
C57: FOB-JKT | E57: per carton USD | G57: =G51-G55 -> 5.439876 | I57: =I51-I55 -> 5.589876 | K57: =K51-K55 -> 5.439876 | M57: =M51-M55 -> 5.439876 | O57: =O51-O55 -> 5.445 | Q57: =Q51-Q55 -> 5.595 | S57: =S51-S55 -> 5.445 | U57: =U51-U55 -> 5.445 | W57: =W51-W55 -> 5.4253521 | Y57: =Y51-Y55 -> 5.5753521 | AA57: =AA51-AA55 -> 5.4253521 | AC57: =AC51-AC55 -> 5.4253521
C58: FOB-JKT after disc | E58: per carton USD | G58: =G47-G55 -> 4.969876 | I58: =I47-I55 -> 5.119876 | K58: =K47-K55 -> 4.969876 | M58: =M47-M55 -> 5.039876 | O58: =O47-O55 -> 4.975 | Q58: =Q47-Q55 -> 5.125 | S58: =S47-S55 -> 4.975 | U58: =U47-U55 -> 5.045 | W58: =W47-W55 -> 4.9553521 | Y58: =Y47-Y55 -> 5.1053521 | AA58: =AA47-AA55 -> 4.9553521 | AC58: =AC47-AC55 -> 5.0253521
E59: per pack USD | G59: =+G57/G9 -> 0.1359969 | I59: =+I57/I9 -> 0.1397469 | K59: =+K57/K9 -> 0.1359969 | M59: =+M57/M9 -> 0.1359969 | O59: =+O57/O9 -> 0.136125 | Q59: =+Q57/Q9 -> 0.139875 | S59: =+S57/S9 -> 0.136125 | U59: =+U57/U9 -> 0.136125 | W59: =+W57/W9 -> 0.1356338 | Y59: =+Y57/Y9 -> 0.1393838 | AA59: =+AA57/AA9 -> 0.1356338 | AC59: =+AC57/AC9 -> 0.1356338
B61: Producer | C61: COGS after VSE | E61: per carton USD | G61: =G64+G62 -> 3.644178 | I61: =I64+I62 -> 3.644178 | K61: =K64+K62 -> 3.644178 | M61: =M64+M62 -> 3.644178 | O61: =O64+O62 -> 3.9280357 | Q61: =Q64+Q62 -> 3.9280357 | S61: =S64+S62 -> 3.9280357 | U61: =U64+U62 -> 3.9280357 | W61: =W64+W62 -> 4.8437877 | Y61: =Y64+Y62 -> 4.8437877 | AA61: =AA64+AA62 -> 4.8437877 | AC61: =AC64+AC62 -> 4.8437877
C62: VSE | E62: per carton USD | G62: =G103 -> 0.11917798 | I62: =I103 -> 0.11917798 | K62: =K103 -> 0.11917798 | M62: =M103 -> 0.11917798 | O62: =O103 -> 0.11553571 | Q62: =Q103 -> 0.11553571 | S62: =S103 -> 0.11553571 | U62: =U103 -> 0.11553571 | W62: =W103 -> 0.12950201 | Y62: =Y103 -> 0.12950201 | AA62: =AA103 -> 0.12950201 | AC62: =AC103 -> 0.12950201
C64: COGS | E64: =+E57 -> per carton USD | G64: =+G66*G9/G68 -> 3.525 | I64: =+I66*I9/I68 -> 3.525 | K64: =+K66*K9/K68 -> 3.525 | M64: =+M66*M9/M68 -> 3.525 | O64: =+O66*O9/O68 -> 3.8125 | Q64: =+Q66*Q9/Q68 -> 3.8125 | S64: =+S66*S9/S68 -> 3.8125 | U64: =+U66*U9/U68 -> 3.8125 | W64: =+W66*W9/W68 -> 4.7142857 | Y64: =+Y66*Y9/Y68 -> 4.7142857 | AA64: =+AA66*AA9/AA68 -> 4.7142857 | AC64: =+AC66*AC9/AC68 -> 4.7142857
E65: =+E59 -> per pack USD | G65: =+G64/G9 -> 0.088125 | I65: =+I64/I9 -> 0.088125 | K65: =+K64/K9 -> 0.088125 | M65: =+M64/M9 -> 0.088125 | O65: =+O64/O9 -> 0.0953125 | Q65: =+Q64/Q9 -> 0.0953125 | S65: =+S64/S9 -> 0.0953125 | U65: =+U64/U9 -> 0.0953125 | W65: =+W64/W9 -> 0.11785714 | Y65: =+Y64/Y9 -> 0.11785714 | AA65: =+AA64/AA9 -> 0.11785714 | AC65: =+AC64/AC9 -> 0.11785714
C66: COGS in pack | E66: Rp. | G66: =49350/40 -> 1233.75 | I66: 1233.75 | K66: 1233.75 | M66: 1233.75 | O66: =53375/40 -> 1334.375 | Q66: =O66 -> 1334.375 | S66: =Q66 -> 1334.375 | U66: =S66 -> 1334.375 | W66: 1650 | Y66: =W66 -> 1650 | AA66: =Y66 -> 1650 | AC66: =AA66 -> 1650
C68: Exchange rate | E68: 1 USD = RP. | G68: 14000 | I68: =G68 -> 14000 | K68: =I68 -> 14000 | M68: =K68 -> 14000 | O68: 14000 | Q68: =O68 -> 14000 | S68: =Q68 -> 14000 | U68: =S68 -> 14000 | W68: 14000 | Y68: =W68 -> 14000 | AA68: =Y68 -> 14000 | AC68: =AA68 -> 14000
C69: Margins from FOB | E69: =+E64 -> per carton USD | G69: =+G57-G64 -> 1.914876 | I69: =+I57-I64 -> 2.064876 | K69: =+K57-K64 -> 1.914876 | M69: =+M57-M64 -> 1.914876 | O69: =+O57-O64 -> 1.6325 | Q69: =+Q57-Q64 -> 1.7825 | S69: =+S57-S64 -> 1.6325 | U69: =+U57-U64 -> 1.6325 | W69: =+W57-W64 -> 0.7110664 | Y69: =+Y57-Y64 -> 0.8610664 | AA69: =+AA57-AA64 -> 0.7110664 | AC69: =+AC57-AC64 -> 0.7110664
E70: =+E65 -> per pack USD | G70: =+G69/G9 -> 0.047871901 | I70: =+I69/I9 -> 0.051621901 | K70: =+K69/K9 -> 0.047871901 | M70: =+M69/M9 -> 0.047871901 | O70: =+O69/O9 -> 0.0408125 | Q70: =+Q69/Q9 -> 0.0445625 | S70: =+S69/S9 -> 0.0408125 | U70: =+U69/U9 -> 0.0408125 | W70: =+W69/W9 -> 0.01777666 | Y70: =+Y69/Y9 -> 0.02152666 | AA70: =+AA69/AA9 -> 0.01777666 | AC70: =+AC69/AC9 -> 0.01777666
C71: Margin % from FOB | G71: =+G69/G57 -> 0.35200729 | I71: =+I69/I57 -> 0.36939568 | K71: =+K69/K57 -> 0.35200729 | M71: =+M69/M57 -> 0.35200729 | O71: =+O69/O57 -> 0.29981635 | Q71: =+Q69/Q57 -> 0.31858803 | S71: =+S69/S57 -> 0.29981635 | U71: =+U69/U57 -> 0.29981635 | W71: =+W69/W57 -> 0.13106364 | Y71: =+Y69/Y57 -> 0.15444162 | AA71: =+AA69/AA57 -> 0.13106364 | AC71: =+AC69/AC57 -> 0.13106364
C72: Margins after Support | E72: =E69 -> per carton USD | G72: =G69-G48 -> 1.444876 | I72: =I69-I48 -> 1.594876 | K72: =K69-K48 -> 1.444876 | M72: =M69-M48 -> 1.514876 | O72: =O69-O48 -> 1.1625 | Q72: =Q69-Q48 -> 1.3125 | S72: =S69-S48 -> 1.1625 | U72: =U69-U48 -> 1.2325 | W72: =W69-W48 -> 0.2410664 | Y72: =Y69-Y48 -> 0.3910664 | AA72: =AA69-AA48 -> 0.2410664 | AC72: =AC69-AC48 -> 0.3110664
C73: Margin % after Support | G73: =G72/G57 -> 0.26560826 | I73: =I72/I57 -> 0.2853151 | K73: =K72/K57 -> 0.26560826 | M73: =M72/M57 -> 0.2784762 | O73: =O72/O57 -> 0.21349862 | Q73: =Q72/Q57 -> 0.23458445 | S73: =S72/S57 -> 0.21349862 | U73: =U72/U57 -> 0.22635445 | W73: =W72/W57 -> 0.044433318 | Y73: =Y72/Y57 -> 0.070142009 | AA73: =AA72/AA57 -> 0.044433318 | AC73: =AC72/AC57 -> 0.057335707
C75: Margin after Support + VSE | E75: =E72 -> per carton USD | G75: =G72-G62 -> 1.3256981 | I75: =I72-I62 -> 1.4756981 | K75: =K72-K62 -> 1.3256981 | M75: =M72-M62 -> 1.3956981 | O75: =O72-O62 -> 1.0469643 | Q75: =Q72-Q62 -> 1.1969643 | S75: =S72-S62 -> 1.0469643 | U75: =U72-U62 -> 1.1169643 | W75: =W72-W62 -> 0.11156439 | Y75: =Y72-Y62 -> 0.26156439 | AA75: =AA72-AA62 -> 0.11156439 | AC75: =AC72-AC62 -> 0.18156439
C76: Margin % after Support + VSE | G76: =G75/G57 -> 0.24370005 | I76: =I75/I57 -> 0.26399477 | K76: =K75/K57 -> 0.24370005 | M76: =M75/M57 -> 0.25656799 | O76: =O75/O57 -> 0.19227994 | Q76: =Q75/Q57 -> 0.21393464 | S76: =S75/S57 -> 0.19227994 | U76: =U75/U57 -> 0.20513577 | W76: =W75/W57 -> 0.020563529 | Y76: =Y75/Y57 -> 0.046914416 | AA76: =AA75/AA57 -> 0.020563529 | AC76: =AC75/AC57 -> 0.033465918
C78: Margin after Support + VSE + Prepayment | E78: =E75 -> per carton USD | G78: =G75 -> 1.3256981 | I78: =I75 -> 1.4756981 | K78: =K75 -> 1.3256981 | M78: =M75 -> 1.3956981 | O78: =O75 -> 1.0469643 | Q78: =Q75 -> 1.1969643 | S78: =S75 -> 1.0469643 | U78: =U75 -> 1.1169643 | W78: =W75 -> 0.11156439 | Y78: =Y75 -> 0.26156439 | AA78: =AA75 -> 0.11156439 | AC78: =AC75 -> 0.18156439
C79: Margin % after Support + VSE + Prepayment | G79: =G78/G57 -> 0.24370005 | I79: =I78/I57 -> 0.26399477 | K79: =K78/K57 -> 0.24370005 | M79: =M78/M57 -> 0.25656799 | O79: =O78/O57 -> 0.19227994 | Q79: =Q78/Q57 -> 0.21393464 | S79: =S78/S57 -> 0.19227994 | U79: =U78/U57 -> 0.20513577 | W79: =W78/W57 -> 0.020563529 | Y79: =Y78/Y57 -> 0.046914416 | AA79: =AA78/AA57 -> 0.020563529 | AC79: =AC78/AC57 -> 0.033465918
C81: Margin after Support + VSE + Prepayment + Marketing | E81: per carton USD | G81: =G78-1.1 -> 0.22569805 | I81: =I78-1.1 -> 0.37569805 | K81: =K78-0.9 -> 0.42569805 | M81: =M78-1 -> 0.39569805 | O81: =O78-0.9 -> 0.14696429 | Q81: =Q78-0.9 -> 0.29696429 | S81: =S78-0.6 -> 0.44696429 | U81: =U78-0.75 -> 0.36696429 | W81: =W78 -> 0.11156439 | Y81: =Y78 -> 0.26156439 | AA81: =AA78 -> 0.11156439 | AC81: =AC78 -> 0.18156439
C82: Margin % after Support + VSE + Prepayment + Marketing | G82: =G81/G57 -> 0.041489558 | I82: =I81/I57 -> 0.067210444 | K82: =K81/K57 -> 0.078255102 | M82: =M81/M57 -> 0.07274027 | O82: =O81/O57 -> 0.026990686 | Q82: =Q81/Q57 -> 0.053076727 | S82: =S81/S57 -> 0.082087105 | U82: =U81/U57 -> 0.067394726 | W82: =W81/W57 -> 0.020563529 | Y82: =Y81/Y57 -> 0.046914416 | AA82: =AA81/AA57 -> 0.020563529 | AC82: =AC81/AC57 -> 0.033465918
C84: OF Difference | G84: =(G119-G118)/G56 -> 0.13688017 | I84: =(I119-I118)/I56 -> 0.13688017 | K84: =(K119-K118)/K56 -> 0.13688017 | M84: =(M119-M118)/M56 -> 0.13688017 | O84: =(O119-O118)/O56 -> 0.1325 | Q84: =(Q119-Q118)/Q56 -> 0.1325 | S84: =(S119-S118)/S56 -> 0.1325 | U84: =(U119-U118)/U56 -> 0.1325 | W84: =(W119-W118)/W56 -> 0.14929577 | Y84: =(Y119-Y118)/Y56 -> 0.14929577 | AA84: =(AA119-AA118)/AA56 -> 0.14929577 | AC84: =(AC119-AC118)/AC56 -> 0.14929577
C86: GP after OF Difference | E86: per carton USD | G86: =G81-G84 -> 0.088817887 | I86: =I81-I84 -> 0.23881789 | K86: =K81-K84 -> 0.28881789 | M86: =M81-M84 -> 0.25881789 | O86: =O81-O84 -> 0.014464286 | Q86: =Q81-Q84 -> 0.16446429 | S86: =S81-S84 -> 0.31446429 | U86: =U81-U84 -> 0.23446429 | W86: =W81-W84 -> -0.037731388 | Y86: =Y81-Y84 -> 0.11226861 | AA86: =AA81-AA84 -> -0.037731388 | AC86: =AC81-AC84 -> 0.032268612
C87: % GP after OF Difference | G87: =G86/G57 -> 0.016327189 | I87: =I86/I57 -> 0.042723289 | K87: =K86/K57 -> 0.053092733 | M87: =M86/M57 -> 0.047577902 | O87: =O86/O57 -> 0.0026564345 | Q87: =Q86/Q57 -> 0.029394868 | S87: =S86/S57 -> 0.057752853 | U87: =U86/U57 -> 0.043060475 | W87: =W86/W57 -> -0.0069546432 | Y87: =Y86/Y57 -> 0.020136596 | AA87: =AA86/AA57 -> -0.0069546432 | AC87: =AC86/AC57 -> 0.0059477451
B88: Freight Difference | C88: Freight in Pricing Structure | E88: USD/40HC | G88: 620 | O88: 620 | W88: 620
C89: Freight in Jan-21 | E89: USD/40HC | G89: 1150 | O89: 1150 | W89: 1150
C90: Freight in Jan-20 | E90: USD/40HC | G90: 750 | O90: 750 | W90: 750
C92: Difference per 40HC | E92: USD/40HC | G92: =G89-G88 -> 530 | O92: =O89-O88 -> 530 | W92: =W89-W88 -> 530
C93: Difference per ctn (Jan-21) | E93: USD/ctn | G93: =G92/G56 -> 0.13688017 | O93: =O92/O56 -> 0.1325 | W93: =W92/W56 -> 0.14929577
C94: Difference per ctn (Jan-20) | E94: USD/ctn | G94: =(G89-G90)/G56 -> 0.10330579 | O94: =(O89-O90)/O56 -> 0.1 | W94: =(W89-W90)/W56 -> 0.11267606
C96: GP After Freight Difference (Jan-21) | G96: =G51-(G89/G56)-G64 -> 1.7779959 | O96: =O51-(O89/O56)-O64 -> 1.5 | W96: =W51-(W89/W56)-W64 -> 0.56177062
C97: Margin % after Freight Difference (Jan-21) | G97: =G96/G57 -> 0.32684492 | O97: =O96/O57 -> 0.27548209 | W97: =W96/W57 -> 0.10354547
C99: GP After Freight Difference (Jan-20) | G99: =G51-(G90/G56)-G64 -> 1.8813017 | O99: =O51-(O90/O56)-O64 -> 1.6 | W99: =W51-(W90/W56)-W64 -> 0.67444668
C100: Margin % after Freight Difference (Jan-20) | G100: =G99/G57 -> 0.34583539 | O100: =O99/O57 -> 0.29384757 | W100: =W99/W57 -> 0.1243139
C102: VSE in $/container | F102: $ | G102: =G104/G68 -> 461.45714 | H102: $ | I102: =I104/I68 -> 461.45714 | J102: $ | K102: =K104/K68 -> 461.45714 | L102: $ | M102: =M104/M68 -> 461.45714 | N102: $ | O102: =O104/O68 -> 462.14286 | P102: $ | Q102: =Q104/Q68 -> 462.14286 | R102: $ | S102: =S104/S68 -> 462.14286 | T102: $ | U102: =U104/U68 -> 462.14286 | V102: $ | W102: =W104/W68 -> 459.73214 | X102: $ | Y102: =Y104/Y68 -> 459.73214 | Z102: $ | AA102: =AA104/AA68 -> 459.73214 | AB102: $ | AC102: =AC104/AC68 -> 459.73214
C103: VSE in $/carton | F103: $ | G103: =G102/G56 -> 0.11917798 | H103: $ | I103: =I102/I56 -> 0.11917798 | J103: $ | K103: =K102/K56 -> 0.11917798 | L103: $ | M103: =M102/M56 -> 0.11917798 | N103: $ | O103: =O102/O56 -> 0.11553571 | P103: $ | Q103: =Q102/Q56 -> 0.11553571 | R103: $ | S103: =S102/S56 -> 0.11553571 | T103: $ | U103: =U102/U56 -> 0.11553571 | V103: $ | W103: =W102/W56 -> 0.12950201 | X103: $ | Y103: =Y102/Y56 -> 0.12950201 | Z103: $ | AA103: =AA102/AA56 -> 0.12950201 | AB103: $ | AC103: =AC102/AC56 -> 0.12950201
C104: VSE in IDR/container | F104: IDR | G104: =G105*G56 -> 6460400 | H104: IDR | I104: =I105*I56 -> 6460400 | J104: IDR | K104: =K105*K56 -> 6460400 | L104: IDR | M104: =M105*M56 -> 6460400 | N104: IDR | O104: =O105*O56 -> 6470000 | P104: IDR | Q104: =Q105*Q56 -> 6470000 | R104: IDR | S104: =S105*S56 -> 6470000 | T104: IDR | U104: =U105*U56 -> 6470000 | V104: IDR | W104: =W105*W56 -> 6436250 | X104: IDR | Y104: =Y105*Y56 -> 6436250 | Z104: IDR | AA104: =AA105*AA56 -> 6436250 | AB104: IDR | AC104: =AC105*AC56 -> 6436250
C105: VSE in IDR/carton | F105: IDR | G105: =SUM(G106:G111) -> 1668.4917 | H105: IDR | I105: =SUM(I106:I111) -> 1668.4917 | J105: IDR | K105: =SUM(K106:K111) -> 1668.4917 | L105: IDR | M105: =SUM(M106:M111) -> 1668.4917 | N105: IDR | O105: =SUM(O106:O111) -> 1617.5 | P105: IDR | Q105: =SUM(Q106:Q111) -> 1617.5 | R105: IDR | S105: =SUM(S106:S111) -> 1617.5 | T105: IDR | U105: =SUM(U106:U111) -> 1617.5 | V105: IDR | W105: =SUM(W106:W111) -> 1813.0282 | X105: IDR | Y105: =SUM(Y106:Y111) -> 1813.0282 | Z105: IDR | AA105: =SUM(AA106:AA111) -> 1813.0282 | AB105: IDR | AC105: =SUM(AC106:AC111) -> 1813.0282
C106: Labor Cost | F106: IDR | G106: 75 | H106: IDR | I106: 75 | J106: IDR | K106: 75 | L106: IDR | M106: 75 | N106: IDR | O106: 75 | P106: IDR | Q106: 75 | R106: IDR | S106: 75 | T106: IDR | U106: 75 | V106: IDR | W106: 75 | X106: IDR | Y106: 75 | Z106: IDR | AA106: 75 | AB106: IDR | AC106: 75
C107: Trucking Cost | F107: IDR | G107: =1940000/G56 -> 501.03306 | H107: IDR | I107: =1940000/I56 -> 501.03306 | J107: IDR | K107: =1940000/K56 -> 501.03306 | L107: IDR | M107: =1940000/M56 -> 501.03306 | N107: IDR | O107: =1940000/O56 -> 485 | P107: IDR | Q107: =1940000/Q56 -> 485 | R107: IDR | S107: =1940000/S56 -> 485 | T107: IDR | U107: =1940000/U56 -> 485 | V107: IDR | W107: =1940000/W56 -> 546.47887 | X107: IDR | Y107: =1940000/Y56 -> 546.47887 | Z107: IDR | AA107: =1940000/AA56 -> 546.47887 | AB107: IDR | AC107: =1940000/AC56 -> 546.47887
C108: Custom Charge | F108: IDR | G108: =275000/G56 -> 71.022727 | H108: IDR | I108: =275000/I56 -> 71.022727 | J108: IDR | K108: =275000/K56 -> 71.022727 | L108: IDR | M108: =275000/M56 -> 71.022727 | N108: IDR | O108: =275000/O56 -> 68.75 | P108: IDR | Q108: =275000/Q56 -> 68.75 | R108: IDR | S108: =275000/S56 -> 68.75 | T108: IDR | U108: =275000/U56 -> 68.75 | V108: IDR | W108: =275000/W56 -> 77.464789 | X108: IDR | Y108: =275000/Y56 -> 77.464789 | Z108: IDR | AA108: =275000/AA56 -> 77.464789 | AB108: IDR | AC108: =275000/AC56 -> 77.464789
C109: LOLO Charge | F109: IDR | G109: =1280000/G56 -> 330.57851 | H109: IDR | I109: =1280000/I56 -> 330.57851 | J109: IDR | K109: =1280000/K56 -> 330.57851 | L109: IDR | M109: =1280000/M56 -> 330.57851 | N109: IDR | O109: =1280000/O56 -> 320 | P109: IDR | Q109: =1280000/Q56 -> 320 | R109: IDR | S109: =1280000/S56 -> 320 | T109: IDR | U109: =1280000/U56 -> 320 | V109: IDR | W109: =1280000/W56 -> 360.56338 | X109: IDR | Y109: =1280000/Y56 -> 360.56338 | Z109: IDR | AA109: =1280000/AA56 -> 360.56338 | AB109: IDR | AC109: =1280000/AC56 -> 360.56338
C110: Document Charge (HC & Veterinary Certificate) | F110: IDR | G110: =225000/G56 -> 58.109504 | H110: IDR | I110: =225000/I56 -> 58.109504 | J110: IDR | K110: =225000/K56 -> 58.109504 | L110: IDR | M110: =225000/M56 -> 58.109504 | N110: IDR | O110: =225000/O56 -> 56.25 | P110: IDR | Q110: =225000/Q56 -> 56.25 | R110: IDR | S110: =225000/S56 -> 56.25 | T110: IDR | U110: =225000/U56 -> 56.25 | V110: IDR | W110: =225000/W56 -> 63.380282 | X110: IDR | Y110: =225000/Y56 -> 63.380282 | Z110: IDR | AA110: =225000/AA56 -> 63.380282 | AB110: IDR | AC110: =225000/AC56 -> 63.380282
C111: THC & Doc Seal Charge | F111: IDR | G111: =(175*G68)/G56 -> 632.74793 | H111: IDR | I111: =(175*I68)/I56 -> 632.74793 | J111: IDR | K111: =(175*K68)/K56 -> 632.74793 | L111: IDR | M111: =(175*M68)/M56 -> 632.74793 | N111: IDR | O111: =(175*O68)/O56 -> 612.5 | P111: IDR | Q111: =(175*Q68)/Q56 -> 612.5 | R111: IDR | S111: =(175*S68)/S56 -> 612.5 | T111: IDR | U111: =(175*U68)/U56 -> 612.5 | V111: IDR | W111: =(175*W68)/W56 -> 690.14085 | X111: IDR | Y111: =(175*Y68)/Y56 -> 690.14085 | Z111: IDR | AA111: =(175*AA68)/AA56 -> 690.14085 | AB111: IDR | AC111: =(175*AC68)/AC56 -> 690.14085
C113: Sales Volume 2020 | E113: packs | G113: 33580560 | I113: =G113 -> 33580560 | K113: =I113 -> 33580560 | M113: =K113 -> 33580560 | O113: 8114880 | Q113: =O113 -> 8114880 | S113: =Q113 -> 8114880 | U113: =S113 -> 8114880 | W113: 11492280 | Y113: =W113 -> 11492280 | AA113: =Y113 -> 11492280 | AC113: =AA113 -> 11492280
C114: Sales Volume 2021 | E114: packs | G114: 44153968 | I114: =G114 -> 44153968 | K114: =I114 -> 44153968 | M114: =K114 -> 44153968 | O114: 10000000 | Q114: =O114 -> 10000000 | S114: =Q114 -> 10000000 | U114: =S114 -> 10000000 | W114: 23655905 | Y114: =W114 -> 23655905 | AA114: =Y114 -> 23655905 | AC114: =AA114 -> 23655905
E115: ctn | G115: =G114/40 -> 1103849.2 | I115: =I114/40 -> 1103849.2 | K115: =K114/40 -> 1103849.2 | M115: =M114/40 -> 1103849.2 | O115: =O114/40 -> 250000 | Q115: =Q114/40 -> 250000 | S115: =S114/40 -> 250000 | U115: =U114/40 -> 250000 | W115: =W114/40 -> 591397.62 | Y115: =Y114/40 -> 591397.62 | AA115: =AA114/40 -> 591397.62 | AC115: =AC114/40 -> 591397.62
E116: 40'HC | G116: =G115/G56 -> 285.08502 | I116: =I115/I56 -> 285.08502 | K116: =K115/K56 -> 285.08502 | M116: =M115/M56 -> 285.08502 | O116: =O115/O56 -> 62.5 | Q116: =Q115/Q56 -> 62.5 | S116: =S115/S56 -> 62.5 | U116: =U115/U56 -> 62.5 | W116: =W115/W56 -> 166.59088 | Y116: =Y115/Y56 -> 166.59088 | AA116: =AA115/AA56 -> 166.59088 | AC116: =AC115/AC56 -> 166.59088
C118: OF in Pricing Structure | E118: in USD | G118: =G54 -> 620 | I118: =I54 -> 620 | K118: =K54 -> 620 | M118: =M54 -> 620 | O118: =O54 -> 620 | Q118: =Q54 -> 620 | S118: =S54 -> 620 | U118: =U54 -> 620 | W118: =W54 -> 620 | Y118: =Y54 -> 620 | AA118: =AA54 -> 620 | AC118: =AC54 -> 620
C119: OF in Jan-21 | E119: in USD | G119: 1150 | I119: =G119 -> 1150 | K119: =I119 -> 1150 | M119: =K119 -> 1150 | O119: 1150 | Q119: =O119 -> 1150 | S119: =Q119 -> 1150 | U119: =S119 -> 1150 | W119: 1150 | Y119: =W119 -> 1150 | AA119: =Y119 -> 1150 | AC119: =AA119 -> 1150
C120: OF in Jan-20 | G120: 750 | I120: =G120 -> 750 | K120: =I120 -> 750 | M120: =K120 -> 750 | O120: 750 | Q120: =O120 -> 750 | S120: =Q120 -> 750 | U120: =S120 -> 750 | W120: 750 | Y120: =W120 -> 750 | AA120: =Y120 -> 750 | AC120: =AA120 -> 750
C122: Difference OF | E122: in 40'HC | G122: =G119-G118 -> 530 | I122: =I119-I118 -> 530 | K122: =K119-K118 -> 530 | M122: =M119-M118 -> 530 | O122: =O119-O118 -> 530 | Q122: =Q119-Q118 -> 530 | S122: =S119-S118 -> 530 | U122: =U119-U118 -> 530 | W122: =W119-W118 -> 530 | Y122: =Y119-Y118 -> 530 | AA122: =AA119-AA118 -> 530 | AC122: =AC119-AC118 -> 530
...

Sheet All SKU Pricing Structure
B2: PRICING STRUCTURE | F2: =F3 -> GSS LOKAL 40 | H2: =H3 -> IIP LOKAL 40 | J2: =J3 -> IHAG LOKAL 40 | L2: =L3 -> GPD LOKAL 40 | N2: =N3 -> CGSS MA 12 | P2: =P3 -> PMAD LOKAL 12 | R2: =R3 -> PMAJ LOKAL 24
F3: GSS LOKAL 40 | H3: IIP LOKAL 40 | J3: IHAG LOKAL 40 | L3: GPD LOKAL 40 | N3: CGSS MA 12 | P3: PMAD LOKAL 12 | R3: PMAJ LOKAL 24
B5: General Info | C5: Type
C6: Flavour Matcode | F6: 100493 | H6: 141884 | J6: 199660 | L6: 100491 | N6: 123630 | P6: 184763 | R6: 136915
C7: CIF | F7: =G51 -> 5.6 | H7: =I51 -> 5.6 | J7: =K51 -> 5.6 | L7: =M51 -> 5.6 | N7: =O51 -> 4.6 | P7: =Q51 -> 4.25 | R7: =S51 -> 6.3
C8: Disc | F8: TP $0.40/ctn | H8: TP $0.40/ctn | J8: TP $0.40/ctn | L8: TP $0.40/ctn | N8: TP $0.90/ctn | P8: TP $0.90/ctn | R8: TP $1.80/ctn
C9: Content | F9: =RIGHT(F2,2) -> 40 | G9: =+F9 -> 40 | H9: =RIGHT(H2,2) -> 40 | I9: =+H9 -> 40 | J9: =RIGHT(J2,2) -> 40 | K9: =+J9 -> 40 | L9: =RIGHT(L2,2) -> 40 | M9: =+L9 -> 40 | N9: =RIGHT(N2,2) -> 12 | O9: =+N9 -> 12 | P9: =RIGHT(P2,2) -> 12 | Q9: =+P9 -> 12 | R9: =RIGHT(R2,2) -> 24 | S9: =+R9 -> 24
C10: Currency | F10: KHR | G10: USD | H10: KHR | I10: USD | J10: KHR | K10: USD | L10: KHR | M10: USD | N10: KHR | O10: USD | P10: KHR | Q10: USD | R10: KHR | S10: USD
C11: Exchange rate per- | D11: 44407 | F11: 4068.66 | H11: 4068.66 | J11: 4068.66 | L11: 4068.66 | N11: 4068.66 | P11: 4068.66 | R11: 4068.66
B14: Consumer | C14: CBP with VAT - per pack | F14: 1000 | G14: =+F14/F11 -> 0.24578117 | H14: 1000 | I14: =+H14/H11 -> 0.24578117 | J14: 1000 | K14: =+J14/J11 -> 0.24578117 | L14: 1000 | M14: =+L14/L11 -> 0.24578117 | N14: 3250 | O14: =+N14/N11 -> 0.79878879 | P14: 2400 | Q14: =+P14/P11 -> 0.5898748 | R14: 2000 | S14: =+R14/R11 -> 0.49156233
C15: CBP with VAT - per carton | F15: =+F14*F9 -> 40000 | G15: =+G14*G9 -> 9.8312467 | H15: =+H14*H9 -> 40000 | I15: =+I14*I9 -> 9.8312467 | J15: =+J14*J9 -> 40000 | K15: =+K14*K9 -> 9.8312467 | L15: =+L14*L9 -> 40000 | M15: =+M14*M9 -> 9.8312467 | ... S15: =+S14*S9 -> 11.797496
C16: VAT | D16: - per pack | F16: 0 | G16: 0 | H16: 0 | I16: 0 | J16: 0 | K16: 0 | L16: 0 | M16: 0 | N16: 0 | O16: 0 | P16: 0 | Q16: 0 | R16: 0 | S16: 0
C17: VAT % | F17: 0 | G17: 0 | H17: 0 | I17: 0 | J17: 0 | K17: 0 | L17: 0 | M17: 0 | N17: 0 | O17: 0 | P17: 0 | Q17: 0 | R17: 0 | S17: 0
C18: CBP without VAT - per pack | F18: =F14-F16 -> 1000 | G18: =G14-G16 -> 0.24578117 | H18: =H14-H16 -> 1000 | I18: =I14-I16 -> 0.24578117 | J18: =J14-J16 -> 1000 | K18: =K14-K16 -> 0.24578117 | L18: =L14-L16 -> 1000 | M18: =M14-M16 -> 0.24578117 | ... S18: =S14-S16 -> 0.49156233
C19: CBP without VAT - per carton | F19: =1/(1+F17)*F15 -> 40000 | G19: =1/(1+G17)*G15 -> 9.8312467 | H19: =1/(1+H17)*H15 -> 40000 | I19: =1/(1+I17)*I15 -> 9.8312467 | J19: =1/(1+J17)*J15 -> 40000 | K19: =1/(1+K17)*K15 -> 9.8312467 | L19: =1/(1+L17)*L15 -> 40000 | M19: =1/(1+M17)*M15 -> 9.8312467 | ... S19: =1/(1+S17)*S15 -> 11.797496
B21: Retailer
C22: Retailers' margin (%) | F22: =F23/F19 -> 0.19 | G22: =G23/G19 -> 0.19 | H22: =H23/H19 -> 0.19 | I22: =I23/I19 -> 0.19 | J22: =J23/J19 -> 0.19 | K22: =K23/K19 -> 0.19 | L22: =L23/L19 -> 0.19 | M22: =M23/M19 -> 0.19 | ... S22: =S23/S19 -> 0.240625
C23: Retailers' margin | F23: =F19-F25 -> 7600 | G23: =G19-G25 -> 1.8679369 | H23: =H19-H25 -> 7600 | I23: =I19-I25 -> 1.8679369 | J23: =J19-J25 -> 7600 | K23: =K19-K25 -> 1.8679369 | L23: =L19-L25 -> 7600 | M23: =M19-M25 -> 1.8679369 | ... S23: =S19-S25 -> 2.8387725
C24: Retailers' Buying Price per carton +VAT | F24: =F25 -> 32400 | G24: =G25 -> 7.9633098 | H24: =H25 -> 32400 | I24: =I25 -> 7.9633098 | J24: =J25 -> 32400 | K24: =K25 -> 7.9633098 | L24: =L25 -> 32400 | M24: =M25 -> 7.9633098 | ... S24: =S25 -> 8.9587235
C25: Retailers' Buying Price (ctn) | F25: 32400 | G25: =+F25/F11 -> 7.9633098 | H25: 32400 | I25: =+H25/H11 -> 7.9633098 | J25: 32400 | K25: =+J25/J11 -> 7.9633098 | L25: 32400 | M25: =+L25/L11 -> 7.9633098 | N25: 25110 | O25: =+N25/N11 -> 6.1715651 | P25: 20400 | Q25: =+P25/P11 -> 5.0139358 | R25: 36450 | S25: =+R25/R11 -> 8.9587235
B27: Wholesaler
C28: Wholesalers' margin (%) | F28: =F29/F25 -> 0.071541433 | G28: =G29/G25 -> 0.071541433 | H28: =H29/H25 -> 0.071541433 | I28: =I29/I25 -> 0.071541433 | J28: =J29/J25 -> 0.071541433 | K28: =K29/K25 -> 0.071541433 | L28: =L29/L25 -> 0.071541433 | M28: =M29/M25 -> 0.071541433 | ... S28: =S29/S25 -> 0.082139918
C29: Wholesalers' margin | F29: =F25-F31 -> 2317.9424 | G29: =G25-G31 -> 0.5697066 | H29: =H25-H31 -> 2317.9424 | I29: =I25-I31 -> 0.5697066 | J29: =J25-J31 -> 2317.9424 | K29: =K25-K31 -> 0.5697066 | L29: =L25-L31 -> 2317.9424 | M29: =M25-M31 -> 0.5697066 | ... S29: =S25-S31 -> 0.73586881
C30: Wholesalers' Buying Price per carton +VAT | F30: =+F31 -> 30082.058 | G30: =G31 -> 7.3936032 | H30: =+H31 -> 30082.058 | I30: =I31 -> 7.3936032 | J30: =+J31 -> 30082.058 | K30: =K31 -> 7.3936032 | L30: =+L31 -> 30082.058 | M30: =M31 -> 7.3936032 | N30: =+N31 -> 24480 | O30: =O31 -> 6.016723 | P30: =+P31 -> 19380 | Q30: =Q31 -> 4.763239 | R30: =+R31 -> 33456 | S30: =S31 -> 8.2228547
C31: Wholesalers' Buying Price (ctn) | F31: 30082.058 | G31: =+F31/F11 -> 7.3936032 | H31: 30082.058 | I31: =+H31/H11 -> 7.3936032 | J31: 30082.058 | K31: =+J31/J11 -> 7.3936032 | L31: 30082.058 | M31: =+L31/L11 -> 7.3936032 | N31: 24480 | O31: =+N31/N11 -> 6.016723 | P31: 19380 | Q31: =+P31/P11 -> 4.763239 | R31: 33456 | S31: =+R31/R11 -> 8.2228547
B33: Distributor
C34: Distributors' margin (%) | F34: =+F35/F31 -> 0.12480074 | G34: =+G35/G31 -> 0.12480074 | H34: =+H35/H31 -> 0.12681276 | I34: =+I35/I31 -> 0.12681276 | J34: =+J35/J31 -> 0.11909767 | K34: =+K35/K31 -> 0.11909767 | L34: =+L35/L31 -> 0.12480074 | M34: =+M35/M31 -> 0.12480074 | ... S34: =+S35/S31 -> 0.27671104
C35: Distributors' margin | F35: =+F31-F36 -> 3754.2631 | G35: =+G31-G36 -> 0.92272716 | H35: =+H31-H36 -> 3814.7886 | I35: =+I31-I36 -> 0.93760319 | J35: =+J31-J36 -> 3582.7031 | K35: =+K31-K36 -> 0.88056094 | L35: =+L31-L36 -> 3754.2631 | M35: =+M31-M36 -> 0.92272716 | ... S35: =+S31-S36 -> 2.2753547
C36: Distributors' Buying Price | F36: =+G40*F11 -> 26327.794 | G36: =+G40 -> 6.470876 | H36: =+I40*H11 -> 26267.269 | I36: =+I40 -> 6.456 | J36: =+K40*J11 -> 26499.354 | K36: =+K40 -> 6.5130423 | L36: =+M40*L11 -> 26327.794 | M36: =+M40 -> 6.470876 | N36: =+O40*N11 -> 18869.926 | O36: =+O40 -> 4.6378725 | P36: =+Q40*P11 -> 17268.41 | Q36: =+Q40 -> 4.24425 | R36: =+S40*R11 -> 24198.355 | S36: =+S40 -> 5.9475
C37: Additional cost In Land trucking | F37: 0 | H37: 0 | J37: 0 | L37: 0 | N37: 0 | P37: 0 | R37: 0
B38: Importer / Distributor
C39: Landed Cost in pack | E39: USD | F39: =+F40/F9 -> 658.19486 | G39: =+G40/G9 -> 0.1617719 | H39: =+H40/H9 -> 656.68172 | I39: =+I40/I9 -> 0.1614 | J39: =+J40/J9 -> 662.48386 | K39: =+K40/K9 -> 0.16282606 | L39: =+L40/L9 -> 658.19486 | M39: =+M40/M9 -> 0.1617719 | ... S39: =+S40/S9 -> 0.2478125
C40: Landed Cost in carton | E40: USD | F40: =+G40*F11 -> 26327.794 | G40: =+G41+G43+G47+G45 -> 6.470876 | H40: =+I40*H11 -> 26267.269 | I40: =+I41+I43+I47+I45 -> 6.456 | J40: =+K40*J11 -> 26499.354 | K40: =+K41+K43+K47+K45 -> 6.5130423 | L40: =+M40*L11 -> 26327.794 | M40: =+M41+M43+M47+M45 -> 6.470876 | N40: =+O40*N11 -> 18869.926 | O40: =+O41+O43+O47+O45 -> 4.6378725 | P40: =+Q40*P11 -> 17268.41 | Q40: =+Q41+Q43+Q47+Q45 -> 4.24425 | R40: =+S40*R11 -> 24198.355 | S40: =+S41+S43+S47+S45 -> 5.9475
C41: Import duty rate - 5% | E41: USD | G41: =+G42*G47 -> 0.26 | I41: =+I42*I47 -> 0.26 | K41: =+K42*K47 -> 0.26 | M41: =+M42*M47 -> 0.26 | O41: =+O42*O47 -> 0.185 | Q41: =+Q42*Q47 -> 0.1675 | S41: =+S42*S47 -> 0.225
C42: Import duty % | G42: 0.05 | I42: 0.05 | K42: 0.05 | M42: 0.05 | O42: 0.05 | Q42: 0.05 | S42: 0.05
C43: Other charges - Clearance cost | E43: USD | G43: =$D$44/G56 -> 0.46487603 | I43: =$D$44/I56 -> 0.45 | K43: =$D$44/K56 -> 0.50704225 | M43: =$D$44/M56 -> 0.46487603 | O43: =$D$44/O56 -> 0.36437247 | Q43: =$D$44/Q56 -> 0.375 | S43: =$D$44/S56 -> 0.75
C44: Other charges % | D44: 1800 | G44: =G43/G47 -> 0.089399237 | I44: =I43/I47 -> 0.086538462 | K44: =K43/K47 -> 0.097508126 | M44: =M43/M47 -> 0.089399237 | O44: =O43/O47 -> 0.098479046 | Q44: =Q43/Q47 -> 0.1119403 | S44: =S43/S47 -> 0.16666667
C45: VAT in | G45: =(G46*(G47+G41)) -> 0.546 | I45: =(I46*(I47+I41)) -> 0.546 | K45: =(K46*(K47+K41)) -> 0.546 | M45: =(M46*(M47+M41)) -> 0.546 | O45: =(O46*(O47+O41)) -> 0.3885 | Q45: =(Q46*(Q47+Q41)) -> 0.35175 | S45: =(S46*(S47+S41)) -> 0.4725
C46: VAT in (% from CIF + Import duty) | G46: 0.1 | I46: 0.1 | K46: 0.1 | M46: 0.1 | O46: 0.1 | Q46: 0.1 | S46: 0.1
C47: CIF price after support & Freight Surcharge | E47: USD | G47: =G51-G48+G49 -> 5.2 | I47: =I51-I48+I49 -> 5.2 | K47: =K51-K48+K49 -> 5.2 | M47: =M51-M48+M49 -> 5.2 | O47: =O51-O48+O49 -> 3.7 | Q47: =Q51-Q48+Q49 -> 3.35 | S47: =S51-S48+S49 -> 4.5
C48: PROMO SUPPORT | E48: =+E47 -> USD | G48: 0.4 | I48: 0.4 | K48: 0.4 | M48: 0.4 | O48: 0.9 | Q48: 0.9 | S48: 1.8
C49: FREIGHT SURCHARGE | E49: =+E48 -> USD | G49: 0 | I49: 0 | K49: 0 | M49: 0 | O49: 0 | Q49: 0 | S49: 0
C50: FOB + FREIGHT + INSURANCE | E50: USD | G50: =+G53+G55+G57 -> 5.60308 | I50: =+I53+I55+I57 -> 5.60308 | K50: =+K53+K55+K57 -> 5.60308 | M50: =+M53+M55+M57 -> 5.60308 | O50: =+O53+O55+O57 -> 4.60253 | Q50: =+Q53+Q55+Q57 -> 4.2523375 | S50: =+S53+S55+S57 -> 6.303465
C51: CIF price | E51: USD | G51: 5.6 | I51: 5.6 | K51: 5.6 | M51: 5.6 | O51: 4.6 | Q51: 4.25 | S51: 6.3
C52: COST :
C53: Insurance | E53: per carton USD | G53: =0.055/100*(G57+(G54/G56)) -> 0.00308 | I53: =0.055/100*(I57+(I54/I56)) -> 0.00308 | K53: =0.055/100*(K57+(K54/K56)) -> 0.00308 | M53: =0.055/100*(M57+(M54/M56)) -> 0.00308 | O53: =0.055/100*(O57+(O54/O56)) -> 0.00253 | Q53: =0.055/100*(Q57+(Q54/Q56)) -> 0.0023375 | S53: =0.055/100*(S57+(S54/S56)) -> 0.003465
C54: Freight cost | D54: - 40 HI-CUBE | G54: 1150 | I54: 1150 | K54: 1150 | M54: 1150 | O54: 1150 | Q54: 1150 | S54: 1150
C55: =+C54 -> Freight cost | E55: =+E53 -> per carton USD | G55: =+G54/G56 -> 0.29700413 | I55: =+I54/I56 -> 0.2875 | K55: =+K54/K56 -> 0.32394366 | M55: =+M54/M56 -> 0.29700413 | O55: =+O54/O56 -> 0.23279352 | Q55: =+Q54/Q56 -> 0.23958333 | S55: =+S54/S56 -> 0.47916667
C56: Container load | E56: per carton USD | G56: 3872 | I56: 4000 | K56: 3550 | M56: 3872 | O56: 4940 | Q56: 4800 | S56: 2400
C57: FOB-JKT | E57: per carton USD | G57: =G51-G55 -> 5.3029959 | I57: =I51-I55 -> 5.3125 | K57: =K51-K55 -> 5.2760563 | M57: =M51-M55 -> 5.3029959 | O57: =O51-O55 -> 4.3672065 | Q57: =Q51-Q55 -> 4.0104167 | S57: =S51-S55 -> 5.8208333
C58: FOB-JKT after disc | E58: per carton USD | G58: =G47-G55 -> 4.9029959 | I58: =I47-I55 -> 4.9125 | K58: =K47-K55 -> 4.8760563 | M58: =M47-M55 -> 4.9029959 | O58: =O47-O55 -> 3.4672065 | Q58: =Q47-Q55 -> 3.1104167 | S58: =S47-S55 -> 4.0208333
E59: per pack USD | G59: =+G57/G9 -> 0.1325749 | I59: =+I57/I9 -> 0.1328125 | K59: =+K57/K9 -> 0.13190141 | M59: =+M57/M9 -> 0.1325749 | O59: =+O57/O9 -> 0.36393387 | Q59: =+Q57/Q9 -> 0.33420139 | S59: =+S57/S9 -> 0.24253472
B61: Producer | C61: COGS after VSE | E61: per carton USD | G61: =G64+G62 -> 3.7179873 | I61: =I64+I62 -> 4.1643804 | K61: =K64+K62 -> 4.7782112 | M61: =M64+M62 -> 3.8179873 | O61: =O64+O62 -> 2.5436187 | Q61: =Q64+Q62 -> 2.5461955 | S61: =S64+S62 -> 3.7371201
C62: VSE | E62: per carton USD | G62: =G105 -> 0.11798733 | I62: =I105 -> 0.1143804 | K62: =K105 -> 0.12821118 | M62: =M105 -> 0.11798733 | O62: =O105 -> 0.09361868 | Q62: =Q105 -> 0.09619549 | S62: =S105 -> 0.18712005
C64: COGS | E64: =+E57 -> per carton USD | G64: 3.6 | I64: 4.05 | K64: 4.65 | M64: 3.7 | O64: 2.45 | Q64: 2.45 | S64: 3.55
E65: =+E59 -> per pack USD | G65: =+G64/G9 -> 0.09 | I65: =+I64/I9 -> 0.10125 | K65: =+K64/K9 -> 0.11625 | M65: =+M64/M9 -> 0.0925 | O65: =+O64/O9 -> 0.20416667 | Q65: =+Q64/Q9 -> 0.20416667 | S65: =+S64/S9 -> 0.14791667
C66: COGS in ctn | E66: Rp. | G66: =G64*G69 -> 51224.4 | I66: =I64*I69 -> 57627.45 | K66: =K64*K69 -> 66164.85 | M66: =M64*M69 -> 52647.3 | O66: =O64*O69 -> 34861.05 | Q66: =Q64*Q69 -> 34861.05 | S66: =S64*S69 -> 50512.95
C67: COGS in pack | E67: Rp. | G67: =G66/G9 -> 1280.61 | I67: =I66/I9 -> 1440.6862 | K67: =K66/K9 -> 1654.1213 | M67: =M66/M9 -> 1316.1825 | O67: =O66/O9 -> 2905.0875 | Q67: =Q66/Q9 -> 2905.0875 | S67: =S66/S9 -> 2104.7062
C69: Exchange rate | E69: 1 USD = RP. | G69: 14229 | I69: =G69 -> 14229 | K69: =I69 -> 14229 | M69: =K69 -> 14229 | O69: =M69 -> 14229 | Q69: =O69 -> 14229 | S69: =Q69 -> 14229
C70: Margins from FOB | E70: =+E64 -> per carton USD | G70: =+G57-G64 -> 1.7029959 | I70: =+I57-I64 -> 1.2625 | K70: =+K57-K64 -> 0.62605634 | M70: =+M57-M64 -> 1.6029959 | O70: =+O57-O64 -> 1.9172065 | Q70: =+Q57-Q64 -> 1.5604167 | S70: =+S57-S64 -> 2.2708333
E71: =+E65 -> per pack USD | G71: =+G70/G9 -> 0.042574897 | I71: =+I70/I9 -> 0.0315625 | K71: =+K70/K9 -> 0.015651408 | M71: =+M70/M9 -> 0.040074897 | O71: =+O70/O9 -> 0.15976721 | Q71: =+Q70/Q9 -> 0.13003472 | S71: =+S70/S9 -> 0.094618056
C72: Margin % from FOB | G72: =+G70/G57 -> 0.32113845 | I72: =+I70/I57 -> 0.23764706 | K72: =+K70/K57 -> 0.1186599 | M72: =+M70/M57 -> 0.30228118 | O72: =+O70/O57 -> 0.43900065 | Q72: =+Q70/Q57 -> 0.38909091 | S72: =+S70/S57 -> 0.39012169
C73: Margins after Support | E73: =E70 -> per carton USD | G73: =G70-G48 -> 1.3029959 | I73: =I70-I48 -> 0.8625 | K73: =K70-K48 -> 0.22605634 | M73: =M70-M48 -> 1.2029959 | O73: =O70-O48 -> 1.0172065 | Q73: =Q70-Q48 -> 0.66041667 | S73: =S70-S48 -> 0.47083333
C74: Margin % after Support | G74: =G73/G57 -> 0.24570939 | I74: =I73/I57 -> 0.16235294 | K74: =K73/K57 -> 0.042845702 | M74: =M73/M57 -> 0.22685212 | O74: =O73/O57 -> 0.23291925 | Q74: =Q73/Q57 -> 0.16467532 | S74: =S73/S57 -> 0.080887616
C76: Margin after Support + VSE | E76: =E73 -> per carton USD | G76: =G73-G62 -> 1.1850085 | I76: =I73-I62 -> 0.7481196 | K76: =K73-K62 -> 0.097845157 | M76: =M73-M62 -> 1.0850085 | O76: =O73-O62 -> 0.9235878 | Q76: =Q73-Q62 -> 0.56422118 | S76: =S73-S62 -> 0.28371328
C77: Margin % after Support + VSE | G77: =G76/G57 -> 0.2234602 | I77: =I76/I57 -> 0.14082251 | K77: =K76/K57 -> 0.018545131 | M77: =M76/M57 -> 0.20460294 | O77: =O76/O57 -> 0.21148251 | Q77: =Q76/Q57 -> 0.14068892 | S77: =S76/S57 -> 0.048741007
C79: Margin after Support + VSE + Prepayment | E79: =E76 -> per carton USD | G79: =G76 -> 1.1850085 | I79: =I76 -> 0.7481196 | K79: =K76 -> 0.097845157 | M79: =M76 -> 1.0850085 | O79: =O76 -> 0.9235878 | Q79: =Q76 -> 0.56422118 | S79: =S76 -> 0.28371328
C80: Margin % after Support + VSE + Prepayment | G80: =G79/G57 -> 0.2234602 | I80: =I79/I57 -> 0.14082251 | K80: =K79/K57 -> 0.018545131 | M80: =M79/M57 -> 0.20460294 | O80: =O79/O57 -> 0.21148251 | Q80: =Q79/Q57 -> 0.14068892 | S80: =S79/S57 -> 0.048741007
C82: Marketing | E82: per carton USD | G82: 0.25 | I82: 0.25 | K82: 0 | M82: 0 | O82: 0 | Q82: 0 | S82: 0
C83: Margin after Support + VSE + Prepayment + Marketing | E83: per carton USD | G83: =G79-G82 -> 0.93500854 | I83: =I79-I82 -> 0.4981196 | K83: =K79-K82 -> 0.097845157 | M83: =M79-M82 -> 1.0850085 | O83: =O79-O82 -> 0.9235878 | Q83: =Q79-Q82 -> 0.56422118 | S83: =S79-S82 -> 0.28371328
C84: Margin % after Support + VSE + Prepayment + Marketing | G84: =G83/G57 -> 0.17631704 | I84: =I83/I57 -> 0.093763689 | K84: =K83/K57 -> 0.018545131 | M84: =M83/M57 -> 0.20460294 | O84: =O83/O57 -> 0.21148251 | Q84: =Q83/Q57 -> 0.14068892 | S84: =S83/S57 -> 0.048741007
C86: OF Difference | G86: =(G121-G120)/G56 -> 0 | I86: =(I121-I120)/I56 -> 0 | K86: =(K121-K120)/K56 -> 0 | M86: =(M121-M120)/M56 -> 0 | O86: =(O121-O120)/O56 -> 0 | Q86: =(Q121-Q120)/Q56 -> 0 | S86: =(S121-S120)/S56 -> 0
C88: GP after OF Difference | E88: per carton USD | G88: =G83-G86 -> 0.93500854 | I88: =I83-I86 -> 0.4981196 | K88: =K83-K86 -> 0.097845157 | M88: =M83-M86 -> 1.0850085 | O88: =O83-O86 -> 0.9235878 | Q88: =Q83-Q86 -> 0.56422118 | S88: =S83-S86 -> 0.28371328
C89: % GP after OF Difference | G89: =G88/G57 -> 0.17631704 | I89: =I88/I57 -> 0.093763689 | K89: =K88/K57 -> 0.018545131 | M89: =M88/M57 -> 0.20460294 | O89: =O88/O57 -> 0.21148251 | Q89: =Q88/Q57 -> 0.14068892 | S89: =S88/S57 -> 0.048741007
B90: Freight Difference | C90: Freight in Pricing Structure | E90: USD/40HC | G90: 620 | I90: 620 | K90: 620 | M90: 620 | O90: 620 | Q90: 620 | S90: 620
C91: Freight in Jun-21 | E91: USD/40HC | G91: 1150 | I91: 1150 | K91: 1150 | M91: 1150 | O91: 1150 | Q91: 1150 | S91: 1150
C92: Freight in Jan-20 | E92: USD/40HC | G92: 750 | I92: 750 | K92: 750 | M92: 750 | O92: 750 | Q92: 750 | S92: 750
C94: Difference per 40HC | E94: USD/40HC | G94: =G91-G90 -> 530 | I94: =I91-I90 -> 530 | K94: =K91-K90 -> 530 | M94: =M91-M90 -> 530 | O94: =O91-O90 -> 530 | Q94: =Q91-Q90 -> 530 | S94: =S91-S90 -> 530
C95: Difference per ctn (Jan-21) | E95: USD/ctn | G95: =G94/G56 -> 0.13688017 | I95: =I94/I56 -> 0.1325 | K95: =K94/K56 -> 0.14929577 | M95: =M94/M56 -> 0.13688017 | O95: =O94/O56 -> 0.10728745 | Q95: =Q94/Q56 -> 0.11041667 | S95: =S94/S56 -> 0.22083333
C96: Difference per ctn (Jan-20) | E96: USD/ctn | G96: =(G91-G92)/G56 -> 0.10330579 | I96: =(I91-I92)/I56 -> 0.1 | K96: =(K91-K92)/K56 -> 0.11267606 | M96: =(M91-M92)/M56 -> 0.10330579 | O96: =(O91-O92)/O56 -> 0.08097166 | Q96: =(Q91-Q92)/Q56 -> 0.083333333 | S96: =(S91-S92)/S56 -> 0.16666667
C98: GP After Freight Difference (Jan-21) | G98: =G51-(G91/G56)-G64 -> 1.7029959 | I98: =I51-(I91/I56)-I64 -> 1.2625 | K98: =K51-(K91/K56)-K64 -> 0.62605634 | M98: =M51-(M91/M56)-M64 -> 1.6029959 | O98: =O51-(O91/O56)-O64 -> 1.9172065 | Q98: =Q51-(Q91/Q56)-Q64 -> 1.5604167 | S98: =S51-(S91/S56)-S64 -> 2.2708333
C99: Margin % after Freight Difference (Jan-21) | G99: =G98/G57 -> 0.32113845 | I99: =I98/I57 -> 0.23764706 | K99: =K98/K57 -> 0.1186599 | M99: =M98/M57 -> 0.30228118 | O99: =O98/O57 -> 0.43900065 | Q99: =Q98/Q57 -> 0.38909091 | S99: =S98/S57 -> 0.39012169
C101: GP After Freight Difference (Jan-20) | G101: =G51-(G92/G56)-G64 -> 1.8063017 | I101: =I51-(I92/I56)-I64 -> 1.3625 | K101: =K51-(K92/K56)-K64 -> 0.73873239 | M101: =M51-(M92/M56)-M64 -> 1.7063017 | O101: =O51-(O92/O56)-O64 -> 1.9981781 | Q101: =Q51-(Q92/Q56)-Q64 -> 1.64375 | S101: =S51-(S92/S56)-S64 -> 2.4375
C102: Margin % after Freight Difference (Jan-20) | G102: =G101/G57 -> 0.34061909 | I102: =I101/I57 -> 0.25647059 | K102: =K101/K57 -> 0.14001602 | M102: =M101/M57 -> 0.32176183 | O102: =O101/O57 -> 0.45754149 | Q102: =Q101/Q57 -> 0.40987013 | S102: =S101/S57 -> 0.41875447
C104: VSE in $/container | F104: $ | G104: =G106/G69 -> 456.84693 | H104: $ | I104: =I106/I69 -> 457.52161 | J104: $ | K104: =K106/K69 -> 455.14969 | L104: $ | M104: =M106/M69 -> 456.84693 | N104: $ | O104: =O106/O69 -> 462.47628 | P104: $ | Q104: =Q106/Q69 -> 461.73835 | R104: $ | S104: =S106/S69 -> 449.08813
C105: VSE in $/carton | F105: $ | G105: =G104/G56 -> 0.11798733 | H105: $ | I105: =I104/I56 -> 0.1143804 | J105: $ | K105: =K104/K56 -> 0.12821118 | L105: $ | M105: =M104/M56 -> 0.11798733 | N105: $ | O105: =O104/O56 -> 0.09361868 | P105: $ | Q105: =Q104/Q56 -> 0.09619549 | R105: $ | S105: =S104/S56 -> 0.18712005
C106: VSE in IDR/container | F106: IDR | G106: =G107*G56 -> 6500475 | H106: IDR | I106: =I107*I56 -> 6510075 | J106: IDR | K106: =K107*K56 -> 6476325 | L106: IDR | M106: =M107*M56 -> 6500475 | N106: IDR | O106: =O107*O56 -> 6580575 | P106: IDR | Q106: =Q107*Q56 -> 6570075 | R106: IDR | S106: =S107*S56 -> 6390075
C107: VSE in IDR/carton | F107: IDR | G107: =SUM(G108:G113) -> 1678.8417 | H107: IDR | I107: =SUM(I108:I113) -> 1627.5187 | J107: IDR | K107: =SUM(K108:K113) -> 1824.3169 | L107: IDR | M107: =SUM(M108:M113) -> 1678.8417 | N107: IDR | O107: =SUM(O108:O113) -> 1332.1002 | P107: IDR | Q107: =SUM(Q108:Q113) -> 1368.7656 | R107: IDR | S107: =SUM(S108:S113) -> 2662.5312
C108: Labor Cost | F108: IDR | G108: 75 | H108: IDR | I108: 75 | J108: IDR | K108: 75 | L108: IDR | M108: 75 | N108: IDR | O108: 75 | P108: IDR | Q108: 75 | R108: IDR | S108: 75
C109: Trucking Cost | F109: IDR | G109: =1940000/G56 -> 501.03306 | H109: IDR | I109: =1940000/I56 -> 485 | J109: IDR | K109: =1940000/K56 -> 546.47887 | L109: IDR | M109: =1940000/M56 -> 501.03306 | N109: IDR | O109: =1940000/O56 -> 392.71255 | P109: IDR | Q109: =1940000/Q56 -> 404.16667 | R109: IDR | S109: =1940000/S56 -> 808.33333
C110: Custom Charge | F110: IDR | G110: =275000/G56 -> 71.022727 | H110: IDR | I110: =275000/I56 -> 68.75 | J110: IDR | K110: =275000/K56 -> 77.464789 | L110: IDR | M110: =275000/M56 -> 71.022727 | N110: IDR | O110: =275000/O56 -> 55.668016 | P110: IDR | Q110: =275000/Q56 -> 57.291667 | R110: IDR | S110: =275000/S56 -> 114.58333
C111: LOLO Charge | F111: IDR | G111: =1280000/G56 -> 330.57851 | H111: IDR | I111: =1280000/I56 -> 320 | J111: IDR | K111: =1280000/K56 -> 360.56338 | L111: IDR | M111: =1280000/M56 -> 330.57851 | N111: IDR | O111: =1280000/O56 -> 259.10931 | P111: IDR | Q111: =1280000/Q56 -> 266.66667 | R111: IDR | S111: =1280000/S56 -> 533.33333
C112: Document Charge (HC & Veterinary Certificate) | F112: IDR | G112: =225000/G56 -> 58.109504 | H112: IDR | I112: =225000/I56 -> 56.25 | J112: IDR | K112: =225000/K56 -> 63.380282 | L112: IDR | M112: =225000/M56 -> 58.109504 | N112: IDR | O112: =225000/O56 -> 45.546559 | P112: IDR | Q112: =225000/Q56 -> 46.875 | R112: IDR | S112: =225000/S56 -> 93.75
C113: THC & Doc Seal Charge | F113: IDR | G113: =(175*G69)/G56 -> 643.09788 | H113: IDR | I113: =(175*I69)/I56 -> 622.51875 | J113: IDR | K113: =(175*K69)/K56 -> 701.42958 | L113: IDR | M113: =(175*M69)/M56 -> 643.09788 | N113: IDR | O113: =(175*O69)/O56 -> 504.06377 | P113: IDR | Q113: =(175*Q69)/Q56 -> 518.76562 | R113: IDR | S113: =(175*S69)/S56 -> 1037.5312
C115: Sales Volume 2020 | E115: packs | G115: 33580560 | I115: 8114880 | K115: 11492280 | M115: 429560 | O115: 154272 | Q115: 291156 | S115: 271128
C116: Sales Volume 2021 | E116: packs | G116: 44498720 | I116: 12851920 | K116: 33398120 | M116: 426920 | O116: 192132 | Q116: 413556 | S116: 293304
E117: ctn | G117: =G116/G9 -> 1112468 | I117: =I116/I9 -> 321298 | K117: =K116/K9 -> 834953 | M117: =M116/M9 -> 10673 | O117: =O116/O9 -> 16011 | Q117: =Q116/Q9 -> 34463 | S117: =S116/S9 -> 12221
E118: 40'HC | G118: =G117/G56 -> 287.31095 | I118: =I117/I56 -> 80.3245 | K118: =K117/K56 -> 235.19803 | M118: =M117/M56 -> 2.7564566 | O118: =O117/O56 -> 3.2410931 | Q118: =Q117/Q56 -> 7.1797917 | S118: =S117/S56 -> 5.0920833
C120: OF in Pricing Structure | E120: in USD | G120: =G54 -> 1150 | I120: =I54 -> 1150 | K120: =K54 -> 1150 | M120: =M54 -> 1150 | O120: =O54 -> 1150 | Q120: =Q54 -> 1150 | S120: =S54 -> 1150
C121: OF in Jun-21 | E121: in USD | G121: 1150 | I121: 1150 | K121: 1150 | M121: 1150 | O121: 1150 | Q121: 1150 | S121: 1150
...

Sheet P&L by Ctn
C1: CIF Incr | D1: =G12/E12-1 -> #REF! | E1: =G12-E12 -> #REF! | I1: CIF Incr | J1: =M12/K12-1 -> #REF! | K1: =M12-K12 -> #REF! | O1: CIF Incr | P1: =T12/Q12-1 -> #REF! | Q1: =T12-Q12 -> #REF!
C2: FOB Incr | D2: =G13/E13-1 -> #REF! | E2: =G13-E13 -> #REF! | I2: FOB Incr | J2: =M13/K13-1 -> #REF! | K2: =M13-K13 -> #REF! | O2: FOB Incr | P2: =T13/Q13-1 -> #REF! | Q2: =T13-Q13 -> #REF!
C3: Net CIF Incr | D3: =G19/E19-1 -> #REF! | E3: =G19-E19 -> #REF! | I3: Net CIF Incr | J3: =M19/K19-1 -> #REF! | K3: =M19-K19 -> #REF! | O3: Net CIF Incr | P3: =T19/Q19-1 -> #REF! | Q3: =T19-Q19 -> #REF!
C4: COGS Incr | D4: =G14/E14-1 -> #REF! | E4: =G14-E14 -> #REF! | I4: COGS Incr | J4: =M14/K14-1 -> #REF! | K4: =M14-K14 -> #REF! | O4: COGS Incr | P4: =T14/Q14-1 -> #REF! | Q4: =T14-Q14 -> #REF!
C5: GP4 (Excl MF) Incr | D5: =G31/E31-1 -> #REF! | E5: =G31-E31 -> #REF! | I5: GP4 (Excl MF) Incr | J5: =M31/K31-1 -> #REF! | K5: =M31-K31 -> #REF! | O5: GP4 (Excl MF) Incr | P5: =T31/Q31-1 -> #REF! | Q5: =T31-Q31 -> #REF!
C8: 1 | D8: 2 | E8: 3 | F8: 4 | G8: 5 | H8: 6 | I8: 7 | J8: 8 | K8: 9 | L8: 10 | M8: 11 | N8: 12 | O8: 13 | P8: 14 | Q8: 15 | R8: 16 | S8: 17 | T8: 18 | U8: 19 | V8: 20 | W8: 21 | X8: 22 | Y8: 23 | Z8: 24 | AA8: 25 | AB8: 26 | AC8: 27 | AD8: 28 | AE8: 29 | AF8: 30 | AG8: 31
F9: Scenario 3 | G9: Scenario +15%, 1100 | H9: Scenario +15%, 1200 | L9: =F9 -> Scenario 3 | M9: =G9 -> Scenario +15%, 1100 | N9: =H9 -> Scenario +15%, 1200 | R9: =L9 -> Scenario 3 | S9: Scenario 4 | T9: =M9 -> Scenario +15%, 1100 | U9: =N9 -> Scenario +15%, 1200 | X9: Freight 1500 | AA9: Freight 1500 | AD9: Freight 1500 | AG9: Freight 1500
C10: GSS LOKAL 40 | D10: GSS LOKAL 40 | E10: GSS LOKAL 40 | F10: GSS LOKAL 40 | G10: GSS LOKAL 40 | H10: GSS LOKAL 40 | I10: IIP LOKAL 40 | J10: IIP LOKAL 40 | K10: IIP LOKAL 40 | L10: IIP LOKAL 40 | M10: IIP LOKAL 40 | N10: IIP LOKAL 40 | O10: IHAG LOKAL 40 | P10: IHAG LOKAL 40 | Q10: IHAG LOKAL 40 | R10: IHAG LOKAL 40 | S10: IHAG LOKAL 40 | T10: IHAG LOKAL 40 | U10: IHAG LOKAL 40 | V10: GPD LOKAL 40 | W10: GPD LOKAL 40 | X10: GPD LOKAL 40 | Y10: PMAD LOKAL 12 | Z10: PMAD LOKAL 12 | AA10: PMAD LOKAL 12 | AB10: CGSS MA (NS) 12 | AC10: CGSS MA (NS) 12 | AD10: CGSS MA (NS) 12 | AE10: PMAJ LOKAL 24 | AF10: PMAJ LOKAL 24 | AG10: PMAJ LOKAL 24
C11: 2020 | D11: 2021 | E11: 2022 | F11: 2022 | G11: 2022 | H11: 2022 | I11: 2020 | J11: 2021 | K11: 2022 | L11: 2022 | M11: 2022 | N11: 2022 | O11: 2020 | P11: 2021 | Q11: 2022 | R11: 2022 | S11: 2022 | T11: 2022 | U11: 2022 | V11: 2021 | W11: 2022 | X11: 2022 | Y11: 2021 | Z11: 2022 | AA11: 2022 | AB11: 2021 | AC11: 2022 | AD11: 2022 | AE11: 2021 | AF11: 2022 | AG11: 2022
A12: 5 | B12: CIF | C12: ='Pricing Structure - All SKU'!G60 -> 5.6 | D12: ='Pricing Structure - All SKU'!I60 -> 5.6 | E12: ='Pricing Structure - All SKU'!K60 -> 6.0429664 | F12: ='Pricing Structure - GSS'!#REF! -> #REF! | G12: ='Pricing Structure - GSS'!#REF! -> #REF! | H12: ='Pricing Structure - GSS'!#REF! -> #REF! | I12: ='Pricing Structure - All SKU'!T60 -> 5.6 | J12: ='Pricing Structure - All SKU'!V60 -> 5.6 | K12: ='Pricing Structure - All SKU'!X60 -> 6.0375316 | L12: ='Pricing Structure - IIP'!#REF! -> #REF! | M12: ='Pricing Structure - IIP'!#REF! -> #REF! | N12: ='Pricing Structure - IIP'!#REF! -> #REF! | O12: ='Pricing Structure - All SKU'!AI60 -> 5.6 | P12: ='Pricing Structure - All SKU'!AK60 -> 5.6 | Q12: ='Pricing Structure - All SKU'!AM60 -> 6.0445945 | R12: ='Pricing Structure - IHAG'!#REF! -> #REF! | S12: ='Pricing Structure - IHAG'!#REF! -> #REF! | T12: ='Pricing Structure - IHAG'!#REF! -> #REF! | U12: ='Pricing Structure - IHAG'!#REF! -> #REF! | V12: ='Pricing Structure - All SKU'!AZ60 -> 5.6 | W12: ='Pricing Structure - All SKU'!BB60 -> 6.0499174 | X12: ='Pricing Structure - All SKU'!BH60 -> 6.0522124 | Y12: ='Pricing Structure - All SKU'!BT60 -> 4.38 | Z12: ='Pricing Structure - All SKU'!BV60 -> 4.38 | AA12: ='Pricing Structure - All SKU'!BZ60 -> 4.5522525 | AB12: ='Pricing Structure - All SKU'!BL60 -> 4.722915 | AC12: ='Pricing Structure - All SKU'!BN60 -> 4.722915 | AD12: ='Pricing Structure - All SKU'!BR60 -> 5.0501487 | AE12: ='Pricing Structure - All SKU'!CB60 -> 6.55 | AF12: ='Pricing Structure - All SKU'!CD60 -> 6.55 | AG12: ='Pricing Structure - All SKU'!CH60 -> 6.5520188
A13: 6 | B13: FOB | C13: ='Pricing Structure - All SKU'!G67 -> 5.439876 | D13: ='Pricing Structure - All SKU'!I67 -> 5.3029959 | E13: ='Pricing Structure - All SKU'!K67 -> 5.7331826 | F13: ='Pricing Structure - GSS'!#REF! -> #REF! | G13: ='Pricing Structure - GSS'!#REF! -> #REF! | H13: ='Pricing Structure - GSS'!#REF! -> #REF! | I13: ='Pricing Structure - All SKU'!T67 -> 5.4375 | J13: ='Pricing Structure - All SKU'!V67 -> 5.3125 | K13: ='Pricing Structure - All SKU'!X67 -> 5.7281473 | L13: ='Pricing Structure - IIP'!#REF! -> #REF! | M13: ='Pricing Structure - IIP'!#REF! -> #REF! | N13: ='Pricing Structure - IIP'!#REF! -> #REF! | O13: ='Pricing Structure - All SKU'!AI67 -> 5.3971831 | P13: ='Pricing Structure - All SKU'!AK67 -> 5.2760563 | Q13: ='Pricing Structure - All SKU'!AM67 -> 5.7048348 | R13: ='Pricing Structure - IHAG'!#REF! -> #REF! | S13: ='Pricing Structure - IHAG'!#REF! -> #REF! | T13: ='Pricing Structure - IHAG'!#REF! -> #REF! | U13: ='Pricing Structure - IHAG'!#REF! -> #REF! | V13: ='Pricing Structure - All SKU'!AZ67 -> 5.3029959 | W13: ='Pricing Structure - All SKU'!BB67 -> 5.74 | X13: ='Pricing Structure - All SKU'!BH67 -> 5.74 | Y13: ='Pricing Structure - All SKU'!BT67 -> 4.13 | Z13: ='Pricing Structure - All SKU'!BV67 -> 4.13 | AA13: ='Pricing Structure - All SKU'!BZ67 -> 4.3 | AB13: ='Pricing Structure - All SKU'!BL67 -> 4.48 | AC13: ='Pricing Structure - All SKU'!BN67 -> 4.48 | AD13: ='Pricing Structure - All SKU'!BR67 -> 4.8 | AE13: ='Pricing Structure - All SKU'!CB67 -> 6.05 | AF13: ='Pricing Structure - All SKU'!CD67 -> 6.05 | AG13: ='Pricing Structure - All SKU'!CH67 -> 6.05
A14: 7 | B14: COGS | C14: ='Pricing Structure - All SKU'!G74 -> 3.2951822 | D14: ='Pricing Structure - All SKU'!I74 -> 3.5328331 | E14: ='Pricing Structure - All SKU'!K74 -> 3.8637981 | F14: ='Pricing Structure - GSS'!#REF! -> #REF! | G14: ='Pricing Structure - GSS'!#REF! -> #REF! | H14: ='Pricing Structure - GSS'!#REF! -> #REF! | I14: ='Pricing Structure - All SKU'!T74 -> 3.7 | J14: ='Pricing Structure - All SKU'!V74 -> 3.9789363 | K14: ='Pricing Structure - All SKU'!X74 -> 4.2894638 | L14: ='Pricing Structure - IIP'!#REF! -> #REF! | M14: ='Pricing Structure - IIP'!#REF! -> #REF! | N14: ='Pricing Structure - IIP'!#REF! -> #REF! | O14: ='Pricing Structure - All SKU'!AI74 -> 4.4243786 | P14: ='Pricing Structure - All SKU'!AK74 -> 4.6419623 | Q14: ='Pricing Structure - All SKU'!AM74 -> 5.0750328 | R14: ='Pricing Structure - IHAG'!#REF! -> #REF! | S14: ='Pricing Structure - IHAG'!#REF! -> #REF! | T14: ='Pricing Structure - IHAG'!#REF! -> #REF! | U14: ='Pricing Structure - IHAG'!#REF! -> #REF! | V14: ='Pricing Structure - All SKU'!AZ74 -> 3.6780718 | W14: ='Pricing Structure - All SKU'!BB74 -> 3.8793987 | X14: ='Pricing Structure - All SKU'!BH74 -> 4.0540541 | Y14: ='Pricing Structure - All SKU'!BT74 -> 2.7993673 | Z14: ='Pricing Structure - All SKU'!BV74 -> 2.8488108 | AA14: ='Pricing Structure - All SKU'!BZ74 -> 3 | AB14: ='Pricing Structure - All SKU'!BL74 -> 2.5589374 | AC14: ='Pricing Structure - All SKU'!BN74 -> 2.6298189 | AD14: ='Pricing Structure - All SKU'!BR74 -> 2.8378378 | AE14: ='Pricing Structure - All SKU'!CB74 -> 4.2400614 | AF14: ='Pricing Structure - All SKU'!CD74 -> 3.9409356 | AG14: ='Pricing Structure - All SKU'!CH74 -> 4.2162162
A15: 8 | B15: GP1 | C15: =C13-C14 -> 2.1446938 | D15: =D13-D14 -> 1.7701627 | E15: =E13-E14 -> 1.8693845 | F15: =F13-F14 -> #REF! | G15: =G13-G14 -> #REF! | H15: =H13-H14 -> #REF! | I15: =I13-I14 -> 1.7375 | J15: =J13-J14 -> 1.3335637 | ... AG15: =AG13-AG14 -> 1.8337838
A16: 9 | B16: GP1% | C16: =C15/C$13 -> 0.39425417 | D16: =D15/D$13 -> 0.33380429 | E16: =E15/E$13 -> 0.32606401 | F16: =F15/F$13 -> #REF! | G16: =G15/G$13 -> #REF! | H16: =H15/H$13 -> #REF! | I16: =I15/I$13 -> 0.31954023 | J16: =J15/J$13 -> 0.25102376 | ... AG16: =AG15/AG$13 -> 0.30310476
A17: 10 | B17: TP | C17: ='Pricing Structure - All SKU'!G57 -> 0.5 | D17: ='Pricing Structure - All SKU'!I57 -> 0.42334055 | E17: ='Pricing Structure - All SKU'!K57 -> 0.79380235 | F17: ='Pricing Structure - GSS'!#REF! -> #REF! | G17: ='Pricing Structure - GSS'!#REF! -> #REF! | H17: ='Pricing Structure - GSS'!#REF! -> #REF! | I17: ='Pricing Structure - All SKU'!T57 -> 0.5 | J17: ='Pricing Structure - All SKU'!V57 -> 0.4 | K17: ='Pricing Structure - All SKU'!X57 -> 0.78897422 | L17: ='Pricing Structure - IIP'!#REF! -> #REF! | M17: ='Pricing Structure - IIP'!#REF! -> #REF! | N17: ='Pricing Structure - IIP'!#REF! -> #REF! | O17: ='Pricing Structure - All SKU'!AI57 -> 0.5 | P17: ='Pricing Structure - All SKU'!AK57 -> 0.41917048 | Q17: ='Pricing Structure - All SKU'!AM57 -> 0.64699696 | R17: ='Pricing Structure - IHAG'!#REF! -> #REF! | S17: ='Pricing Structure - IHAG'!#REF! -> #REF! | T17: ='Pricing Structure - IHAG'!#REF! -> #REF! | U17: ='Pricing Structure - IHAG'!#REF! -> #REF! | V17: ='Pricing Structure - All SKU'!AZ57 -> 0.4 | W17: ='Pricing Structure - All SKU'!BB57 -> 0.8 | X17: ='Pricing Structure - All SKU'!BH57 -> 0.8 | Y17: ='Pricing Structure - All SKU'!BT57 -> 1.03 | Z17: ='Pricing Structure - All SKU'!BV57 -> 1.03 | AA17: ='Pricing Structure - All SKU'!BZ57 -> 0.9 | AB17: ='Pricing Structure - All SKU'!BL57 -> 1.02 | AC17: ='Pricing Structure - All SKU'!BN57 -> 1.02 | AD17: ='Pricing Structure - All SKU'!BR57 -> 1 | AE17: ='Pricing Structure - All SKU'!CB57 -> 1.8 | AF17: ='Pricing Structure - All SKU'!CD57 -> 1.8 | AG17: ='Pricing Structure - All SKU'!CH57 -> 1.45
A18: 11 | B18: TP% | C18: =C17/C$13 -> 0.091913859 | D18: =D17/D13 -> 0.079830451 | E18: =E17/E13 -> 0.13845754 | F18: =F17/F$13 -> #REF! | G18: =G17/G$13 -> #REF! | H18: =H17/H$13 -> #REF! | I18: =I17/I13 -> 0.091954023 | J18: =J17/J13 -> 0.075294118 | K18: =K17/K13 -> 0.13773637 | L18: =L17/L$13 -> #REF! | M18: =M17/M$13 -> #REF! | N18: =N17/N$13 -> #REF! | O18: =O17/O13 -> 0.092640919 | P18: =P17/P13 -> 0.079447689 | Q18: =Q17/Q13 -> 0.11341204 | R18: =R17/R$13 -> #REF! | S18: =S17/S$13 -> #REF! | T18: =T17/T$13 -> #REF! | U18: =U17/U$13 -> #REF! | V18: =V17/V13 -> 0.075429061 | W18: =W17/W13 -> 0.13937282 | X18: =X17/X13 -> 0.13937282 | Y18: =Y17/Y13 -> 0.24939467 | Z18: =Z17/Z13 -> 0.24939467 | AA18: =AA17/AA13 -> 0.20930233 | AB18: =AB17/AB13 -> 0.22767857 | AC18: =AC17/AC13 -> 0.22767857 | ... AG18: =AG17/AG13 -> 0.23966942
A19: 12 | B19: CIF - TP | C19: =C12-C17 -> 5.1 | D19: =D12-D17 -> 5.1766594 | E19: =E12-E17 -> 5.2491641 | F19: =F12-F17 -> #REF! | G19: =G12-G17 -> #REF! | H19: =H12-H17 -> #REF! | I19: =I12-I17 -> 5.1 | J19: =J12-J17 -> 5.2 | ... AG19: =AG12-AG17 -> 5.1020188
A20: 13 | B20: MF | C20: ='Pricing Structure - All SKU'!G92 -> 1.0331208 | D20: ='Pricing Structure - All SKU'!I92 -> 0.82389229 | E20: ='Pricing Structure - All SKU'!K92 -> 0.8851129 | F20: ='Pricing Structure - GSS'!#REF! -> #REF! | G20: ='Pricing Structure - GSS'!#REF! -> #REF! | H20: ='Pricing Structure - GSS'!#REF! -> #REF! | I20: ='Pricing Structure - All SKU'!T92 -> 0.9 | J20: ='Pricing Structure - All SKU'!V92 -> 0.55 | K20: ='Pricing Structure - All SKU'!X92 -> 0.39456602 | L20: ='Pricing Structure - IIP'!#REF! -> #REF! | M20: ='Pricing Structure - IIP'!#REF! -> #REF! | N20: ='Pricing Structure - IIP'!#REF! -> #REF! | O20: ='Pricing Structure - All SKU'!AI92 -> 0 | P20: ='Pricing Structure - All SKU'!AK92 -> 0 | Q20: ='Pricing Structure - All SKU'!AM92 -> 0 | R20: ='Pricing Structure - IHAG'!#REF! -> #REF! | S20: ='Pricing Structure - IHAG'!#REF! -> #REF! | T20: ='Pricing Structure - IHAG'!#REF! -> #REF! | U20: ='Pricing Structure - IHAG'!#REF! -> #REF! | V20: 0 | W20: 0 | X20: 0 | Y20: 0 | Z20: 0 | AA20: 0 | AB20: 0 | AC20: 0 | AD20: 0 | AE20: 0 | AF20: 0 | AG20: 0
A21: 14 | B21: MF% | C21: =C20/C$13 -> 0.18991623 | D21: =D20/D15 -> 0.46543307 | E21: =E20/E15 -> 0.47347825 | F21: =F20/F$13 -> #REF! | G21: =G20/G$13 -> #REF! | H21: =H20/H$13 -> #REF! | I21: =I20/I15 -> 0.51798561 | J21: =J20/J15 -> 0.41242873 | K21: =K20/K15 -> 0.27425492 | L21: =L20/L$13 -> #REF! | M21: =M20/M$13 -> #REF! | N21: =N20/N$13 -> #REF! | O21: =O20/O15 -> 0 | P21: =P20/P15 -> 0 | Q21: =Q20/Q15 -> 0 | R21: =R20/R$13 -> #REF! | S21: =S20/S$13 -> #REF! | T21: =T20/T$13 -> #REF! | U21: =U20/U$13 -> #REF! | V21: =V20/V15 -> 0 | W21: =W20/W15 -> 0 | X21: =X20/X15 -> 0 | Y21: =Y20/Y15 -> 0 | Z21: =Z20/Z15 -> 0 | AA21: =AA20/AA15 -> 0 | AB21: =AB20/AB15 -> 0 | AC21: =AC20/AC15 -> 0 | ... AG21: =AG20/AG15 -> 0
A22: 15 | B22: VSE | C22: ='Pricing Structure - All SKU'!G72 -> 0.11589149 | D22: ='Pricing Structure - All SKU'!I72 -> 0.11746357 | E22: ='Pricing Structure - All SKU'!K72 -> 0.13716874 | F22: ='Pricing Structure - GSS'!#REF! -> #REF! | G22: ='Pricing Structure - GSS'!#REF! -> #REF! | H22: ='Pricing Structure - GSS'!#REF! -> #REF! | I22: ='Pricing Structure - All SKU'!T72 -> 0.11234678 | J22: ='Pricing Structure - All SKU'!V72 -> 0.11387219 | K22: ='Pricing Structure - All SKU'!X72 -> 0.10059002 | L22: ='Pricing Structure - IIP'!#REF! -> #REF! | M22: ='Pricing Structure - IIP'!#REF! -> #REF! | N22: ='Pricing Structure - IIP'!#REF! -> #REF! | O22: ='Pricing Structure - All SKU'!AI72 -> 0.12593901 | P22: ='Pricing Structure - All SKU'!AK72 -> 0.12764335 | Q22: ='Pricing Structure - All SKU'!AM72 -> 0.10951514 | R22: ='Pricing Structure - IHAG'!#REF! -> #REF! | S22: ='Pricing Structure - IHAG'!#REF! -> #REF! | T22: ='Pricing Structure - IHAG'!#REF! -> #REF! | U22: ='Pricing Structure - IHAG'!#REF! -> #REF! | V22: ='Pricing Structure - All SKU'!AZ72 -> 0.11589149 | W22: ='Pricing Structure - All SKU'!BB72 -> 0.11762592 | X22: ='Pricing Structure - All SKU'!BH72 -> 0.11517897 | Y22: ='Pricing Structure - All SKU'!BT72 -> 0.041738561 | Z22: ='Pricing Structure - All SKU'!BV72 -> 0.038391337 | AA22: ='Pricing Structure - All SKU'!BZ72 -> 0.038391337 | AB22: ='Pricing Structure - All SKU'!BL72 -> 0.040963349 | AC22: ='Pricing Structure - All SKU'!BN72 -> 0.036717558 | AD22: ='Pricing Structure - All SKU'!BR72 -> 0.036717558 | AE22: ='Pricing Structure - All SKU'!CB72 -> 0.082051204 | AF22: ='Pricing Structure - All SKU'!CD72 -> 0.082651304 | AG22: ='Pricing Structure - All SKU'!CH72 -> 0.082651304
A23: 16 | B23: GP2 | C23: =C15-C17-C20-C22 -> 0.49568157 | D23: =D15-D17-D20-D22 -> 0.40546634 | E23: =E15-E17-E20-E22 -> 0.053300503 | F23: =F15-F17-F20-F22 -> #REF! | G23: =G15-G17-G20-G22 -> #REF! | H23: =H15-H17-H20-H22 -> #REF! | I23: =I15-I17-I20-I22 -> 0.22515322 | J23: =J15-J17-J20-J22 -> 0.26969155 | ... AG23: =AG15-AG17-AG20-AG22 -> 0.30113248
A24: 17 | B24: GP2% | C24: =C23/C$13 -> 0.091120012 | D24: =D23/D$13 -> 0.076459864 | E24: =E23/E$13 -> 0.0092968438 | F24: =F23/F$13 -> #REF! | G24: =G23/G$13 -> #REF! | H24: =H23/H$13 -> #REF! | I24: =I23/I$13 -> 0.041407489 | J24: =J23/J$13 -> 0.050765469 | ... AG24: =AG23/AG$13 -> 0.049773964
A25: 18 | B25: A&P | C25: ='Pricing Structure - All SKU'!G78 -> 0 | D25: ='Pricing Structure - All SKU'!I78 -> 0 | E25: ='Pricing Structure - All SKU'!K78 -> 0 | F25: 0 | G25: 0 | H25: 0 | I25: ='Pricing Structure - All SKU'!T78 -> 0 | J25: ='Pricing Structure - All SKU'!V78 -> 0 | K25: ='Pricing Structure - All SKU'!X78 -> 0 | L25: 0 | M25: 0 | N25: 0 | O25: ='Pricing Structure - All SKU'!AI78 -> 0 | P25: ='Pricing Structure - All SKU'!AK78 -> 0 | Q25: ='Pricing Structure - All SKU'!AM78 -> 0 | R25: 0 | S25: 0 | T25: 0 | U25: 0 | V25: 0 | W25: 0 | X25: 0 | Y25: 0 | Z25: 0 | AA25: 0 | AB25: 0 | AC25: 0 | AD25: 0 | AE25: 0 | AF25: 0 | AG25: 0
A26: 19 | B26: GP3 | C26: =C23-C25 -> 0.49568157 | D26: =D23-D25 -> 0.40546634 | E26: =E23-E25 -> 0.053300503 | F26: =F23-F25 -> #REF! | G26: =G23-G25 -> #REF! | H26: =H23-H25 -> #REF! | I26: =I23-I25 -> 0.22515322 | J26: =J23-J25 -> 0.26969155 | ... AG26: =AG23-AG25 -> 0.30113248
A27: 20 | B27: GP3% | C27: =C26/C$13 -> 0.091120012 | D27: =D26/D$13 -> 0.076459864 | E27: =E26/E$13 -> 0.0092968438 | F27: =F26/F$13 -> #REF! | G27: =G26/G$13 -> #REF! | H27: =H26/H$13 -> #REF! | I27: =I26/I$13 -> 0.041407489 | J27: =J26/J$13 -> 0.050765469 | ... AG27: =AG26/AG$13 -> 0.049773964
A28: 21 | B28: Freight Difference | C28: ='Pricing Structure - All SKU'!G96 -> 0.14979339 | D28: ='Pricing Structure - All SKU'!I96 -> 0.012913223 | E28: ='Pricing Structure - All SKU'!K96 -> -0.0045096113 | F28: ='Pricing Structure - GSS'!#REF! -> #REF! | G28: ='Pricing Structure - GSS'!#REF! -> #REF! | H28: ='Pricing Structure - GSS'!#REF! -> #REF! | I28: ='Pricing Structure - All SKU'!T96 -> 0.13737078 | J28: ='Pricing Structure - All SKU'!V96 -> 0.012370779 | K28: ='Pricing Structure - All SKU'!X96 -> 0.027076247 | L28: ='Pricing Structure - IIP'!#REF! -> #REF! | M28: ='Pricing Structure - IIP'!#REF! -> #REF! | N28: ='Pricing Structure - IIP'!#REF! -> #REF! | O28: ='Pricing Structure - All SKU'!AI96 -> 0.16416203 | P28: ='Pricing Structure - All SKU'!AK96 -> 0.043035268 | Q28: ='Pricing Structure - All SKU'!AM96 -> -0.0089872836 | R28: ='Pricing Structure - IHAG'!#REF! -> #REF! | S28: ='Pricing Structure - IHAG'!#REF! -> #REF! | T28: ='Pricing Structure - IHAG'!#REF! -> #REF! | U28: ='Pricing Structure - IHAG'!#REF! -> #REF! | V28: ='Pricing Structure - All SKU'!AZ96 -> 0.0062609198 | W28: ='Pricing Structure - All SKU'!BB96 -> -0.0066523034 | X28: ='Pricing Structure - All SKU'!BH96 -> -0.077479339 | Y28: ='Pricing Structure - All SKU'!BT96 -> 0.040847469 | Z28: ='Pricing Structure - All SKU'!BV96 -> 0.008214092 | AA28: ='Pricing Structure - All SKU'!BZ96 -> -0.0625 | AB28: ='Pricing Structure - All SKU'!BL96 -> 0.022792124 | AC28: ='Pricing Structure - All SKU'!BN96 -> 0.026609261 | AD28: ='Pricing Structure - All SKU'!BR96 -> -0.060728745 | AE28: ='Pricing Structure - All SKU'!CB96 -> -0.16745423 | AF28: ='Pricing Structure - All SKU'!CD96 -> -0.23874774 | AG28: ='Pricing Structure - All SKU'!CH96 -> -0.125
A29: 22 | B29: GP4 | C29: =C26-C28 -> 0.34588818 | D29: =D26-D28 -> 0.39255312 | E29: =E26-E28 -> 0.057810114 | F29: =F26-F28 -> #REF! | G29: =G26-G28 -> #REF! | H29: =H26-H28 -> #REF! | I29: =I26-I28 -> 0.087782445 | J29: =J26-J28 -> 0.25732077 | ... AG29: =AG26-AG28 -> 0.42613248
A30: 23 | B30: GP4% | C30: =C29/C$13 -> 0.063583836 | D30: =D29/D$13 -> 0.074024783 | E30: =E29/E$13 -> 0.010083425 | F30: =F29/F$13 -> #REF! | G30: =G29/G$13 -> #REF! | H30: =H29/H$13 -> #REF! | I30: =I29/I$13 -> 0.016143898 | J30: =J29/J$13 -> 0.048436852 | ... AG30: =AG29/AG$13 -> 0.070435121
A31: 24 | B31: GP4 (Exclude MF) | C31: =C29+C20 -> 1.379009 | D31: =D29+D20 -> 1.2164454 | E31: =E29+E20 -> 0.94292302 | F31: =F29+F20 -> #REF! | G31: =G29+G20 -> #REF! | H31: =H29+H20 -> #REF! | I31: =I29+I20 -> 0.98778244 | J31: =J29+J20 -> 0.80732077 | ... AG31: =AG29+AG20 -> 0.42613248
A32: 25
A33: 26 | B33: Distributor Buying Value | C33: ='Pricing Structure - All SKU'!G45 -> 6.355376 | D33: ='Pricing Structure - All SKU'!I45 -> 6.4439177 | E33: ='Pricing Structure - GSS'!O45 -> 6.5251783 | F33: =F47 -> #REF! | G33: =G47 -> #REF! | H33: =H47 -> #REF! | I33: ='Pricing Structure - IIP'!G45 -> 6.3405 | J33: ='Pricing Structure - IIP'!I45 -> 6.456 | K33: ='Pricing Structure - IIP'!O45 -> 6.5214073 | L33: =L47 -> #REF! | M33: =M47 -> #REF! | N33: =N47 -> #REF! | O33: ='Pricing Structure - IHAG'!G45 -> 6.3975423 | P33: ='Pricing Structure - IHAG'!I45 -> 6.5130423 | Q33: ='Pricing Structure - IHAG'!O45 -> 6.7293686 | R33: =R47 -> #REF! | S33: =S47 -> #REF! | T33: =T47 -> #REF! | U33: =U47 -> #REF! | V33: ='Pricing Structure - All SKU'!AZ45 -> 6.470876 | W33: ='Pricing Structure - All SKU'!BB45 -> 6.5285306 | X33: ='Pricing Structure - All SKU'!BH45 -> 6.5311813 | Y33: ='Pricing Structure - All SKU'!BT45 -> 4.24425 | Z33: ='Pricing Structure - All SKU'!BV45 -> 4.24425 | AA33: ='Pricing Structure - All SKU'!BZ45 -> 4.5933516 | AB33: ='Pricing Structure - All SKU'!BL45 -> 4.6412393 | AC33: ='Pricing Structure - All SKU'!BN45 -> 4.6412393 | AD33: ='Pricing Structure - All SKU'!BR45 -> 5.0422943 | AE33: ='Pricing Structure - All SKU'!CB45 -> 6.23625 | AF33: ='Pricing Structure - All SKU'!CD45 -> 6.23625 | AG33: ='Pricing Structure - All SKU'!CH45 -> 6.6428317
A34: 27 | B34: Distributor Selling Value | C34: ='Pricing Structure - All SKU'!G32 -> 7.36 | D34: ='Pricing Structure - All SKU'!I32 -> 7.36 | E34: ='Pricing Structure - GSS'!O32 -> 7.3377472 | F34: =F48 -> #REF! | G34: =G48 -> #REF! | H34: =H48 -> #REF! | I34: ='Pricing Structure - IIP'!G32 -> 7.36 | J34: ='Pricing Structure - IIP'!I32 -> 7.36 | K34: ='Pricing Structure - IIP'!O32 -> 7.3377472 | L34: =L48 -> #REF! | M34: =M48 -> #REF! | N34: =N48 -> #REF! | O34: ='Pricing Structure - IHAG'!G32 -> 7.36 | P34: ='Pricing Structure - IHAG'!I32 -> 7.36 | Q34: ='Pricing Structure - IHAG'!O32 -> 7.3946099 | R34: =R48 -> #REF! | S34: =S48 -> #REF! | T34: =T48 -> #REF! | U34: =U48 -> #REF! | V34: ='Pricing Structure - All SKU'!AZ32 -> 7.36 | W34: ='Pricing Structure - All SKU'!BB32 -> 7.3394363 | X34: ='Pricing Structure - All SKU'!BH32 -> 7.3377472 | Y34: ='Pricing Structure - All SKU'!BT32 -> 4.3181818 | Z34: ='Pricing Structure - All SKU'!BV32 -> 4.3181818 | AA34: ='Pricing Structure - All SKU'!BZ32 -> 4.7272727 | AB34: ='Pricing Structure - All SKU'!BL32 -> 6.016723 | AC34: ='Pricing Structure - All SKU'!BN32 -> 6 | AD34: ='Pricing Structure - All SKU'!BR32 -> 6.1 | AE34: ='Pricing Structure - All SKU'!CB32 -> 8.2228547 | AF34: ='Pricing Structure - All SKU'!CD32 -> 7.2888889 | AG34: ='Pricing Structure - All SKU'!CH32 -> 7.9111111
A35: 28 | B35: Distributor Margin | C35: =C34-C$33-'Pricing Structure - All SKU'!G41 -> 0.87103306 | D35: =D34-D$33-'Pricing Structure - All SKU'!I41 -> 0.79054064 | E35: =E34-E$33-'Pricing Structure - GSS'!O41 -> 0.69643753 | F35: =F49 -> #REF! | G35: =G49 -> #REF! | H35: =H49 -> #REF! | I35: =I34-I$33-'Pricing Structure - IIP'!G41 -> 0.88590909 | J35: =J34-J$33-'Pricing Structure - IIP'!I41 -> 0.78090909 | K35: =K34-K$33-'Pricing Structure - IIP'!O41 -> 0.6998657 | L35: =L49 -> #REF! | M35: =M49 -> #REF! | N35: =N49 -> #REF! | O35: =O34-O$33-'Pricing Structure - IHAG'!G41 -> 0.82886684 | P35: =P34-P$33-'Pricing Structure - IHAG'!I41 -> 0.72386684 | Q35: =Q34-Q$33-'Pricing Structure - IHAG'!O41 -> 0.55866999 | R35: =R49 -> #REF! | S35: =S49 -> #REF! | T35: =T49 -> #REF! | U35: =U49 -> #REF! | V35: =V34-V$33-'Pricing Structure - All SKU'!AZ41 -> 0.76603306 | W35: =W34-W$33-'Pricing Structure - All SKU'!BB41 -> 0.69492561 | X35: =X34-X$33-'Pricing Structure - All SKU'!BH41 -> 0.69098023 | Y35: =Y34-Y$33-'Pricing Structure - All SKU'!BT41 -> 0.033119835 | Z35: =Z34-Z$33-'Pricing Structure - All SKU'!BV41 -> 0.033119835 | AA35: =AA34-AA$33-'Pricing Structure - All SKU'!BZ41 -> 0.087655536 | AB35: =AB34-AB$33-'Pricing Structure - All SKU'!BL41 -> 1.2173149 | AC35: =AC34-AC$33-'Pricing Structure - All SKU'!BN41 -> 1.2021123 | AD35: =AD34-AD$33-'Pricing Structure - All SKU'!BR41 -> 0.92842589 | AE35: =AE34-AE$33-'Pricing Structure - All SKU'!CB41 -> 1.7378225 | AF35: =AF34-AF$33-'Pricing Structure - All SKU'!CD41 -> 0.88876263 | AG35: =AG34-AG$33-'Pricing Structure - All SKU'!CH41 -> 1.0847995
A36: 29 | B36: Distributor Margin % | C36: =IFERROR(C35/C34,0) -> 0.11834688 | D36: =IFERROR(D35/D34,0) -> 0.10741041 | E36: =IFERROR(E35/E34,0) -> 0.094911629 | F36: =F50 -> 0 | G36: =IFERROR(G35/G34,0) -> 0 | H36: =IFERROR(H35/H34,0) -> 0 | I36: =IFERROR(I35/I34,0) -> 0.12036808 | J36: =IFERROR(J35/J34,0) -> 0.10610178 | K36: =IFERROR(K35/K34,0) -> 0.095378825 | L36: =IFERROR(L35/L34,0) -> 0 | M36: =IFERROR(M35/M34,0) -> 0 | N36: =IFERROR(N35/N34,0) -> 0 | ... AG36: =IFERROR(AG35/AG34,0) -> 0.13712353
A37: 30 | B37: Growth | D37: =D35/C35-1 -> -0.092410296 | E37: =E35/D35-1 -> -0.11903639 | F37: =F35/E35-1 -> #REF! | G37: =G35/E35-1 -> #REF! | H37: =H35/E35-1 -> #REF! | J37: =J35/I35-1 -> -0.11852232 | K37: =K35/J35-1 -> -0.10378082 | L37: =L35/K35-1 -> #REF! | M37: =M35/K35-1 -> #REF! | N37: =N35/K35-1 -> #REF! | P37: =P35/O35-1 -> -0.12667897 | Q37: =Q35/P35-1 -> -0.22821442 | R37: =R35/Q35-1 -> #REF! | S37: =S35/Q35-1 -> #REF! | T37: =T35/Q35-1 -> #REF! | U37: =U35/Q35-1 -> #REF! | W37: =W35/S35-1 -> #REF! | X37: =X35/V35-1 -> -0.097975963 | Z37: =Z35/X35-1 -> -0.95206833 | AA37: =AA35/Y35-1 -> 1.6466176 | AC37: =AC35/AA35-1 -> 12.714048 | AD37: =AD35/AB35-1 -> -0.23731661 | AF37: =AF35/AD35-1 -> -0.042720978 | AG37: =AG35/AE35-1 -> -0.37577081
A38: 31
A39: 32 | B39: CBP | E39: 1000 | F39: 1000 | G39: 1100 | H39: 1200 | K39: 1000 | L39: 1000 | M39: 1100 | N39: 1200 | Q39: 1000 | S39: 1200 | T39: 1100 | U39: 1200
C41: =IF(C31>C35,"IOD > Dist","IOD < Dist") -> IOD > Dist | D41: =IF(D31>D35,"IOD > Dist","IOD < Dist") -> IOD > Dist | E41: =IF(E31>E35,"IOD > Dist","IOD < Dist") -> IOD > Dist | F41: =IF(F31>G35,"IOD > Dist","IOD < Dist") -> #REF! | G41: =IF(H31>H35,"IOD > Dist","IOD < Dist") -> #REF! | H41: =IF(I31>I35,"IOD > Dist","IOD < Dist") -> IOD > Dist | I41: =IF(J31>J35,"IOD > Dist","IOD < Dist") -> IOD > Dist | J41: =IF(K31>K35,"IOD > Dist","IOD < Dist") -> IOD < Dist | K41: =IF(L31>L35,"IOD > Dist","IOD < Dist") -> #REF! | L41: =IF(N31>N35,"IOD > Dist","IOD < Dist") -> #REF! | M41: =IF(O31>O35,"IOD > Dist","IOD < Dist") -> IOD < Dist | N41: =IF(P31>P35,"IOD > Dist","IOD < Dist") -> IOD < Dist | O41: =IF(Q31>Q35,"IOD > Dist","IOD < Dist") -> IOD < Dist | P41: =IF(R31>R35,"IOD > Dist","IOD < Dist") -> #REF! | Q41: =IF(S31>S35,"IOD > Dist","IOD < Dist") -> #REF! | R41: =IF(U31>U35,"IOD > Dist","IOD < Dist") -> #REF! | S41: =IF(V31>V35,"IOD > Dist","IOD < Dist") -> IOD > Dist | T41: =IF(W31>W35,"IOD > Dist","IOD < Dist") -> IOD > Dist | U41: =IF(X31>X35,"IOD > Dist","IOD < Dist") -> IOD > Dist | V41: =IF(Y31>Y35,"IOD > Dist","IOD < Dist") -> IOD > Dist | W41: =IF(Z31>Z35,"IOD > Dist","IOD < Dist") -> IOD > Dist | X41: =IF(AA31>AA35,"IOD > Dist","IOD < Dist") -> IOD > Dist | Y41: =IF(AB31>AB35,"IOD > Dist","IOD < Dist") -> IOD < Dist | ... AD41: =IF(AG31>AG35,"IOD > Dist","IOD < Dist") -> IOD < Dist
D46: Scenario 1 | E46: Scenario 2 | F46: Scenario 3 | G46: =G9 -> Scenario +15%, 1100 | H46: =H9 -> Scenario +15%, 1200 | J46: Scenario 1 | K46: Scenario 2 | L46: Scenario 3 | M46: =G46 -> Scenario +15%, 1100 | N46: =H46 -> Scenario +15%, 1200 | P46: Scenario 1 | Q46: Scenario 2 | R46: Scenario 3 | S46: Scenario 4 | T46: =M46 -> Scenario +15%, 1100 | U46: =N46 -> Scenario +15%, 1200
B47: Distributor Buying Value | D47: ='Pricing Structure - GSS'!#REF! -> #REF! | E47: ='Pricing Structure - GSS'!#REF! -> #REF! | F47: ='Pricing Structure - GSS'!#REF! -> #REF! | G47: ='Pricing Structure - GSS'!#REF! -> #REF! | H47: ='Pricing Structure - GSS'!#REF! -> #REF! | J47: ='Pricing Structure - IIP'!#REF! -> #REF! | K47: ='Pricing Structure - IIP'!#REF! -> #REF! | L47: ='Pricing Structure - IIP'!#REF! -> #REF! | M47: ='Pricing Structure - IIP'!#REF! -> #REF! | N47: ='Pricing Structure - IIP'!#REF! -> #REF! | P47: ='Pricing Structure - IHAG'!#REF! -> #REF! | Q47: ='Pricing Structure - IHAG'!#REF! -> #REF! | R47: ='Pricing Structure - IHAG'!#REF! -> #REF! | S47: ='Pricing Structure - IHAG'!#REF! -> #REF! | T47: ='Pricing Structure - IHAG'!#REF! -> #REF! | U47: ='Pricing Structure - IHAG'!#REF! -> #REF!
B48: Distributor Selling Value | D48: ='Pricing Structure - GSS'!#REF! -> #REF! | E48: ='Pricing Structure - GSS'!#REF! -> #REF! | F48: ='Pricing Structure - GSS'!#REF! -> #REF! | G48: ='Pricing Structure - GSS'!#REF! -> #REF! | H48: ='Pricing Structure - GSS'!#REF! -> #REF! | J48: ='Pricing Structure - IIP'!#REF! -> #REF! | K48: ='Pricing Structure - IIP'!#REF! -> #REF! | L48: ='Pricing Structure - IIP'!#REF! -> #REF! | M48: ='Pricing Structure - IIP'!#REF! -> #REF! | N48: ='Pricing Structure - IIP'!#REF! -> #REF! | P48: ='Pricing Structure - IHAG'!#REF! -> #REF! | Q48: ='Pricing Structure - IHAG'!#REF! -> #REF! | R48: ='Pricing Structure - IHAG'!#REF! -> #REF! | S48: ='Pricing Structure - IHAG'!#REF! -> #REF! | T48: ='Pricing Structure - IHAG'!#REF! -> #REF! | U48: ='Pricing Structure - IHAG'!#REF! -> #REF!
B49: Distributor Margin | D49: =D48-D$47-'Pricing Structure - GSS'!#REF! -> #REF! | E49: =E48-E$47-'Pricing Structure - GSS'!#REF! -> #REF! | F49: =F48-F$47-'Pricing Structure - GSS'!#REF! -> #REF! | G49: =G48-G$47-'Pricing Structure - GSS'!#REF! -> #REF! | H49: =H48-H$47-'Pricing Structure - GSS'!#REF! -> #REF! | J49: =J48-J$47-'Pricing Structure - IIP'!#REF! -> #REF! | K49: =K48-K$47-'Pricing Structure - IIP'!#REF! -> #REF! | L49: =L48-L$47-'Pricing Structure - IIP'!#REF! -> #REF! | M49: =M48-M$47-'Pricing Structure - IIP'!#REF! -> #REF! | N49: =N48-N$47-'Pricing Structure - IIP'!#REF! -> #REF! | P49: =P48-P$47-'Pricing Structure - IHAG'!#REF! -> #REF! | Q49: =Q48-Q$47-'Pricing Structure - IHAG'!#REF! -> #REF! | R49: =R48-R$47-'Pricing Structure - IHAG'!#REF! -> #REF! | S49: =S48-S$47-'Pricing Structure - IHAG'!#REF! -> #REF! | T49: =T48-T$47-'Pricing Structure - IHAG'!#REF! -> #REF! | U49: =U48-U$47-'Pricing Structure - IHAG'!#REF! -> #REF!
B50: Distributor Margin % | D50: =IFERROR(D49/D48,0) -> 0 | E50: =IFERROR(E49/E48,0) -> 0 | F50: =IFERROR(F49/F48,0) -> 0 | G50: =IFERROR(G49/G48,0) -> 0 | H50: =IFERROR(H49/H48,0) -> 0 | J50: =IFERROR(J49/J48,0) -> 0 | K50: =IFERROR(K49/K48,0) -> 0 | L50: =IFERROR(L49/L48,0) -> 0 | M50: =IFERROR(M49/M48,0) -> 0 | N50: =IFERROR(N49/N48,0) -> 0 | P50: =IFERROR(P49/P48,0) -> 0 | Q50: =IFERROR(Q49/Q48,0) -> 0 | R50: =IFERROR(R49/R48,0) -> 0 | S50: =IFERROR(S49/S48,0) -> 0 | T50: =IFERROR(T49/T48,0) -> 0 | U50: =IFERROR(U49/U48,0) -> 0
D51: =D48-D47 -> #REF! | E51: =E48-E47 -> #REF! | F51: =F48-F47 -> #REF! | G51: =G48-G47 -> #REF! | H51: =H48-H47 -> #REF! | I51: =I48-I47 -> 0 | J51: =J48-J47 -> #REF! | K51: =K48-K47 -> #REF! | ... U51: =U48-U47 -> #REF!
B52: Net VAT | D52: =D51-D49 -> #REF! | E52: =E51-E49 -> #REF! | F52: =F51-F49 -> #REF! | G52: =G51-G49 -> #REF! | H52: =H51-H49 -> #REF! | I52: =I51-I49 -> 0 | J52: =J51-J49 -> #REF! | K52: =K51-K49 -> #REF! | ... U52: =U51-U49 -> #REF!

Sheet P&L TOTAL 150
B2: Scenario 1000 | C2: 3 | D2: 9 | E2: 15 | F2: 21 | G2: 27 | H2: 24 | I2: 30
B3: Scenario 1100 | C3: 5 | D3: 11 | E3: 19 | F3: 22 | G3: 28 | H3: 25 | I3: 31
B5: Scenario COGS 1 | C5: 3 | D5: 9 | E5: 15 | F5: 21 | G5: 27 | H5: 24 | I5: 30
B6: Scenario COGS 2 | C6: 5 | D6: 11 | E6: 19 | F6: 22 | G6: 28 | H6: 25 | I6: 31
B7: Scenario COGS 3 | C7: 5 | D7: 11 | E7: 19 | F7: 22 | G7: 28 | H7: 25 | I7: 31
B9: Scenario | C9: 1 | K9: 1 | S9: 1 | AA9: 1 | AI9: 1 | AQ9: 1 | AY9: 2 | BG9: 2 | BO9: 2 | BW9: 2 | CE9: 2 | CM9: 2
C10: =IF($C9=1,$C2,$C3) -> 3 | D10: =IF($C9=1,$D2,$D3) -> 9 | E10: =IF($C9=1,$E2,$E3) -> 15 | F10: =IF($C9=1,$F2,$F3) -> 21 | G10: =IF($C9=1,$G2,$G3) -> 27 | H10: =IF($C9=1,$H2,$H3) -> 24 | I10: =IF($I9=1,$I2,$I3) -> 31 | K10: =IF(K9=1,$C2,$C3) -> 3 | L10: =IF(K9=1,$D2,$D3) -> 9 | M10: =IF(K9=1,$E2,$E3) -> 15 | N10: =IF(K9=1,$F2,$F3) -> 21 | O10: =IF(K9=1,$G2,$G3) -> 27 | P10: =IF(K9=1,$H2,$H3) -> 24 | Q10: =IF(K9=1,$I2,$I3) -> 30 | S10: =IF(S9=1,$C2,$C3) -> 3 | T10: =IF(S9=1,$D2,$D3) -> 9 | U10: =IF(S9=1,$E2,$E3) -> 15 | V10: =IF(S9=1,$F2,$F3) -> 21 | W10: =IF(S9=1,$G2,$G3) -> 27 | X10: =IF(S9=1,$H2,$H3) -> 24 | Y10: =IF(S9=1,$I2,$I3) -> 30 | AA10: =IF(AA9=1,$C2,$C3) -> 3 | AB10: =IF(AA9=1,$D2,$D3) -> 9 | AC10: =IF(AA9=1,$E2,$E3) -> 15 | AD10: =IF(AA9=1,$F2,$F3) -> 21 | AE10: =IF(AA9=1,$G2,$G3) -> 27 | AF10: =IF(AA9=1,$H2,$H3) -> 24 | AG10: =IF(AA9=1,$I2,$I3) -> 30 | AI10: =IF(AI9=1,$C2,$C3) -> 3 | AJ10: =IF(AI9=1,$D2,$D3) -> 9 | AK10: =IF(AI9=1,$E2,$E3) -> 15 | AL10: =IF(AI9=1,$F2,$F3) -> 21 | AM10: =IF(AI9=1,$G2,$G3) -> 27 | AN10: =IF(AI9=1,$H2,$H3) -> 24 | AO10: =IF(AI9=1,$I2,$I3) -> 30 | AQ10: =IF(AQ9=1,$C2,$C3) -> 3 | AR10: =IF(AQ9=1,$D2,$D3) -> 9 | AS10: =IF(AQ9=1,$E2,$E3) -> 15 | AT10: =IF(AQ9=1,$F2,$F3) -> 21 | AU10: =IF(AQ9=1,$G2,$G3) -> 27 | AV10: =IF(AQ9=1,$H2,$H3) -> 24 | AW10: =IF(AQ9=1,$I2,$I3) -> 30 | AY10: =IF(AY9=1,$C2,$C3) -> 5 | AZ10: =IF(AY9=1,$D2,$D3) -> 11 | BA10: =IF(AY9=1,$E2,$E3) -> 19 | BB10: =IF(AY9=1,$F2,$F3) -> 22 | BC10: =IF(AY9=1,$G2,$G3) -> 28 | BD10: =IF(AY9=1,$H2,$H3) -> 25 | BE10: =IF(AY9=1,$I2,$I3) -> 31 | BG10: =IF(BG9=1,$C2,$C3) -> 5 | BH10: =IF(BG9=1,$D2,$D3) -> 11 | BI10: =IF(BG9=1,$E2,$E3) -> 19 | BJ10: =IF(BG9=1,$F2,$F3) -> 22 | BK10: =IF(BG9=1,$G2,$G3) -> 28 | BL10: =IF(BG9=1,$H2,$H3) -> 25 | BM10: =IF(BG9=1,$I2,$I3) -> 31 | BO10: =IF(BO9=1,$C2,$C3) -> 5 | BP10: =IF(BO9=1,$D2,$D3) -> 11 | BQ10: =IF(BO9=1,$E2,$E3) -> 19 | BR10: =IF(BO9=1,$F2,$F3) -> 22 | BS10: =IF(BO9=1,$G2,$G3) -> 28 | BT10: =IF(BO9=1,$H2,$H3) -> 25 | BU10: =IF(BO9=1,$I2,$I3) -> 31 | BW10: =IF(BW9=1,$C2,$C3) -> 5 | BX10: =IF(BW9=1,$D2,$D3) -> 11 | BY10: =IF(BW9=1,$E2,$E3) -> 19 | BZ10: =IF(BW9=1,$F2,$F3) -> 22 | CA10: =IF(BW9=1,$G2,$G3) -> 28 | CB10: =IF(BW9=1,$H2,$H3) -> 25 | CC10: =IF(BW9=1,$I2,$I3) -> 31 | CE10: =IF(CE9=1,$C2,$C3) -> 5 | CF10: =IF(CE9=1,$D2,$D3) -> 11 | CG10: =IF(CE9=1,$E2,$E3) -> 19 | CH10: =IF(CE9=1,$F2,$F3) -> 22 | CI10: =IF(CE9=1,$G2,$G3) -> 28 | CJ10: =IF(CE9=1,$H2,$H3) -> 25 | CK10: =IF(CE9=1,$I2,$I3) -> 31 | CM10: =IF(CM9=1,$C2,$C3) -> 5 | CN10: =IF(CM9=1,$D2,$D3) -> 11 | CO10: =IF(CM9=1,$E2,$E3) -> 19 | CP10: =IF(CM9=1,$F2,$F3) -> 22 | CQ10: =IF(CM9=1,$G2,$G3) -> 28 | CR10: =IF(CM9=1,$H2,$H3) -> 25 | CS10: =IF(CM9=1,$I2,$I3) -> 31
B11: Scenario COGS | J11: Actual Jan | R11: Actual Feb | Z11: Actual Feb | AA11: =AH11 -> Q2 | AH11: Q2 | AI11: =AP11 -> Q2 | AP11: Q2 | AQ11: =AX11 -> Q2 | AX11: Q2 | AY11: =BF11 -> Q4 | BF11: Q4 | BG11: =BN11 -> Q4 | BN11: Q4 | BO11: =BV11 -> Q4 | BV11: Q4 | BW11: =CD11 -> Q4 | CD11: Q4 | CE11: =CL11 -> Q4 | CL11: Q4 | CM11: =CT11 -> Q4 | CT11: Q4
J12: =J24/J16 -> 0.62652933 | R12: =R24/R16 -> 0.39722463 | Z12: =Z24/Z16 -> 0.38935033 | AA12: =AA24/AA16 -> 0.8851129 | AB12: =AB24/AB16 -> 0.39456602 | AC12: =AC24/AC16 -> 0 | AD12: =AD24/AD16 -> #DIV/0! | AE12: =AE24/AE16 -> 0 | AF12: =AF24/AF16 -> 0 | AG12: =AG24/AG16 -> 0 | AH12: =AH24/AH16 -> 0.43563356 | AI12: 0.6 | AJ12: 0.15 | AK12: 0 | AL12: 0 | AM12: 0 | AN12: 0 | AO12: 0 | AP12: =AP24/AP16 -> 0.28355357 | AQ12: 0.6 | AR12: 0.15 | AS12: 0 | AT12: 0 | AU12: 0 | AV12: 0 | AW12: 0 | AX12: =AX24/AX16 -> 0.27917974 | AY12: =AY24/AY16 -> #REF! | AZ12: =AZ24/AZ16 -> #REF! | BA12: =BA24/BA16 -> #REF! | BB12: =BB24/BB16 -> #DIV/0! | BC12: =BC24/BC16 -> #DIV/0! | BD12: =BD24/BD16 -> 0 | BE12: =BE24/BE16 -> #DIV/0! | BF12: =BF24/BF16 -> #REF! | BN12: =BN24/BN16 -> #REF! | BV12: =BV24/BV16 -> #REF! | CD12: =CD24/CD16 -> #REF! | CL12: =CL24/CL16 -> #REF! | CT12: =CT24/CT16 -> #REF!
C13: Jan | K13: Feb | S13: Mar | AA13: Apr | AI13: May | AQ13: Jun | AY13: Jul | BG13: Aug | BO13: Sep | BW13: Oct | CE13: Nov | CM13: Dec | CU13: TOTAL
B14: Jan-Mar | C14: GSS LOKAL 40 | D14: IIP LOKAL 40 | E14: IHAG LOKAL 40 | F14: GPD LOKAL 40 | G14: CGSS MA (NS) 12 | H14: PMAD LOKAL 12 | I14: PMAJ LOKAL 24 | J14: JAN | K14: GSS LOKAL 40 | L14: IIP LOKAL 40 | M14: IHAG LOKAL 40 | N14: GPD LOKAL 40 | O14: CGSS MA (NS) 12 | P14: PMAD LOKAL 12 | Q14: PMAJ LOKAL 24 | R14: FEB | S14: GSS LOKAL 40 | T14: IIP LOKAL 40 | U14: IHAG LOKAL 40 | V14: GPD LOKAL 40 | W14: CGSS MA (NS) 12 | X14: PMAD LOKAL 12 | Y14: PMAJ LOKAL 24 | Z14: MAR | AA14: GSS LOKAL 40 | AB14: IIP LOKAL 40 | AC14: IHAG LOKAL 40 | AD14: GPD LOKAL 40 | AE14: CGSS MA (NS) 12 | AF14: PMAD LOKAL 12 | AG14: PMAJ LOKAL 24 | AH14: APR | AI14: GSS LOKAL 40 | AJ14: IIP LOKAL 40 | AK14: IHAG LOKAL 40 | AL14: GPD LOKAL 40 | AM14: CGSS MA (NS) 12 | AN14: PMAD LOKAL 12 | AO14: PMAJ LOKAL 24 | AP14: MAY | AQ14: GSS LOKAL 40 | AR14: IIP LOKAL 40 | AS14: IHAG LOKAL 40 | AT14: GPD LOKAL 40 | AU14: CGSS MA (NS) 12 | AV14: PMAD LOKAL 12 | AW14: PMAJ LOKAL 24 | AX14: JUN | AY14: GSS LOKAL 40 | AZ14: IIP LOKAL 40 | BA14: IHAG LOKAL 40 | BB14: GPD LOKAL 40 | BC14: CGSS MA (NS) 12 | BD14: PMAD LOKAL 12 | BE14: PMAJ LOKAL 24 | BF14: JUL | BG14: GSS LOKAL 40 | BH14: IIP LOKAL 40 | BI14: IHAG LOKAL 40 | BJ14: GPD LOKAL 40 | BK14: CGSS MA (NS) 12 | BL14: PMAD LOKAL 12 | BM14: PMAJ LOKAL 24 | BN14: AUG | BO14: GSS LOKAL 40 | BP14: IIP LOKAL 40 | BQ14: IHAG LOKAL 40 | BR14: GPD LOKAL 40 | BS14: CGSS MA (NS) 12 | BT14: PMAD LOKAL 12 | BU14: PMAJ LOKAL 24 | BV14: SEP | BW14: GSS LOKAL 40 | BX14: IIP LOKAL 40 | BY14: IHAG LOKAL 40 | BZ14: GPD LOKAL 40 | CA14: CGSS MA (NS) 12 | CB14: PMAD LOKAL 12 | CC14: PMAJ LOKAL 24 | CD14: OCT | CE14: GSS LOKAL 40 | CF14: IIP LOKAL 40 | CG14: IHAG LOKAL 40 | CH14: GPD LOKAL 40 | CI14: CGSS MA (NS) 12 | CJ14: PMAD LOKAL 12 | CK14: PMAJ LOKAL 24 | CL14: NOV | CM14: GSS LOKAL 40 | CN14: IIP LOKAL 40 | CO14: IHAG LOKAL 40 | CP14: GPD LOKAL 40 | CQ14: CGSS MA (NS) 12 | CR14: PMAD LOKAL 12 | CS14: PMAJ LOKAL 24 | CT14: DEC | CU14: GSS LOKAL 40 | CV14: IIP LOKAL 40 | CW14: IHAG LOKAL 40 | CX14: GPD LOKAL 40 | CY14: CGSS MA (NS) 12 | CZ14: PMAD LOKAL 12 | DA14: PMAJ LOKAL 24 | DB14: TOTAL | DC14: YTD
B15: Vol (pcs) | C15: ='STT STD - By SKU 150'!$C5 -> 10376960 | D15: ='STT STD - By SKU 150'!$D5 -> 2560000 | E15: ='STT STD - By SKU 150'!$E5 -> 5677200 | F15: ='STT STD - By SKU 150'!$F5 -> 0 | G15: ='STT STD - By SKU 150'!$G5 -> 0 | H15: ='STT STD - By SKU 150'!$H5 -> 28800 | I15: ='STT STD - By SKU 150'!$I5 -> 28224 | J15: =SUM(C15:I15) -> 18671184 | K15: ='STT STD - By SKU 150'!$C6 -> 4985400 | L15: ='STT STD - By SKU 150'!$D6 -> 2080000 | M15: ='STT STD - By SKU 150'!$E6 -> 5968800 | N15: ='STT STD - By SKU 150'!$F6 -> 0 | O15: ='STT STD - By SKU 150'!$G6 -> 13668 | P15: ='STT STD - By SKU 150'!$H6 -> 28500 | Q15: ='STT STD - By SKU 150'!$I6 -> 0 | R15: =SUM(K15:Q15) -> 13076368 | S15: ='STT STD - By SKU 150'!$C7 -> 7376400 | T15: ='STT STD - By SKU 150'!$D7 -> 1760000 | U15: ='STT STD - By SKU 150'!$E7 -> 8875000 | V15: ='STT STD - By SKU 150'!$F7 -> 64000 | W15: ='STT STD - By SKU 150'!$G7 -> 27900 | X15: ='STT STD - By SKU 150'!$H7 -> 86400 | Y15: ='STT STD - By SKU 150'!$I7 -> 57600 | Z15: =SUM(S15:Y15) -> 18247300 | AA15: ='STT STD - By SKU 150'!$C8 -> 5699680 | AB15: ='STT STD - By SKU 150'!$D8 -> 1600000 | AC15: ='STT STD - By SKU 150'!$E8 -> 5538000 | AD15: ='STT STD - By SKU 150'!$F8 -> 0 | AE15: ='STT STD - By SKU 150'!$G8 -> 14400 | AF15: ='STT STD - By SKU 150'!$H8 -> 28800 | AG15: ='STT STD - By SKU 150'!$I8 -> 28800 | AH15: =SUM(AA15:AG15) -> 12909680 | AI15: ='STT STD - By SKU 150'!$C9 -> 3376480 | AJ15: ='STT STD - By SKU 150'!$D9 -> 960000 | AK15: ='STT STD - By SKU 150'!$E9 -> 3124000 | AL15: ='STT STD - By SKU 150'!$F9 -> 0 | AM15: ='STT STD - By SKU 150'!$G9 -> 14400 | AN15: ='STT STD - By SKU 150'!$H9 -> 28800 | AO15: ='STT STD - By SKU 150'!$I9 -> 28800 | AP15: =SUM(AI15:AO15) -> 7532480 | AQ15: ='STT STD - By SKU 150'!$C10 -> 5343360 | AR15: ='STT STD - By SKU 150'!$D10 -> 1600000 | AS15: ='STT STD - By SKU 150'!$E10 -> 5112000 | AT15: ='STT STD - By SKU 150'!$F10 -> 0 | AU15: ='STT STD - By SKU 150'!$G10 -> 14400 | AV15: ='STT STD - By SKU 150'!$H10 -> 57600 | AW15: ='STT STD - By SKU 150'!$I10 -> 28800 | AX15: =SUM(AQ15:AW15) -> 12156160 | AY15: ='STT STD - By SKU 150'!$C11 -> 4646400 | AZ15: ='STT STD - By SKU 150'!$D11 -> 1280000 | BA15: ='STT STD - By SKU 150'!$E11 -> 4402000 | BB15: ='STT STD - By SKU 150'!$F11 -> 0 | BC15: ='STT STD - By SKU 150'!$G11 -> 0 | BD15: ='STT STD - By SKU 150'!$H11 -> 28800 | BE15: ='STT STD - By SKU 150'!$I11 -> 0 | BF15: =SUM(AY15:BE15) -> 10357200 | BG15: ='STT STD - By SKU 150'!$C12 -> 4104320 | BH15: ='STT STD - By SKU 150'!$D12 -> 1280000 | BI15: ='STT STD - By SKU 150'!$E12 -> 4544000 | BJ15: ='STT STD - By SKU 150'!$F12 -> 0 | BK15: ='STT STD - By SKU 150'!$G12 -> 14400 | BL15: ='STT STD - By SKU 150'!$H12 -> 57600 | BM15: ='STT STD - By SKU 150'!$I12 -> 28800 | BN15: =SUM(BG15:BM15) -> 10029120 | BO15: ='STT STD - By SKU 150'!$C13 -> 5265920 | BP15: ='STT STD - By SKU 150'!$D13 -> 1760000 | BQ15: ='STT STD - By SKU 150'!$E13 -> 5822000 | BR15: ='STT STD - By SKU 150'!$F13 -> 0 | BS15: ='STT STD - By SKU 150'!$G13 -> 14400 | BT15: ='STT STD - By SKU 150'!$H13 -> 28800 | BU15: ='STT STD - By SKU 150'!$I13 -> 28800 | BV15: =SUM(BO15:BU15) -> 12919920 | BW15: ='STT STD - By SKU 150'!$C14 -> 3872000 | BX15: ='STT STD - By SKU 150'!$D14 -> 1440000 | BY15: ='STT STD - By SKU 150'!$E14 -> 4544000 | BZ15: ='STT STD - By SKU 150'!$F14 -> 0 | CA15: ='STT STD - By SKU 150'!$G14 -> 14400 | CB15: ='STT STD - By SKU 150'!$H14 -> 28800 | CC15: ='STT STD - By SKU 150'!$I14 -> 0 | CD15: =SUM(BW15:CC15) -> 9899200 | CE15: ='STT STD - By SKU 150'!$C15 -> 4104320 | CF15: ='STT STD - By SKU 150'!$D15 -> 1280000 | CG15: ='STT STD - By SKU 150'!$E15 -> 4686000 | CH15: ='STT STD - By SKU 150'!$F15 -> 0 | CI15: ='STT STD - By SKU 150'!$G15 -> 0 | CJ15: ='STT STD - By SKU 150'!$H15 -> 28800 | CK15: ='STT STD - By SKU 150'!$I15 -> 28800 | CL15: =SUM(CE15:CK15) -> 10127920 | CM15: ='STT STD - By SKU 150'!$C16 -> 6421680 | CN15: ='STT STD - By SKU 150'!$D16 -> 1760000 | CO15: ='STT STD - By SKU 150'!$E16 -> 5822000 | CP15: ='STT STD - By SKU 150'!$F16 -> 0 | CQ15: ='STT STD - By SKU 150'!$G16 -> 14400 | CR15: ='STT STD - By SKU 150'!$H16 -> 28800 | CS15: ='STT STD - By SKU 150'!$I16 -> 28800 | CT15: =SUM(CM15:CS15) -> 14075680 | CU15: =SUMIFS($C15:$CT15,$C$14:$CT$14,CU$14) -> 65572920 | CV15: =SUMIFS($C15:$CT15,$C$14:$CT$14,CV$14) -> 19360000 | CW15: =SUMIFS($C15:$CT15,$C$14:$CT$14,CW$14) -> 64115000 | CX15: =SUMIFS($C15:$CT15,$C$14:$CT$14,CX$14) -> 64000 | CY15: =SUMIFS($C15:$CT15,$C$14:$CT$14,CY$14) -> 142368 | CZ15: =SUMIFS($C15:$CT15,$C$14:$CT$14,CZ$14) -> 460500 | DA15: =SUMIFS($C15:$CT15,$C$14:$CT$14,DA$14) -> 287424 | DB15: =SUM(CU15:DA15) -> 150002212 | DC15: =SUM(J15,R15) -> 31747552
B16: Vol (ctn) | C16: =C15/RIGHT(C14,2) -> 259424 | D16: =D15/RIGHT(D14,2) -> 64000 | E16: =E15/RIGHT(E14,2) -> 141930 | F16: =F15/RIGHT(F14,2) -> 0 | G16: =G15/RIGHT(G14,2) -> 0 | H16: =H15/RIGHT(H14,2) -> 2400 | I16: =I15/RIGHT(I14,2) -> 1176 | J16: =SUM(C16:I16) -> 468930 | K16: =K15/RIGHT(K14,2) -> 124635 | L16: =L15/RIGHT(L14,2) -> 52000 | M16: =M15/RIGHT(M14,2) -> 149220 | N16: =N15/RIGHT(N14,2) -> 0 | O16: =O15/RIGHT(O14,2) -> 1139 | P16: =P15/RIGHT(P14,2) -> 2375 | Q16: =Q15/RIGHT(Q14,2) -> 0 | R16: =SUM(K16:Q16) -> 329369 | S16: =S15/RIGHT(S14,2) -> 184410 | T16: =T15/RIGHT(T14,2) -> 44000 | U16: =U15/RIGHT(U14,2) -> 221875 | V16: =V15/RIGHT(V14,2) -> 1600 | W16: =W15/RIGHT(W14,2) -> 2325 | X16: =X15/RIGHT(X14,2) -> 7200 | Y16: =Y15/RIGHT(Y14,2) -> 2400 | Z16: =SUM(S16:Y16) -> 463810 | AA16: =AA15/RIGHT(AA14,2) -> 142492 | AB16: =AB15/RIGHT(AB14,2) -> 40000 | AC16: =AC15/RIGHT(AC14,2) -> 138450 | AD16: =AD15/RIGHT(AD14,2) -> 0 | AE16: =AE15/RIGHT(AE14,2) -> 1200 | AF16: =AF15/RIGHT(AF14,2) -> 2400 | AG16: =AG15/RIGHT(AG14,2) -> 1200 | AH16: =SUM(AA16:AG16) -> 325742 | AI16: =AI15/RIGHT(AI14,2) -> 84412 | AJ16: =AJ15/RIGHT(AJ14,2) -> 24000 | AK16: =AK15/RIGHT(AK14,2) -> 78100 | AL16: =AL15/RIGHT(AL14,2) -> 0 | AM16: =AM15/RIGHT(AM14,2) -> 1200 | AN16: =AN15/RIGHT(AN14,2) -> 2400 | AO16: =AO15/RIGHT(AO14,2) -> 1200 | AP16: =SUM(AI16:AO16) -> 191312 | AQ16: =AQ15/RIGHT(AQ14,2) -> 133584 | AR16: =AR15/RIGHT(AR14,2) -> 40000 | AS16: =AS15/RIGHT(AS14,2) -> 127800 | AT16: =AT15/RIGHT(AT14,2) -> 0 | AU16: =AU15/RIGHT(AU14,2) -> 1200 | AV16: =AV15/RIGHT(AV14,2) -> 4800 | AW16: =AW15/RIGHT(AW14,2) -> 1200 | AX16: =SUM(AQ16:AW16) -> 308584 | AY16: =AY15/RIGHT(AY14,2) -> 116160 | AZ16: =AZ15/RIGHT(AZ14,2) -> 32000 | BA16: =BA15/RIGHT(BA14,2) -> 110050 | BB16: =BB15/RIGHT(BB14,2) -> 0 | BC16: =BC15/RIGHT(BC14,2) -> 0 | BD16: =BD15/RIGHT(BD14,2) -> 2400 | BE16: =BE15/RIGHT(BE14,2) -> 0 | BF16: =SUM(AY16:BE16) -> 260610 | BG16: =BG15/RIGHT(BG14,2) -> 102608 | BH16: =BH15/RIGHT(BH14,2) -> 32000 | BI16: =BI15/RIGHT(BI14,2) -> 113600 | BJ16: =BJ15/RIGHT(BJ14,2) -> 0 | BK16: =BK15/RIGHT(BK14,2) -> 1200 | BL16: =BL15/RIGHT(BL14,2) -> 4800 | BM16: =BM15/RIGHT(BM14,2) -> 1200 | BN16: =SUM(BG16:BM16) -> 255408 | BO16: =BO15/RIGHT(BO14,2) -> 131648 | BP16: =BP15/RIGHT(BP14,2) -> 44000 | BQ16: =BQ15/RIGHT(BQ14,2) -> 145550 | BR16: =BR15/RIGHT(BR14,2) -> 0 | BS16: =BS15/RIGHT(BS14,2) -> 1200 | BT16: =BT15/RIGHT(BT14,2) -> 2400 | BU16: =BU15/RIGHT(BU14,2) -> 1200 | BV16: =SUM(BO16:BU16) -> 325998 | BW16: =BW15/RIGHT(BW14,2) -> 96800 | BX16: =BX15/RIGHT(BX14,2) -> 36000 | BY16: =BY15/RIGHT(BY14,2) -> 113600 | BZ16: =BZ15/RIGHT(BZ14,2) -> 0 | CA16: =CA15/RIGHT(CA14,2) -> 1200 | CB16: =CB15/RIGHT(CB14,2) -> 2400 | CC16: =CC15/RIGHT(CC14,2) -> 0 | CD16: =SUM(BW16:CC16) -> 250000 | CE16: =CE15/RIGHT(CE14,2) -> 102608 | CF16: =CF15/RIGHT(CF14,2) -> 32000 | CG16: =CG15/RIGHT(CG14,2) -> 117150 | CH16: =CH15/RIGHT(CH14,2) -> 0 | CI16: =CI15/RIGHT(CI14,2) -> 0 | CJ16: =CJ15/RIGHT(CJ14,2) -> 2400 | CK16: =CK15/RIGHT(CK14,2) -> 1200 | CL16: =SUM(CE16:CK16) -> 255358 | CM16: =CM15/RIGHT(CM14,2) -> 160542 | CN16: =CN15/RIGHT(CN14,2) -> 44000 | CO16: =CO15/RIGHT(CO14,2) -> 145550 | CP16: =CP15/RIGHT(CP14,2) -> 0 | CQ16: =CQ15/RIGHT(CQ14,2) -> 1200 | CR16: =CR15/RIGHT(CR14,2) -> 2400 | CS16: =CS15/RIGHT(CS14,2) -> 1200 | CT16: =SUM(CM16:CS16) -> 354892 | CU16: =SUMIFS($C16:$CT16,$C$14:$CT$14,CU$14) -> 1639323 | CV16: =SUMIFS($C16:$CT16,$C$14:$CT$14,CV$14) -> 484000 | CW16: =SUMIFS($C16:$CT16,$C$14:$CT$14,CW$14) -> 1602875 | CX16: =SUMIFS($C16:$CT16,$C$14:$CT$14,CX$14) -> 1600 | CY16: =SUMIFS($C16:$CT16,$C$14:$CT$14,CY$14) -> 11864 | CZ16: =SUMIFS($C16:$CT16,$C$14:$CT$14,CZ$14) -> 38375 | DA16: =SUMIFS($C16:$CT16,$C$14:$CT$14,DA$14) -> 11976 | DB16: =SUM(CU16:DA16) -> 3790013 | DC16: =SUM(J16,R16) -> 798299
A17: 5 | B17: CIF | C17: =C$16*HLOOKUP(C$10,'P&L by Ctn'!$C$8:$AG$31,'P&L TOTAL 150'!$A17,0) -> 1567690.5 | D17: =D$16*HLOOKUP(D$10,'P&L by Ctn'!$C$8:$AG$31,'P&L TOTAL 150'!$A17,0) -> 386402.02 | E17: =E$16*HLOOKUP(E$10,'P&L by Ctn'!$C$8:$AG$31,'P&L TOTAL 150'!$A17,0) -> 857909.3 | F17: =F$16*HLOOKUP(F$10,'P&L by Ctn'!$C$8:$AG$31,'P&L TOTAL 150'!$A17,0) -> 0 | G17: =G$16*HLOOKUP(G$10,'P&L by Ctn'!$C$8:$AG$31,'P&L TOTAL 150'!$A17,0) -> 0 | H17: =H$16*HLOOKUP(H$10,'P&L by Ctn'!$C$8:$AG$31,'P&L TOTAL 150'!$A17,0) -> 10512 | I17: =I$16*HLOOKUP(I$10,'P&L by Ctn'!$C$8:$AG$31,'P&L TOTAL 150'!$A17,0) -> 7705.1741 | J17: =SUM(C17:I17) -> 2830219 | K17: =K$16*HLOOKUP(K$10,'P&L by Ctn'!$C$8:$AG$31,'P&L TOTAL 150'!$A17,0) -> 753165.12 | L17: =L$16*HLOOKUP(L$10,'P&L by Ctn'!$C$8:$AG$31,'P&L TOTAL 150'!$A17,0) -> 313951.64 | M17: =M$16*HLOOKUP(M$10,'P&L by Ctn'!$C$8:$AG$31,'P&L TOTAL 150'!$A17,0) -> 901974.4 | N17: =N$16*HLOOKUP(N$10,'P&L by Ctn'!$C$8:$AG$31,'P&L TOTAL 150'!$A17,0) -> 0 | O17: =O$16*HLOOKUP(O$10,'P&L by Ctn'!$C$8:$AG$31,'P&L TOTAL 150'!$A17,0) -> 5379.4002 | P17: =P$16*HLOOKUP(P$10,'P&L by Ctn'!$C$8:$AG$31,'P&L TOTAL 150'!$A17,0) -> 10402.5 | Q17: =Q$16*HLOOKUP(Q$10,'P&L by Ctn'!$C$8:$AG$31,'P&L TOTAL 150'!$A17,0) -> 0 | R17: =SUM(K17:Q17) -> 1984873.1 | S17: =S$16*HLOOKUP(S$10,'P&L by Ctn'!$C$8:$AG$31,'P&L TOTAL 150'!$A17,0) -> 1114383.4 | T17: =T$16*HLOOKUP(T$10,'P&L by Ctn'!$C$8:$AG$31,'P&L TOTAL 150'!$A17,0) -> 265651.39 | U17: =U$16*HLOOKUP(U$10,'P&L by Ctn'!$C$8:$AG$31,'P&L TOTAL 150'!$A17,0) -> 1341144.4 | V17: =V$16*HLOOKUP(V$10,'P&L by Ctn'!$C$8:$AG$31,'P&L TOTAL 150'!$A17,0) -> 9679.8678 | W17: =W$16*HLOOKUP(W$10,'P&L by Ctn'!$C$8:$AG$31,'P&L TOTAL 150'!$A17,0) -> 10980.777 | X17: =X$16*HLOOKUP(X$10,'P&L by Ctn'!$C$8:$AG$31,'P&L TOTAL 150'!$A17,0) -> 31536 | Y17: =Y$16*HLOOKUP(Y$10,'P&L by Ctn'!$C$8:$AG$31,'P&L TOTAL 150'!$A17,0) -> 15720 | Z17: =SUM(S17:Y17) -> 2789095.9 | AA17: =AA$16*HLOOKUP(AA$10,'P&L by Ctn'!$C$8:$AG$31,'P&L TOTAL 150'!$A17,0) -> 861074.37 | AB17: =AB$16*HLOOKUP(AB$10,'P&L by Ctn'!$C$8:$AG$31,'P&L TOTAL 150'!$A17,0) -> 241501.26 | AC17: =AC$16*HLOOKUP(AC$10,'P&L by Ctn'!$C$8:$AG$31,'P&L TOTAL 150'!$A17,0) -> 836874.11 | AD17: =AD$16*HLOOKUP(AD$10,'P&L by Ctn'!$C$8:$AG$31,'P&L TOTAL 150'!$A17,0) -> 0 | AE17: =AE$16*HLOOKUP(AE$10,'P&L by Ctn'!$C$8:$AG$31,'P&L TOTAL 150'!$A17,0) -> 5667.498 | AF17: =AF$16*HLOOKUP(AF$10,'P&L by Ctn'!$C$8:$AG$31,'P&L TOTAL 150'!$A17,0) -> 10512 | AG17: =AG$16*HLOOKUP(AG$10,'P&L by Ctn'!$C$8:$AG$31,'P&L TOTAL 150'!$A17,0) -> 7860 | AH17: =SUM(AA17:AG17) -> 1963489.2 | AI17: =AI$16*HLOOKUP(AI$10,'P&L by Ctn'!$C$8:$AG$31,'P&L TOTAL 150'!$A17,0) -> 510098.88 | AJ17: =AJ$16*HLOOKUP(AJ$10,'P&L by Ctn'!$C$8:$AG$31,'P&L TOTAL 150'!$A17,0) -> 144900.76 | AK17: =AK$16*HLOOKUP(AK$10,'P&L by Ctn'!$C$8:$AG$31,'P&L TOTAL 150'!$A17,0) -> 472082.83 | AL17: =AL$16*HLOOKUP(AL$10,'P&L by Ctn'!$C$8:$AG$31,'P&L TOTAL 150'!$A17,0) -> 0 | AM17: =AM$16*HLOOKUP(AM$10,'P&L by Ctn'!$C$8:$AG$31,'P&L TOTAL 150'!$A17,0) -> 5667.498 | AN17: =AN$16*HLOOKUP(AN$10,'P&L by Ctn'!$C$8:$AG$31,'P&L TOTAL 150'!$A17,0) -> 10512 | AO17: =AO$16*HLOOKUP(AO$10,'P&L by Ctn'!$C$8:$AG$31,'P&L TOTAL 150'!$A17,0) -> 7860 | AP17: =SUM(AI17:AO17) -> 1151122 | AQ17: =AQ$16*HLOOKUP(AQ$10,'P&L by Ctn'!$C$8:$AG$31,'P&L TOTAL 150'!$A17,0) -> 807243.63 | AR17: =AR$16*HLOOKUP(AR$10,'P&L by Ctn'!$C$8:$AG$31,'P&L TOTAL 150'!$A17,0) -> 241501.26 | AS17: =AS$16*HLOOKUP(AS$10,'P&L by Ctn'!$C$8:$AG$31,'P&L TOTAL 150'!$A17,0) -> 772499.18 | AT17: =AT$16*HLOOKUP(AT$10,'P&L by Ctn'!$C$8:$AG$31,'P&L TOTAL 150'!$A17,0) -> 0 | AU17: =AU$16*HLOOKUP(AU$10,'P&L by Ctn'!$C$8:$AG$31,'P&L TOTAL 150'!$A17,0) -> 5667.498 | AV17: =AV$16*HLOOKUP(AV$10,'P&L by Ctn'!$C$8:$AG$31,'P&L TOTAL 150'!$A17,0) -> 21024 | AW17: =AW$16*HLOOKUP(AW$10,'P&L by Ctn'!$C$8:$AG$31,'P&L TOTAL 150'!$A17,0) -> 7860 | AX17: =SUM(AQ17:AW17) -> 1855795.6 | AY17: =AY$16*HLOOKUP(AY$10,'P&L by Ctn'!$C$8:$AG$31,'P&L TOTAL 150'!$A17,0) -> #REF! | AZ17: =AZ$16*HLOOKUP(AZ$10,'P&L by Ctn'!$C$8:$AG$31,'P&L TOTAL 150'!$A17,0) -> #REF! | BA17: =BA$16*HLOOKUP(BA$10,'P&L by Ctn'!$C$8:$AG$31,'P&L TOTAL 150'!$A17,0) -> #REF! | BB17: =BB$16*HLOOKUP(BB$10,'P&L by Ctn'!$C$8:$AG$31,'P&L TOTAL 150'!$A17,0) -> 0 | BC17: =BC$16*HLOOKUP(BC$10,'P&L by Ctn'!$C$8:$AG$31,'P&L TOTAL 150'!$A17,0) -> 0 | BD17: =BD$16*HLOOKUP(BD$10,'P&L by Ctn'!$C$8:$AG$31,'P&L TOTAL 150'!$A17,0) -> 10925.406 | BE17: =BE$16*HLOOKUP(BE$10,'P&L by Ctn'!$C$8:$AG$31,'P&L TOTAL 150'!$A17,0) -> 0 | BF17: =SUM(AY17:BE17) -> #REF! | BG17: =BG$16*HLOOKUP(BG$10,'P&L by Ctn'!$C$8:$AG$31,'P&L TOTAL 150'!$A17,0) -> #REF! | BH17: =BH$16*HLOOKUP(BH$10,'P&L by Ctn'!$C$8:$AG$31,'P&L TOTAL 150'!$A17,0) -> #REF! | BI17: =BI$16*HLOOKUP(BI$10,'P&L by Ctn'!$C$8:$AG$31,'P&L TOTAL 150'!$A17,0) -> #REF! | BJ17: =BJ$16*HLOOKUP(BJ$10,'P&L by Ctn'!$C$8:$AG$31,'P&L TOTAL 150'!$A17,0) -> 0 | BK17: =BK$16*HLOOKUP(BK$10,'P&L by Ctn'!$C$8:$AG$31,'P&L TOTAL 150'!$A17,0) -> 6060.1785 | BL17: =BL$16*HLOOKUP(BL$10,'P&L by Ctn'!$C$8:$AG$31,'P&L TOTAL 150'!$A17,0) -> 21850.812 | BM17: =BM$16*HLOOKUP(BM$10,'P&L by Ctn'!$C$8:$AG$31,'P&L TOTAL 150'!$A17,0) -> 7862.4225 | BN17: =SUM(BG17:BM17) -> #REF! | BO17: =BO$16*HLOOKUP(BO$10,'P&L by Ctn'!$C$8:$AG$31,'P&L TOTAL 150'!$A17,0) -> #REF! | BP17: =BP$16*HLOOKUP(BP$10,'P&L by Ctn'!$C$8:$AG$31,'P&L TOTAL 150'!$A17,0) -> #REF! | BQ17: =BQ$16*HLOOKUP(BQ$10,'P&L by Ctn'!$C$8:$AG$31,'P&L TOTAL 150'!$A17,0) -> #REF! | BR17: =BR$16*HLOOKUP(BR$10,'P&L by Ctn'!$C$8:$AG$31,'P&L TOTAL 150'!$A17,0) -> 0 | BS17: =BS$16*HLOOKUP(BS$10,'P&L by Ctn'!$C$8:$AG$31,'P&L TOTAL 150'!$A17,0) -> 6060.1785 | BT17: =BT$16*HLOOKUP(BT$10,'P&L by Ctn'!$C$8:$AG$31,'P&L TOTAL 150'!$A17,0) -> 10925.406 | BU17: =BU$16*HLOOKUP(BU$10,'P&L by Ctn'!$C$8:$AG$31,'P&L TOTAL 150'!$A17,0) -> 7862.4225 | BV17: =SUM(BO17:BU17) -> #REF! | BW17: =BW$16*HLOOKUP(BW$10,'P&L by Ctn'!$C$8:$AG$31,'P&L TOTAL 150'!$A17,0) -> #REF! | BX17: =BX$16*HLOOKUP(BX$10,'P&L by Ctn'!$C$8:$AG$31,'P&L TOTAL 150'!$A17,0) -> #REF! | BY17: =BY$16*HLOOKUP(BY$10,'P&L by Ctn'!$C$8:$AG$31,'P&L TOTAL 150'!$A17,0) -> #REF! | BZ17: =BZ$16*HLOOKUP(BZ$10,'P&L by Ctn'!$C$8:$AG$31,'P&L TOTAL 150'!$A17,0) -> 0 | CA17: =CA$16*HLOOKUP(CA$10,'P&L by Ctn'!$C$8:$AG$31,'P&L TOTAL 150'!$A17,0) -> 6060.1785 | CB17: =CB$16*HLOOKUP(CB$10,'P&L by Ctn'!$C$8:$AG$31,'P&L TOTAL 150'!$A17,0) -> 10925.406 | CC17: =CC$16*HLOOKUP(CC$10,'P&L by Ctn'!$C$8:$AG$31,'P&L TOTAL 150'!$A17,0) -> 0 | CD17: =SUM(BW17:CC17) -> #REF! | CE17: =CE$16*HLOOKUP(CE$10,'P&L by Ctn'!$C$8:$AG$31,'P&L TOTAL 150'!$A17,0) -> #REF! | CF17: =CF$16*HLOOKUP(CF$10,'P&L by Ctn'!$C$8:$AG$31,'P&L TOTAL 150'!$A17,0) -> #REF! | CG17: =CG$16*HLOOKUP(CG$10,'P&L by Ctn'!$C$8:$AG$31,'P&L TOTAL 150'!$A17,0) -> #REF! | CH17: =CH$16*HLOOKUP(CH$10,'P&L by Ctn'!$C$8:$AG$31,'P&L TOTAL 150'!$A17,0) -> 0 | CI17: =CI$16*HLOOKUP(CI$10,'P&L by Ctn'!$C$8:$AG$31,'P&L TOTAL 150'!$A17,0) -> 0 | CJ17: =CJ$16*HLOOKUP(CJ$10,'P&L by Ctn'!$C$8:$AG$31,'P&L TOTAL 150'!$A17,0) -> 10925.406 | CK17: =CK$16*HLOOKUP(CK$10,'P&L by Ctn'!$C$8:$AG$31,'P&L TOTAL 150'!$A17,0) -> 7862.4225 | CL17: =SUM(CE17:CK17) -> #REF! | CM17: =CM$16*HLOOKUP(CM$10,'P&L by Ctn'!$C$8:$AG$31,'P&L TOTAL 150'!$A17,0) -> #REF! | CN17: =CN$16*HLOOKUP(CN$10,'P&L by Ctn'!$C$8:$AG$31,'P&L TOTAL 150'!$A17,0) -> #REF! | CO17: =CO$16*HLOOKUP(CO$10,'P&L by Ctn'!$C$8:$AG$31,'P&L TOTAL 150'!$A17,0) -> #REF! | CP17: =CP$16*HLOOKUP(CP$10,'P&L by Ctn'!$C$8:$AG$31,'P&L TOTAL 150'!$A17,0) -> 0 | CQ17: =CQ$16*HLOOKUP(CQ$10,'P&L by Ctn'!$C$8:$AG$31,'P&L TOTAL 150'!$A17,0) -> 6060.1785 | CR17: =CR$16*HLOOKUP(CR$10,'P&L by Ctn'!$C$8:$AG$31,'P&L TOTAL 150'!$A17,0) -> 10925.406 | CS17: =CS$16*HLOOKUP(CS$10,'P&L by Ctn'!$C$8:$AG$31,'P&L TOTAL 150'!$A17,0) -> 7862.4225 | CT17: =SUM(CM17:CS17) -> #REF! | CU17: =SUMIFS($C17:$CT17,$C$14:$CT$14,CU$14) -> #REF! | CV17: =SUMIFS($C17:$CT17,$C$14:$CT$14,CV$14) -> #REF! | CW17: =SUMIFS($C17:$CT17,$C$14:$CT$14,CW$14) -> #REF! | CX17: =SUMIFS($C17:$CT17,$C$14:$CT$14,CX$14) -> 9679.8678 | CY17: =SUMIFS($C17:$CT17,$C$14:$CT$14,CY$14) -> 57603.385 | CZ17: =SUMIFS($C17:$CT17,$C$14:$CT$14,CZ$14) -> 170976.34 | DA17: =SUMIFS($C17:$CT17,$C$14:$CT$14,DA$14) -> 78454.864 | DB17: =SUM(CU17:DA17) -> #REF! | DC17: =SUM(J17,R17) -> 4815092.1
A18: 6 | B18: FOB | C18: =C$16*HLOOKUP(C$10,'P&L by Ctn'!$C$8:$AG$31,'P&L TOTAL 150'!$A18,0) -> 1487325.2 | D18: =D$16*HLOOKUP(D$10,'P&L by Ctn'!$C$8:$AG$31,'P&L TOTAL 150'!$A18,0) -> 366601.43 | E18: =E$16*HLOOKUP(E$10,'P&L by Ctn'!$C$8:$AG$31,'P&L TOTAL 150'!$A18,0) -> 809687.2 | F18: =F$16*HLOOKUP(F$10,'P&L by Ctn'!$C$8:$AG$31,'P&L TOTAL 150'!$A18,0) -> 0 | G18: =G$16*HLOOKUP(G$10,'P&L by Ctn'!$C$8:$AG$31,'P&L TOTAL 150'!$A18,0) -> 0 | H18: =H$16*HLOOKUP(H$10,'P&L by Ctn'!$C$8:$AG$31,'P&L TOTAL 150'!$A18,0) -> 9912 | I18: =I$16*HLOOKUP(I$10,'P&L by Ctn'!$C$8:$AG$31,'P&L TOTAL 150'!$A18,0) -> 7114.8 | J18: =SUM(C18:I18) -> 2680640.6 | K18: =K$16*HLOOKUP(K$10,'P&L by Ctn'!$C$8:$AG$31,'P&L TOTAL 150'!$A18,0) -> 714555.21 | L18: =L$16*HLOOKUP(L$10,'P&L by Ctn'!$C$8:$AG$31,'P&L TOTAL 150'!$A18,0) -> 297863.66 | M18: =M$16*HLOOKUP(M$10,'P&L by Ctn'!$C$8:$AG$31,'P&L TOTAL 150'!$A18,0) -> 851275.45 | N18: =N$16*HLOOKUP(N$10,'P&L by Ctn'!$C$8:$AG$31,'P&L TOTAL 150'!$A18,0) -> 0 | O18: =O$16*HLOOKUP(O$10,'P&L by Ctn'!$C$8:$AG$31,'P&L TOTAL 150'!$A18,0) -> 5102.72 | P18: =P$16*HLOOKUP(P$10,'P&L by Ctn'!$C$8:$AG$31,'P&L TOTAL 150'!$A18,0) -> 9808.75 | Q18: =Q$16*HLOOKUP(Q$10,'P&L by Ctn'!$C$8:$AG$31,'P&L TOTAL 150'!$A18,0) -> 0 | R18: =SUM(K18:Q18) -> 1878605.8 | S18: =S$16*HLOOKUP(S$10,'P&L by Ctn'!$C$8:$AG$31,'P&L TOTAL 150'!$A18,0) -> 1057256.2 | T18: =T$16*HLOOKUP(T$10,'P&L by Ctn'!$C$8:$AG$31,'P&L TOTAL 150'!$A18,0) -> 252038.48 | U18: =U$16*HLOOKUP(U$10,'P&L by Ctn'!$C$8:$AG$31,'P&L TOTAL 150'!$A18,0) -> 1265760.2 | V18: =V$16*HLOOKUP(V$10,'P&L by Ctn'!$C$8:$AG$31,'P&L TOTAL 150'!$A18,0) -> 9184 | W18: =W$16*HLOOKUP(W$10,'P&L by Ctn'!$C$8:$AG$31,'P&L TOTAL 150'!$A18,0) -> 10416 | X18: =X$16*HLOOKUP(X$10,'P&L by Ctn'!$C$8:$AG$31,'P&L TOTAL 150'!$A18,0) -> 29736 | Y18: =Y$16*HLOOKUP(Y$10,'P&L by Ctn'!$C$8:$AG$31,'P&L TOTAL 150'!$A18,0) -> 14520 | Z18: =SUM(S18:Y18) -> 2638910.9 | AA18: =AA$16*HLOOKUP(AA$10,'P&L by Ctn'!$C$8:$AG$31,'P&L TOTAL 150'!$A18,0) -> 816932.65 | AB18: =AB$16*HLOOKUP(AB$10,'P&L by Ctn'!$C$8:$AG$31,'P&L TOTAL 150'!$A18,0) -> 229125.89 | AC18: =AC$16*HLOOKUP(AC$10,'P&L by Ctn'!$C$8:$AG$31,'P&L TOTAL 150'!$A18,0) -> 789834.38 | AD18: =AD$16*HLOOKUP(AD$10,'P&L by Ctn'!$C$8:$AG$31,'P&L TOTAL 150'!$A18,0) -> 0 | AE18: =AE$16*HLOOKUP(AE$10,'P&L by Ctn'!$C$8:$AG$31,'P&L TOTAL 150'!$A18,0) -> 5376 | AF18: =AF$16*HLOOKUP(AF$10,'P&L by Ctn'!$C$8:$AG$31,'P&L TOTAL 150'!$A18,0) -> 9912 | AG18: =AG$16*HLOOKUP(AG$10,'P&L by Ctn'!$C$8:$AG$31,'P&L TOTAL 150'!$A18,0) -> 7260 | AH18: =SUM(AA18:AG18) -> 1858440.9 | AI18: =AI$16*HLOOKUP(AI$10,'P&L by Ctn'!$C$8:$AG$31,'P&L TOTAL 150'!$A18,0) -> 483949.41 | AJ18: =AJ$16*HLOOKUP(AJ$10,'P&L by Ctn'!$C$8:$AG$31,'P&L TOTAL 150'!$A18,0) -> 137475.53 | AK18: =AK$16*HLOOKUP(AK$10,'P&L by Ctn'!$C$8:$AG$31,'P&L TOTAL 150'!$A18,0) -> 445547.6 | AL18: =AL$16*HLOOKUP(AL$10,'P&L by Ctn'!$C$8:$AG$31,'P&L TOTAL 150'!$A18,0) -> 0 | AM18: =AM$16*HLOOKUP(AM$10,'P&L by Ctn'!$C$8:$AG$31,'P&L TOTAL 150'!$A18,0) -> 5376 | AN18: =AN$16*HLOOKUP(AN$10,'P&L by Ctn'!$C$8:$AG$31,'P&L TOTAL 150'!$A18,0) -> 9912 | AO18: =AO$16*HLOOKUP(AO$10,'P&L by Ctn'!$C$8:$AG$31,'P&L TOTAL 150'!$A18,0) -> 7260 | AP18: =SUM(AI18:AO18) -> 1089520.5 | AQ18: =AQ$16*HLOOKUP(AQ$10,'P&L by Ctn'!$C$8:$AG$31,'P&L TOTAL 150'!$A18,0) -> 765861.46 | AR18: =AR$16*HLOOKUP(AR$10,'P&L by Ctn'!$C$8:$AG$31,'P&L TOTAL 150'!$A18,0) -> 229125.89 | AS18: =AS$16*HLOOKUP(AS$10,'P&L by Ctn'!$C$8:$AG$31,'P&L TOTAL 150'!$A18,0) -> 729077.88 | AT18: =AT$16*HLOOKUP(AT$10,'P&L by Ctn'!$C$8:$AG$31,'P&L TOTAL 150'!$A18,0) -> 0 | AU18: =AU$16*HLOOKUP(AU$10,'P&L by Ctn'!$C$8:$AG$31,'P&L TOTAL 150'!$A18,0) -> 5376 | AV18: =AV$16*HLOOKUP(AV$10,'P&L by Ctn'!$C$8:$AG$31,'P&L TOTAL 150'!$A18,0) -> 19824 | AW18: =AW$16*HLOOKUP(AW$10,'P&L by Ctn'!$C$8:$AG$31,'P&L TOTAL 150'!$A18,0) -> 7260 | AX18: =SUM(AQ18:AW18) -> 1756525.2 | AY18: =AY$16*HLOOKUP(AY$10,'P&L by Ctn'!$C$8:$AG$31,'P&L TOTAL 150'!$A18,0) -> #REF! | AZ18: =AZ$16*HLOOKUP(AZ$10,'P&L by Ctn'!$C$8:$AG$31,'P&L TOTAL 150'!$A18,0) -> #REF! | BA18: =BA$16*HLOOKUP(BA$10,'P&L by Ctn'!$C$8:$AG$31,'P&L TOTAL 150'!$A18,0) -> #REF! | BB18: =BB$16*HLOOKUP(BB$10,'P&L by Ctn'!$C$8:$AG$31,'P&L TOTAL 150'!$A18,0) -> 0 | BC18: =BC$16*HLOOKUP(BC$10,'P&L by Ctn'!$C$8:$AG$31,'P&L TOTAL 150'!$A18,0) -> 0 | BD18: =BD$16*HLOOKUP(BD$10,'P&L by Ctn'!$C$8:$AG$31,'P&L TOTAL 150'!$A18,0) -> 10320 | BE18: =BE$16*HLOOKUP(BE$10,'P&L by Ctn'!$C$8:$AG$31,'P&L TOTAL 150'!$A18,0) -> 0 | BF18: =SUM(AY18:BE18) -> #REF! | BG18: =BG$16*HLOOKUP(BG$10,'P&L by Ctn'!$C$8:$AG$31,'P&L TOTAL 150'!$A18,0) -> #REF! | BH18: =BH$16*HLOOKUP(BH$10,'P&L by Ctn'!$C$8:$AG$31,'P&L TOTAL 150'!$A18,0) -> #REF! | BI18: =BI$16*HLOOKUP(BI$10,'P&L by Ctn'!$C$8:$AG$31,'P&L TOTAL 150'!$A18,0) -> #REF! | BJ18: =BJ$16*HLOOKUP(BJ$10,'P&L by Ctn'!$C$8:$AG$31,'P&L TOTAL 150'!$A18,0) -> 0 | BK18: =BK$16*HLOOKUP(BK$10,'P&L by Ctn'!$C$8:$AG$31,'P&L TOTAL 150'!$A18,0) -> 5760 | BL18: =BL$16*HLOOKUP(BL$10,'P&L by Ctn'!$C$8:$AG$31,'P&L TOTAL 150'!$A18,0) -> 20640 | BM18: =BM$16*HLOOKUP(BM$10,'P&L by Ctn'!$C$8:$AG$31,'P&L TOTAL 150'!$A18,0) -> 7260 | BN18: =SUM(BG18:BM18) -> #REF! | BO18: =BO$16*HLOOKUP(BO$10,'P&L by Ctn'!$C$8:$AG$31,'P&L TOTAL 150'!$A18,0) -> #REF! | BP18: =BP$16*HLOOKUP(BP$10,'P&L by Ctn'!$C$8:$AG$31,'P&L TOTAL 150'!$A18,0) -> #REF! | BQ18: =BQ$16*HLOOKUP(BQ$10,'P&L by Ctn'!$C$8:$AG$31,'P&L TOTAL 150'!$A18,0) -> #REF! | BR18: =BR$16*HLOOKUP(BR$10,'P&L by Ctn'!$C$8:$AG$31,'P&L TOTAL 150'!$A18,0) -> 0 | BS18: =BS$16*HLOOKUP(BS$10,'P&L by Ctn'!$C$8:$AG$31,'P&L TOTAL 150'!$A18,0) -> 5760 | BT18: =BT$16*HLOOKUP(BT$10,'P&L by Ctn'!$C$8:$AG$31,'P&L TOTAL 150'!$A18,0) -> 10320 | BU18: =BU$16*HLOOKUP(BU$10,'P&L by Ctn'!$C$8:$AG$31,'P&L TOTAL 150'!$A18,0) -> 7260 | BV18: =SUM(BO18:BU18) -> #REF! | BW18: =BW$16*HLOOKUP(BW$10,'P&L by Ctn'!$C$8:$AG$31,'P&L TOTAL 150'!$A18,0) -> #REF! | BX18: =BX$16*HLOOKUP(BX$10,'P&L by Ctn'!$C$8:$AG$31,'P&L TOTAL 150'!$A18,0) -> #REF! | BY18: =BY$16*HLOOKUP(BY$10,'P&L by Ctn'!$C$8:$AG$31,'P&L TOTAL 150'!$A18,0) -> #REF! | BZ18: =BZ$16*HLOOKUP(BZ$10,'P&L by Ctn'!$C$8:$AG$31,'P&L TOTAL 150'!$A18,0) -> 0 | CA18: =CA$16*HLOOKUP(CA$10,'P&L by Ctn'!$C$8:$AG$31,'P&L TOTAL 150'!$A18,0) -> 5760 | CB18: =CB$16*HLOOKUP(CB$10,'P&L by Ctn'!$C$8:$AG$31,'P&L TOTAL 150'!$A18,0) -> 10320 | CC18: =CC$16*HLOOKUP(CC$10,'P&L by Ctn'!$C$8:$AG$31,'P&L TOTAL 150'!$A18,0) -> 0 | CD18: =SUM(BW18:CC18) -> #REF! | CE18: =CE$16*HLOOKUP(CE$10,'P&L by Ctn'!$C$8:$AG$31,'P&L TOTAL 150'!$A18,0) -> #REF! | CF18: =CF$16*HLOOKUP(CF$10,'P&L by Ctn'!$C$8:$AG$31,'P&L TOTAL 150'!$A18,0) -> #REF! | CG18: =CG$16*HLOOKUP(CG$10,'P&L by Ctn'!$C$8:$AG$31,'P&L TOTAL 150'!$A18,0) -> #REF! | CH18: =CH$16*HLOOKUP(CH$10,'P&L by Ctn'!$C$8:$AG$31,'P&L TOTAL 150'!$A18,0) -> 0 | CI18: =CI$16*HLOOKUP(CI$10,'P&L by Ctn'!$C$8:$AG$31,'P&L TOTAL 150'!$A18,0) -> 0 | CJ18: =CJ$16*HLOOKUP(CJ$10,'P&L by Ctn'!$C$8:$AG$31,'P&L TOTAL 150'!$A18,0) -> 10320 | CK18: =CK$16*HLOOKUP(CK$10,'P&L by Ctn'!$C$8:$AG$31,'P&L TOTAL 150'!$A18,0) -> 7260 | CL18: =SUM(CE18:CK18) -> #REF! | CM18: =CM$16*HLOOKUP(CM$10,'P&L by Ctn'!$C$8:$AG$31,'P&L TOTAL 150'!$A18,0) -> #REF! | CN18: =CN$16*HLOOKUP(CN$10,'P&L by Ctn'!$C$8:$AG$31,'P&L TOTAL 150'!$A18,0) -> #REF! | CO18: =CO$16*HLOOKUP(CO$10,'P&L by Ctn'!$C$8:$AG$31,'P&L TOTAL 150'!$A18,0) -> #REF! | CP18: =CP$16*HLOOKUP(CP$10,'P&L by Ctn'!$C$8:$AG$31,'P&L TOTAL 150'!$A18,0) -> 0 | CQ18: =CQ$16*HLOOKUP(CQ$10,'P&L by Ctn'!$C$8:$AG$31,'P&L TOTAL 150'!$A18,0) -> 5760 | CR18: =CR$16*HLOOKUP(CR$10,'P&L by Ctn'!$C$8:$AG$31,'P&L TOTAL 150'!$A18,0) -> 10320 | CS18: =CS$16*HLOOKUP(CS$10,'P&L by Ctn'!$C$8:$AG$31,'P&L TOTAL 150'!$A18,0) -> 7260 | CT18: =SUM(CM18:CS18) -> #REF! | CU18: =SUMIFS($C18:$CT18,$C$14:$CT$14,CU$14) -> #REF! | CV18: =SUMIFS($C18:$CT18,$C$14:$CT$14,CV$14) -> #REF! | CW18: =SUMIFS($C18:$CT18,$C$14:$CT$14,CW$14) -> #REF! | CX18: =SUMIFS($C18:$CT18,$C$14:$CT$14,CX$14) -> 9184 | CY18: =SUMIFS($C18:$CT18,$C$14:$CT$14,CY$14) -> 54686.72 | CZ18: =SUMIFS($C18:$CT18,$C$14:$CT$14,CZ$14) -> 161344.75 | DA18: =SUMIFS($C18:$CT18,$C$14:$CT$14,DA$14) -> 72454.8 | DB18: =SUM(CU18:DA18) -> #REF! | DC18: =SUM(J18,R18) -> 4559246.4
A19: 7 | B19: COGS | C19: =C$16*3.56413598195 -> 924622.41 | D19: =D$16*3.99304894848 -> 255555.13 | E19: =E$16*4.71581901013 -> 669316.19 | F19: =F$16*HLOOKUP(F$10,'P&L by Ctn'!$C$8:$AG$31,'P&L TOTAL 150'!$A19,0) -> 0 | G19: =G$16*HLOOKUP(G$10,'P&L by Ctn'!$C$8:$AG$31,'P&L TOTAL 150'!$A19,0) -> 0 | H19: =H$16*2.59998957605 -> 6239.975 | I19: =I$16*3.79029334655 -> 4457.385 | J19: =SUM(C19:I19) -> 1860191.1 | K19: =K$16*3.80167859783 -> 473822.21 | L19: =L$16*4.1428912669 -> 215430.35 | M19: =M$16*4.99930685414 -> 745996.57 | N19: =N$16*HLOOKUP(N$10,'P&L by Ctn'!$C$8:$AG$31,'P&L TOTAL 150'!$A19,0) -> 0 | O19: =O$16*2.34330836385 -> 2669.0282 | P19: =P$16*2.73075243152 -> 6485.537 | Q19: =Q$16*HLOOKUP(Q$10,'P&L by Ctn'!$C$8:$AG$31,'P&L TOTAL 150'!$A19,0) -> 0 | R19: =SUM(K19:Q19) -> 1444403.7 | S19: =S$16*3.80167859783 -> 701067.55 | T19: =T$16*4.1428912669 -> 182287.22 | U19: =U$16*4.99930685414 -> 1109221.2 | V19: =V$16*HLOOKUP(V$10,'P&L by Ctn'!$C$8:$AG$31,'P&L TOTAL 150'!$A19,0) -> 6207.0379 | W19: =W$16*2.34330836385 -> 5448.1919 | X19: =X$16*2.73075243152 -> 19661.418 | Y19: =Y$16*HLOOKUP(Y$10,'P&L by Ctn'!$C$8:$AG$31,'P&L TOTAL 150'!$A19,0) -> 9458.2455 | Z19: =SUM(S19:Y19) -> 2033350.9 | AA19: =AA$16*VLOOKUP(AA14,Table3[#All],IF(AA11="q2",3,5),0) -> 563144.44 | AB19: =AB$16*VLOOKUP(AB14,Table3[#All],IF(AA11="q2",3,5),0) -> 177352.11 | AC19: =AC$16*VLOOKUP(AC14,Table3[#All],IF(AA11="q2",3,5),0) -> 723840 | AD19: =AD$16*VLOOKUP(AD14,Table3[#All],IF(AA11="q2",3,5),0) -> 0 | AE19: =AE$16*VLOOKUP(AE14,Table3[#All],IF(AA11="q2",3,5),0) -> 3330.2535 | AF19: =AF$16*VLOOKUP(AF14,Table3[#All],IF(AA11="q2",3,5),0) -> 6589.5211 | AG19: =AG$16*VLOOKUP(AG14,Table3[#All],IF(AA11="q2",3,5),0) -> 4822.9859 | AH19: =SUM(AA19:AG19) -> 1479079.3 | AI19: =AI$16*VLOOKUP(AI14,Table3[#All],IF(AI11="q2",3,5),0) -> 333605.74 | AJ19: =AJ$16*VLOOKUP(AJ14,Table3[#All],IF(AI11="q2",3,5),0) -> 106411.27 | AK19: =AK$16*VLOOKUP(AK14,Table3[#All],IF(AI11="q2",3,5),0) -> 408320 | AL19: =AL$16*VLOOKUP(AL14,Table3[#All],IF(AI11="q2",3,5),0) -> 0 | AM19: =AM$16*VLOOKUP(AM14,Table3[#All],IF(AI11="q2",3,5),0) -> 3330.2535 | AN19: =AN$16*VLOOKUP(AN14,Table3[#All],IF(AI11="q2",3,5),0) -> 6589.5211 | AO19: =AO$16*VLOOKUP(AO14,Table3[#All],IF(AI11="q2",3,5),0) -> 4822.9859 | AP19: =SUM(AI19:AO19) -> 863079.76 | AQ19: =AQ$16*VLOOKUP(AQ14,Table3[#All],IF(AQ11="q2",3,5),0) -> 527939.02 | AR19: =AR$16*VLOOKUP(AR14,Table3[#All],IF(AQ11="q2",3,5),0) -> 177352.11 | AS19: =AS$16*VLOOKUP(AS14,Table3[#All],IF(AQ11="q2",3,5),0) -> 668160 | AT19: =AT$16*VLOOKUP(AT14,Table3[#All],IF(AQ11="q2",3,5),0) -> 0 | AU19: =AU$16*VLOOKUP(AU14,Table3[#All],IF(AQ11="q2",3,5),0) -> 3330.2535 | AV19: =AV$16*VLOOKUP(AV14,Table3[#All],IF(AQ11="q2",3,5),0) -> 13179.042 | AW19: =AW$16*VLOOKUP(AW14,Table3[#All],IF(AQ11="q2",3,5),0) -> 4822.9859 | AX19: =SUM(AQ19:AW19) -> 1394783.4 | AY19: =AY$16*VLOOKUP(AY14,Table3[#All],IF(AY11="q2",3,5),0) -> 544152.34 | AZ19: =AZ$16*VLOOKUP(AZ14,Table3[#All],IF(AY11="q2",3,5),0) -> 170005.63 | BA19: =BA$16*VLOOKUP(BA14,Table3[#All],IF(AY11="q2",3,5),0) -> 651310 | BB19: =BB$16*VLOOKUP(BB14,Table3[#All],IF(AY11="q2",3,5),0) -> 0 | BC19: =BC$16*VLOOKUP(BC14,Table3[#All],IF(AY11="q2",3,5),0) -> 0 | BD19: =BD$16*VLOOKUP(BD14,Table3[#All],IF(AY11="q2",3,5),0) -> 7212.169 | BE19: =BE$16*VLOOKUP(BE14,Table3[#All],IF(AY11="q2",3,5),0) -> 0 | BF19: =SUM(AY19:BE19) -> 1372680.1 | BG19: =BG$16*VLOOKUP(BG14,Table3[#All],IF(BG11="q2",3,5),0) -> 480667.9 | BH19: =BH$16*VLOOKUP(BH14,Table3[#All],IF(BG11="q2",3,5),0) -> 170005.63 | BI19: =BI$16*VLOOKUP(BI14,Table3[#All],IF(BG11="q2",3,5),0) -> 672320 | BJ19: =BJ$16*VLOOKUP(BJ14,Table3[#All],IF(BG11="q2",3,5),0) -> 0 | BK19: =BK$16*VLOOKUP(BK14,Table3[#All],IF(BG11="q2",3,5),0) -> 3665.9155 | BL19: =BL$16*VLOOKUP(BL14,Table3[#All],IF(BG11="q2",3,5),0) -> 14424.338 | BM19: =BM$16*VLOOKUP(BM14,Table3[#All],IF(BG11="q2",3,5),0) -> 5046.0845 | BN19: =SUM(BG19:BM19) -> 1346129.9 | BO19: =BO$16*VLOOKUP(BO14,Table3[#All],IF(BO11="q2",3,5),0) -> 616705.98 | BP19: =BP$16*VLOOKUP(BP14,Table3[#All],IF(BO11="q2",3,5),0) -> 233757.75 | BQ19: =BQ$16*VLOOKUP(BQ14,Table3[#All],IF(BO11="q2",3,5),0) -> 861410 | BR19: =BR$16*VLOOKUP(BR14,Table3[#All],IF(BO11="q2",3,5),0) -> 0 | BS19: =BS$16*VLOOKUP(BS14,Table3[#All],IF(BO11="q2",3,5),0) -> 3665.9155 | BT19: =BT$16*VLOOKUP(BT14,Table3[#All],IF(BO11="q2",3,5),0) -> 7212.169 | BU19: =BU$16*VLOOKUP(BU14,Table3[#All],IF(BO11="q2",3,5),0) -> 5046.0845 | BV19: =SUM(BO19:BU19) -> 1727797.9 | BW19: =BW$16*VLOOKUP(BW14,Table3[#All],IF(BW11="q2",3,5),0) -> 453460.28 | BX19: =BX$16*VLOOKUP(BX14,Table3[#All],IF(BW11="q2",3,5),0) -> 191256.34 | BY19: =BY$16*VLOOKUP(BY14,Table3[#All],IF(BW11="q2",3,5),0) -> 672320 | BZ19: =BZ$16*VLOOKUP(BZ14,Table3[#All],IF(BW11="q2",3,5),0) -> 0 | CA19: =CA$16*VLOOKUP(CA14,Table3[#All],IF(BW11="q2",3,5),0) -> 3665.9155 | CB19: =CB$16*VLOOKUP(CB14,Table3[#All],IF(BW11="q2",3,5),0) -> 7212.169 | CC19: =CC$16*VLOOKUP(CC14,Table3[#All],IF(BW11="q2",3,5),0) -> 0 | CD19: =SUM(BW19:CC19) -> 1327914.7 | CE19: =CE$16*VLOOKUP(CE14,Table3[#All],IF(CE11="q2",3,5),0) -> 480667.9 | CF19: =CF$16*VLOOKUP(CF14,Table3[#All],IF(CE11="q2",3,5),0) -> 170005.63 | CG19: =CG$16*VLOOKUP(CG14,Table3[#All],IF(CE11="q2",3,5),0) -> 693330 | CH19: =CH$16*VLOOKUP(CH14,Table3[#All],IF(CE11="q2",3,5),0) -> 0 | CI19: =CI$16*VLOOKUP(CI14,Table3[#All],IF(CE11="q2",3,5),0) -> 0 | CJ19: =CJ$16*VLOOKUP(CJ14,Table3[#All],IF(CE11="q2",3,5),0) -> 7212.169 | CK19: =CK$16*VLOOKUP(CK14,Table3[#All],IF(CE11="q2",3,5),0) -> 5046.0845 | CL19: =SUM(CE19:CK19) -> 1356261.8 | CM19: =CM$16*VLOOKUP(CM14,Table3[#All],IF(CM11="q2",3,5),0) -> 752060.13 | CN19: =CN$16*VLOOKUP(CN14,Table3[#All],IF(CM11="q2",3,5),0) -> 233757.75 | CO19: =CO$16*VLOOKUP(CO14,Table3[#All],IF(CM11="q2",3,5),0) -> 861410 | CP19: =CP$16*VLOOKUP(CP14,Table3[#All],IF(CM11="q2",3,5),0) -> 0 | CQ19: =CQ$16*VLOOKUP(CQ14,Table3[#All],IF(CM11="q2",3,5),0) -> 3665.9155 | CR19: =CR$16*VLOOKUP(CR14,Table3[#All],IF(CM11="q2",3,5),0) -> 7212.169 | CS19: =CS$16*VLOOKUP(CS14,Table3[#All],IF(CM11="q2",3,5),0) -> 5046.0845 | CT19: =SUM(CM19:CS19) -> 1863152 | CU19: =SUMIFS($C19:$CT19,$C$14:$CT$14,CU$14) -> 6851915.9 | CV19: =SUMIFS($C19:$CT19,$C$14:$CT$14,CV$14) -> 2283176.9 | CW19: =SUMIFS($C19:$CT19,$C$14:$CT$14,CW$14) -> 8736954 | CX19: =SUMIFS($C19:$CT19,$C$14:$CT$14,CX$14) -> 6207.0379 | CY19: =SUMIFS($C19:$CT19,$C$14:$CT$14,CY$14) -> 32771.643 | CZ19: =SUMIFS($C19:$CT19,$C$14:$CT$14,CZ$14) -> 109230.2 | DA19: =SUMIFS($C19:$CT19,$C$14:$CT$14,DA$14) -> 48568.926 | DB19: =SUM(CU19:DA19) -> 18068825 | DC19: =SUM(J19,R19) -> 3304594.8
B20: GP1 | C20: =C18-C19 -> 562702.74 | D20: =D18-D19 -> 111046.29 | E20: =E18-E19 -> 140371.01 | F20: =F18-F19 -> 0 | G20: =G18-G19 -> 0 | H20: =H18-H19 -> 3672.025 | I20: =I18-I19 -> 2657.415 | J20: =J18-J19 -> 820449.49 | ... DC20: =DC18-DC19 -> 1254651.6
B21: GP1% | C21: =IFERROR(C20/C$18,0) -> 0.37833203 | D21: =IFERROR(D20/D$18,0) -> 0.30290742 | E21: =IFERROR(E20/E$18,0) -> 0.17336449 | F21: =IFERROR(F20/F$18,0) -> 0 | G21: =IFERROR(G20/G$18,0) -> 0 | H21: =IFERROR(H20/H$18,0) -> 0.37046257 | I21: =IFERROR(I20/I$18,0) -> 0.37350523 | J21: =IFERROR(J20/J$18,0) -> 0.30606471 | ... DC21: =IFERROR(DC20/DC$18,0) -> 0.27518837
A22: 10 | B22: TP | C22: 201344 | D22: 48000 | E22: 89592 | F22: =F$16*HLOOKUP(F$10,'P&L by Ctn'!$C$8:$AG$31,'P&L TOTAL 150'!$A22,0) -> 0 | G22: =G$16*HLOOKUP(G$10,'P&L by Ctn'!$C$8:$AG$31,'P&L TOTAL 150'!$A22,0) -> 0 | H22: 2472 | I22: 2116.8 | J22: =SUM(C22:I22) -> 343524.8 | K22: =K$16*HLOOKUP(K$10,'P&L by Ctn'!$C$8:$AG$31,'P&L TOTAL 150'!$A22,0) -> 98935.555 | L22: =L$16*HLOOKUP(L$10,'P&L by Ctn'!$C$8:$AG$31,'P&L TOTAL 150'!$A22,0) -> 41026.66 | M22: =M$16*HLOOKUP(M$10,'P&L by Ctn'!$C$8:$AG$31,'P&L TOTAL 150'!$A22,0) -> 96544.887 | N22: =N$16*HLOOKUP(N$10,'P&L by Ctn'!$C$8:$AG$31,'P&L TOTAL 150'!$A22,0) -> 0 | O22: =O$16*HLOOKUP(O$10,'P&L by Ctn'!$C$8:$AG$31,'P&L TOTAL 150'!$A22,0) -> 1161.78 | P22: =P$16*HLOOKUP(P$10,'P&L by Ctn'!$C$8:$AG$31,'P&L TOTAL 150'!$A22,0) -> 2446.25 | Q22: =Q$16*HLOOKUP(Q$10,'P&L by Ctn'!$C$8:$AG$31,'P&L TOTAL 150'!$A22,0) -> 0 | R22: =SUM(K22:Q22) -> 240115.13 | S22: =S$16*HLOOKUP(S$10,'P&L by Ctn'!$C$8:$AG$31,'P&L TOTAL 150'!$A22,0) -> 146385.09 | T22: =T$16*HLOOKUP(T$10,'P&L by Ctn'!$C$8:$AG$31,'P&L TOTAL 150'!$A22,0) -> 34714.866 | U22: =U$16*HLOOKUP(U$10,'P&L by Ctn'!$C$8:$AG$31,'P&L TOTAL 150'!$A22,0) -> 143552.45 | V22: =V$16*HLOOKUP(V$10,'P&L by Ctn'!$C$8:$AG$31,'P&L TOTAL 150'!$A22,0) -> 1280 | W22: =W$16*HLOOKUP(W$10,'P&L by Ctn'!$C$8:$AG$31,'P&L TOTAL 150'!$A22,0) -> 2371.5 | X22: =X$16*HLOOKUP(X$10,'P&L by Ctn'!$C$8:$AG$31,'P&L TOTAL 150'!$A22,0) -> 7416 | Y22: =Y$16*HLOOKUP(Y$10,'P&L by Ctn'!$C$8:$AG$31,'P&L TOTAL 150'!$A22,0) -> 4320 | Z22: =SUM(S22:Y22) -> 340039.91 | AA22: =AA$16*HLOOKUP(AA$10,'P&L by Ctn'!$C$8:$AG$31,'P&L TOTAL 150'!$A22,0) -> 113110.48 | AB22: =AB$16*HLOOKUP(AB$10,'P&L by Ctn'!$C$8:$AG$31,'P&L TOTAL 150'!$A22,0) -> 31558.969 | AC22: =AC$16*HLOOKUP(AC$10,'P&L by Ctn'!$C$8:$AG$31,'P&L TOTAL 150'!$A22,0) -> 89576.73 | AD22: =AD$16*HLOOKUP(AD$10,'P&L by Ctn'!$C$8:$AG$31,'P&L TOTAL 150'!$A22,0) -> 0 | AE22: =AE$16*HLOOKUP(AE$10,'P&L by Ctn'!$C$8:$AG$31,'P&L TOTAL 150'!$A22,0) -> 1224 | AF22: =AF$16*HLOOKUP(AF$10,'P&L by Ctn'!$C$8:$AG$31,'P&L TOTAL 150'!$A22,0) -> 2472 | AG22: =AG$16*HLOOKUP(AG$10,'P&L by Ctn'!$C$8:$AG$31,'P&L TOTAL 150'!$A22,0) -> 2160 | AH22: =SUM(AA22:AG22) -> 240102.18 | AI22: =AI$16*HLOOKUP(AI$10,'P&L by Ctn'!$C$8:$AG$31,'P&L TOTAL 150'!$A22,0) -> 67006.444 | AJ22: =AJ$16*HLOOKUP(AJ$10,'P&L by Ctn'!$C$8:$AG$31,'P&L TOTAL 150'!$A22,0) -> 18935.381 | AK22: =AK$16*HLOOKUP(AK$10,'P&L by Ctn'!$C$8:$AG$31,'P&L TOTAL 150'!$A22,0) -> 50530.463 | AL22: =AL$16*HLOOKUP(AL$10,'P&L by Ctn'!$C$8:$AG$31,'P&L TOTAL 150'!$A22,0) -> 0 | AM22: =AM$16*HLOOKUP(AM$10,'P&L by Ctn'!$C$8:$AG$31,'P&L TOTAL 150'!$A22,0) -> 1224 | AN22: =AN$16*HLOOKUP(AN$10,'P&L by Ctn'!$C$8:$AG$31,'P&L TOTAL 150'!$A22,0) -> 2472 | AO22: =AO$16*HLOOKUP(AO$10,'P&L by Ctn'!$C$8:$AG$31,'P&L TOTAL 150'!$A22,0) -> 2160 | AP22: =SUM(AI22:AO22) -> 142328.29 | AQ22: =AQ$16*HLOOKUP(AQ$10,'P&L by Ctn'!$C$8:$AG$31,'P&L TOTAL 150'!$A22,0) -> 106039.29 | AR22: =AR$16*HLOOKUP(AR$10,'P&L by Ctn'!$C$8:$AG$31,'P&L TOTAL 150'!$A22,0) -> 31558.969 | AS22: =AS$16*HLOOKUP(AS$10,'P&L by Ctn'!$C$8:$AG$31,'P&L TOTAL 150'!$A22,0) -> 82686.212 | AT22: =AT$16*HLOOKUP(AT$10,'P&L by Ctn'!$C$8:$AG$31,'P&L TOTAL 150'!$A22,0) -> 0 | AU22: =AU$16*HLOOKUP(AU$10,'P&L by Ctn'!$C$8:$AG$31,'P&L TOTAL 150'!$A22,0) -> 1224 | AV22: =AV$16*HLOOKUP(AV$10,'P&L by Ctn'!$C$8:$AG$31,'P&L TOTAL 150'!$A22,0) -> 4944 | AW22: =AW$16*HLOOKUP(AW$10,'P&L by Ctn'!$C$8:$AG$31,'P&L TOTAL 150'!$A22,0) -> 2160 | AX22: =SUM(AQ22:AW22) -> 228612.47 | AY22: =AY$16*HLOOKUP(AY$10,'P&L by Ctn'!$C$8:$AG$31,'P&L TOTAL 150'!$A22,0) -> #REF! | AZ22: =AZ$16*HLOOKUP(AZ$10,'P&L by Ctn'!$C$8:$AG$31,'P&L TOTAL 150'!$A22,0) -> #REF! | BA22: =BA$16*HLOOKUP(BA$10,'P&L by Ctn'!$C$8:$AG$31,'P&L TOTAL 150'!$A22,0) -> #REF! | BB22: =BB$16*HLOOKUP(BB$10,'P&L by Ctn'!$C$8:$AG$31,'P&L TOTAL 150'!$A22,0) -> 0 | BC22: =BC$16*HLOOKUP(BC$10,'P&L by Ctn'!$C$8:$AG$31,'P&L TOTAL 150'!$A22,0) -> 0 | BD22: =BD$16*HLOOKUP(BD$10,'P&L by Ctn'!$C$8:$AG$31,'P&L TOTAL 150'!$A22,0) -> 2160 | BE22: =BE$16*HLOOKUP(BE$10,'P&L by Ctn'!$C$8:$AG$31,'P&L TOTAL 150'!$A22,0) -> 0 | BF22: =SUM(AY22:BE22) -> #REF! | BG22: =BG$16*HLOOKUP(BG$10,'P&L by Ctn'!$C$8:$AG$31,'P&L TOTAL 150'!$A22,0) -> #REF! | BH22: =BH$16*HLOOKUP(BH$10,'P&L by Ctn'!$C$8:$AG$31,'P&L TOTAL 150'!$A22,0) -> #REF! | BI22: =BI$16*HLOOKUP(BI$10,'P&L by Ctn'!$C$8:$AG$31,'P&L TOTAL 150'!$A22,0) -> #REF! | BJ22: =BJ$16*HLOOKUP(BJ$10,'P&L by Ctn'!$C$8:$AG$31,'P&L TOTAL 150'!$A22,0) -> 0 | BK22: =BK$16*HLOOKUP(BK$10,'P&L by Ctn'!$C$8:$AG$31,'P&L TOTAL 150'!$A22,0) -> 1200 | BL22: =BL$16*HLOOKUP(BL$10,'P&L by Ctn'!$C$8:$AG$31,'P&L TOTAL 150'!$A22,0) -> 4320 | BM22: =BM$16*HLOOKUP(BM$10,'P&L by Ctn'!$C$8:$AG$31,'P&L TOTAL 150'!$A22,0) -> 1740 | BN22: =SUM(BG22:BM22) -> #REF! | BO22: =BO$16*HLOOKUP(BO$10,'P&L by Ctn'!$C$8:$AG$31,'P&L TOTAL 150'!$A22,0) -> #REF! | BP22: =BP$16*HLOOKUP(BP$10,'P&L by Ctn'!$C$8:$AG$31,'P&L TOTAL 150'!$A22,0) -> #REF! | BQ22: =BQ$16*HLOOKUP(BQ$10,'P&L by Ctn'!$C$8:$AG$31,'P&L TOTAL 150'!$A22,0) -> #REF! | BR22: =BR$16*HLOOKUP(BR$10,'P&L by Ctn'!$C$8:$AG$31,'P&L TOTAL 150'!$A22,0) -> 0 | BS22: =BS$16*HLOOKUP(BS$10,'P&L by Ctn'!$C$8:$AG$31,'P&L TOTAL 150'!$A22,0) -> 1200 | BT22: =BT$16*HLOOKUP(BT$10,'P&L by Ctn'!$C$8:$AG$31,'P&L TOTAL 150'!$A22,0) -> 2160 | BU22: =BU$16*HLOOKUP(BU$10,'P&L by Ctn'!$C$8:$AG$31,'P&L TOTAL 150'!$A22,0) -> 1740 | BV22: =SUM(BO22:BU22) -> #REF! | BW22: =BW$16*HLOOKUP(BW$10,'P&L by Ctn'!$C$8:$AG$31,'P&L TOTAL 150'!$A22,0) -> #REF! | BX22: =BX$16*HLOOKUP(BX$10,'P&L by Ctn'!$C$8:$AG$31,'P&L TOTAL 150'!$A22,0) -> #REF! | BY22: =BY$16*HLOOKUP(BY$10,'P&L by Ctn'!$C$8:$AG$31,'P&L TOTAL 150'!$A22,0) -> #REF! | BZ22: =BZ$16*HLOOKUP(BZ$10,'P&L by Ctn'!$C$8:$AG$31,'P&L TOTAL 150'!$A22,0) -> 0 | CA22: =CA$16*HLOOKUP(CA$10,'P&L by Ctn'!$C$8:$AG$31,'P&L TOTAL 150'!$A22,0) -> 1200 | CB22: =CB$16*HLOOKUP(CB$10,'P&L by Ctn'!$C$8:$AG$31,'P&L TOTAL 150'!$A22,0) -> 2160 | CC22: =CC$16*HLOOKUP(CC$10,'P&L by Ctn'!$C$8:$AG$31,'P&L TOTAL 150'!$A22,0) -> 0 | CD22: =SUM(BW22:CC22) -> #REF! | CE22: =CE$16*HLOOKUP(CE$10,'P&L by Ctn'!$C$8:$AG$31,'P&L TOTAL 150'!$A22,0) -> #REF! | CF22: =CF$16*HLOOKUP(CF$10,'P&L by Ctn'!$C$8:$AG$31,'P&L TOTAL 150'!$A22,0) -> #REF! | CG22: =CG$16*HLOOKUP(CG$10,'P&L by Ctn'!$C$8:$AG$31,'P&L TOTAL 150'!$A22,0) -> #REF! | CH22: =CH$16*HLOOKUP(CH$10,'P&L by Ctn'!$C$8:$AG$31,'P&L TOTAL 150'!$A22,0) -> 0 | CI22: =CI$16*HLOOKUP(CI$10,'P&L by Ctn'!$C$8:$AG$31,'P&L TOTAL 150'!$A22,0) -> 0 | CJ22: =CJ$16*HLOOKUP(CJ$10,'P&L by Ctn'!$C$8:$AG$31,'P&L TOTAL 150'!$A22,0) -> 2160 | CK22: =CK$16*HLOOKUP(CK$10,'P&L by Ctn'!$C$8:$AG$31,'P&L TOTAL 150'!$A22,0) -> 1740 | CL22: =SUM(CE22:CK22) -> #REF! | CM22: =CM$16*HLOOKUP(CM$10,'P&L by Ctn'!$C$8:$AG$31,'P&L TOTAL 150'!$A22,0) -> #REF! | CN22: =CN$16*HLOOKUP(CN$10,'P&L by Ctn'!$C$8:$AG$31,'P&L TOTAL 150'!$A22,0) -> #REF! | CO22: =CO$16*HLOOKUP(CO$10,'P&L by Ctn'!$C$8:$AG$31,'P&L TOTAL 150'!$A22,0) -> #REF! | CP22: =CP$16*HLOOKUP(CP$10,'P&L by Ctn'!$C$8:$AG$31,'P&L TOTAL 150'!$A22,0) -> 0 | CQ22: =CQ$16*HLOOKUP(CQ$10,'P&L by Ctn'!$C$8:$AG$31,'P&L TOTAL 150'!$A22,0) -> 1200 | CR22: =CR$16*HLOOKUP(CR$10,'P&L by Ctn'!$C$8:$AG$31,'P&L TOTAL 150'!$A22,0) -> 2160 | CS22: =CS$16*HLOOKUP(CS$10,'P&L by Ctn'!$C$8:$AG$31,'P&L TOTAL 150'!$A22,0) -> 1740 | CT22: =SUM(CM22:CS22) -> #REF! | CU22: =SUMIFS($C22:$CT22,$C$14:$CT$14,CU$14) -> #REF! | CV22: =SUMIFS($C22:$CT22,$C$14:$CT$14,CV$14) -> #REF! | CW22: =SUMIFS($C22:$CT22,$C$14:$CT$14,CW$14) -> #REF! | CX22: =SUMIFS($C22:$CT22,$C$14:$CT$14,CX$14) -> 1280 | CY22: =SUMIFS($C22:$CT22,$C$14:$CT$14,CY$14) -> 12005.28 | CZ22: =SUMIFS($C22:$CT22,$C$14:$CT$14,CZ$14) -> 37342.25 | DA22: =SUMIFS($C22:$CT22,$C$14:$CT$14,DA$14) -> 19876.8 | DB22: =SUM(CU22:DA22) -> #REF! | DC22: =SUM(J22,R22) -> 583639.93 | DE22: =SUM(DB22,DB24)/$DB$18 -> #REF!
B23: TP% | C23: =IFERROR(C22/C$18,0) -> 0.13537322 | D23: =IFERROR(D22/D$18,0) -> 0.13093239 | E23: =IFERROR(E22/E$18,0) -> 0.11065014 | F23: =IFERROR(F22/F$18,0) -> 0 | G23: =IFERROR(G22/G$18,0) -> 0 | H23: =IFERROR(H22/H$18,0) -> 0.24939467 | I23: =IFERROR(I22/I$18,0) -> 0.29752066 | J23: =IFERROR(J22/J$18,0) -> 0.12815026 | ... DC23: =IFERROR(DC22/DC$18,0) -> 0.12801237
A24: 13 | B24: MF | C24: 260198.4 | D24: 33600 | E24: =E$16*HLOOKUP(E$10,'P&L by Ctn'!$C$8:$AG$31,'P&L TOTAL 150'!$A24,0) -> 0 | F24: =F$16*HLOOKUP(F$10,'P&L by Ctn'!$C$8:$AG$31,'P&L TOTAL 150'!$A24,0) -> 0 | G24: =G$16*HLOOKUP(G$10,'P&L by Ctn'!$C$8:$AG$31,'P&L TOTAL 150'!$A24,0) -> 0 | H24: =H$16*HLOOKUP(H$10,'P&L by Ctn'!$C$8:$AG$31,'P&L TOTAL 150'!$A24,0) -> 0 | I24: =I$16*HLOOKUP(I$10,'P&L by Ctn'!$C$8:$AG$31,'P&L TOTAL 150'!$A24,0) -> 0 | J24: =SUM(C24:I24) -> 293798.4 | K24: =K$16*HLOOKUP(K$10,'P&L by Ctn'!$C$8:$AG$31,'P&L TOTAL 150'!$A24,0) -> 110316.05 | L24: =L$16*HLOOKUP(L$10,'P&L by Ctn'!$C$8:$AG$31,'P&L TOTAL 150'!$A24,0) -> 20517.433 | M24: =M$16*HLOOKUP(M$10,'P&L by Ctn'!$C$8:$AG$31,'P&L TOTAL 150'!$A24,0) -> 0 | N24: =N$16*HLOOKUP(N$10,'P&L by Ctn'!$C$8:$AG$31,'P&L TOTAL 150'!$A24,0) -> 0 | O24: =O$16*HLOOKUP(O$10,'P&L by Ctn'!$C$8:$AG$31,'P&L TOTAL 150'!$A24,0) -> 0 | P24: =P$16*HLOOKUP(P$10,'P&L by Ctn'!$C$8:$AG$31,'P&L TOTAL 150'!$A24,0) -> 0 | Q24: =Q$16*HLOOKUP(Q$10,'P&L by Ctn'!$C$8:$AG$31,'P&L TOTAL 150'!$A24,0) -> 0 | R24: =SUM(K24:Q24) -> 130833.48 | S24: =S$16*HLOOKUP(S$10,'P&L by Ctn'!$C$8:$AG$31,'P&L TOTAL 150'!$A24,0) -> 163223.67 | T24: =T$16*HLOOKUP(T$10,'P&L by Ctn'!$C$8:$AG$31,'P&L TOTAL 150'!$A24,0) -> 17360.905 | U24: =U$16*HLOOKUP(U$10,'P&L by Ctn'!$C$8:$AG$31,'P&L TOTAL 150'!$A24,0) -> 0 | V24: =V$16*HLOOKUP(V$10,'P&L by Ctn'!$C$8:$AG$31,'P&L TOTAL 150'!$A24,0) -> 0 | W24: =W$16*HLOOKUP(W$10,'P&L by Ctn'!$C$8:$AG$31,'P&L TOTAL 150'!$A24,0) -> 0 | X24: =X$16*HLOOKUP(X$10,'P&L by Ctn'!$C$8:$AG$31,'P&L TOTAL 150'!$A24,0) -> 0 | Y24: =Y$16*HLOOKUP(Y$10,'P&L by Ctn'!$C$8:$AG$31,'P&L TOTAL 150'!$A24,0) -> 0 | Z24: =SUM(S24:Y24) -> 180584.58 | AA24: =AA$16*HLOOKUP(AA$10,'P&L by Ctn'!$C$8:$AG$31,'P&L TOTAL 150'!$A24,0) -> 126121.51 | AB24: =AB$16*HLOOKUP(AB$10,'P&L by Ctn'!$C$8:$AG$31,'P&L TOTAL 150'!$A24,0) -> 15782.641 | AC24: =AC$16*HLOOKUP(AC$10,'P&L by Ctn'!$C$8:$AG$31,'P&L TOTAL 150'!$A24,0) -> 0 | AD24: =AD$16*HLOOKUP(AD$10,'P&L by Ctn'!$C$8:$AG$31,'P&L TOTAL 150'!$A24,0) -> 0 | AE24: =AE$16*HLOOKUP(AE$10,'P&L by Ctn'!$C$8:$AG$31,'P&L TOTAL 150'!$A24,0) -> 0 | AF24: =AF$16*HLOOKUP(AF$10,'P&L by Ctn'!$C$8:$AG$31,'P&L TOTAL 150'!$A24,0) -> 0 | AG24: =AG$16*HLOOKUP(AG$10,'P&L by Ctn'!$C$8:$AG$31,'P&L TOTAL 150'!$A24,0) -> 0 | AH24: =SUM(AA24:AG24) -> 141904.15 | AI24: =AI$16*AI12 -> 50647.2 | AJ24: =AJ$16*AJ12 -> 3600 | AK24: =AK$16*AK12 -> 0 | AL24: =AL$16*AL12 -> 0 | AM24: =AM$16*AM12 -> 0 | AN24: =AN$16*AN12 -> 0 | AO24: =AO$16*AO12 -> 0 | AP24: =SUM(AI24:AO24) -> 54247.2 | AQ24: =AQ$16*AQ12 -> 80150.4 | AR24: =AR$16*AR12 -> 6000 | AS24: =AS$16*AS12 -> 0 | AT24: =AT$16*AT12 -> 0 | AU24: =AU$16*AU12 -> 0 | AV24: =AV$16*AV12 -> 0 | AW24: =AW$16*AW12 -> 0 | AX24: =SUM(AQ24:AW24) -> 86150.4 | AY24: =AY$16*HLOOKUP(AY$10,'P&L by Ctn'!$C$8:$AG$31,'P&L TOTAL 150'!$A24,0) -> #REF! | AZ24: =AZ$16*HLOOKUP(AZ$10,'P&L by Ctn'!$C$8:$AG$31,'P&L TOTAL 150'!$A24,0) -> #REF! | BA24: =BA$16*HLOOKUP(BA$10,'P&L by Ctn'!$C$8:$AG$31,'P&L TOTAL 150'!$A24,0) -> #REF! | BB24: =BB$16*HLOOKUP(BB$10,'P&L by Ctn'!$C$8:$AG$31,'P&L TOTAL 150'!$A24,0) -> 0 | BC24: =BC$16*HLOOKUP(BC$10,'P&L by Ctn'!$C$8:$AG$31,'P&L TOTAL 150'!$A24,0) -> 0 | BD24: =BD$16*HLOOKUP(BD$10,'P&L by Ctn'!$C$8:$AG$31,'P&L TOTAL 150'!$A24,0) -> 0 | BE24: =BE$16*HLOOKUP(BE$10,'P&L by Ctn'!$C$8:$AG$31,'P&L TOTAL 150'!$A24,0) -> 0 | BF24: =SUM(AY24:BE24) -> #REF! | BG24: =BG$16*HLOOKUP(BG$10,'P&L by Ctn'!$C$8:$AG$31,'P&L TOTAL 150'!$A24,0) -> #REF! | BH24: =BH$16*HLOOKUP(BH$10,'P&L by Ctn'!$C$8:$AG$31,'P&L TOTAL 150'!$A24,0) -> #REF! | BI24: =BI$16*HLOOKUP(BI$10,'P&L by Ctn'!$C$8:$AG$31,'P&L TOTAL 150'!$A24,0) -> #REF! | BJ24: =BJ$16*HLOOKUP(BJ$10,'P&L by Ctn'!$C$8:$AG$31,'P&L TOTAL 150'!$A24,0) -> 0 | BK24: =BK$16*HLOOKUP(BK$10,'P&L by Ctn'!$C$8:$AG$31,'P&L TOTAL 150'!$A24,0) -> 0 | BL24: =BL$16*HLOOKUP(BL$10,'P&L by Ctn'!$C$8:$AG$31,'P&L TOTAL 150'!$A24,0) -> 0 | BM24: =BM$16*HLOOKUP(BM$10,'P&L by Ctn'!$C$8:$AG$31,'P&L TOTAL 150'!$A24,0) -> 0 | BN24: =SUM(BG24:BM24) -> #REF! | BO24: =BO$16*HLOOKUP(BO$10,'P&L by Ctn'!$C$8:$AG$31,'P&L TOTAL 150'!$A24,0) -> #REF! | BP24: =BP$16*HLOOKUP(BP$10,'P&L by Ctn'!$C$8:$AG$31,'P&L TOTAL 150'!$A24,0) -> #REF! | BQ24: =BQ$16*HLOOKUP(BQ$10,'P&L by Ctn'!$C$8:$AG$31,'P&L TOTAL 150'!$A24,0) -> #REF! | BR24: =BR$16*HLOOKUP(BR$10,'P&L by Ctn'!$C$8:$AG$31,'P&L TOTAL 150'!$A24,0) -> 0 | BS24: =BS$16*HLOOKUP(BS$10,'P&L by Ctn'!$C$8:$AG$31,'P&L TOTAL 150'!$A24,0) -> 0 | BT24: =BT$16*HLOOKUP(BT$10,'P&L by Ctn'!$C$8:$AG$31,'P&L TOTAL 150'!$A24,0) -> 0 | BU24: =BU$16*HLOOKUP(BU$10,'P&L by Ctn'!$C$8:$AG$31,'P&L TOTAL 150'!$A24,0) -> 0 | BV24: =SUM(BO24:BU24) -> #REF! | BW24: =BW$16*HLOOKUP(BW$10,'P&L by Ctn'!$C$8:$AG$31,'P&L TOTAL 150'!$A24,0) -> #REF! | BX24: =BX$16*HLOOKUP(BX$10,'P&L by Ctn'!$C$8:$AG$31,'P&L TOTAL 150'!$A24,0) -> #REF! | BY24: =BY$16*HLOOKUP(BY$10,'P&L by Ctn'!$C$8:$AG$31,'P&L TOTAL 150'!$A24,0) -> #REF! | BZ24: =BZ$16*HLOOKUP(BZ$10,'P&L by Ctn'!$C$8:$AG$31,'P&L TOTAL 150'!$A24,0) -> 0 | CA24: =CA$16*HLOOKUP(CA$10,'P&L by Ctn'!$C$8:$AG$31,'P&L TOTAL 150'!$A24,0) -> 0 | CB24: =CB$16*HLOOKUP(CB$10,'P&L by Ctn'!$C$8:$AG$31,'P&L TOTAL 150'!$A24,0) -> 0 | CC24: =CC$16*HLOOKUP(CC$10,'P&L by Ctn'!$C$8:$AG$31,'P&L TOTAL 150'!$A24,0) -> 0 | CD24: =SUM(BW24:CC24) -> #REF! | CE24: =CE$16*HLOOKUP(CE$10,'P&L by Ctn'!$C$8:$AG$31,'P&L TOTAL 150'!$A24,0) -> #REF! | CF24: =CF$16*HLOOKUP(CF$10,'P&L by Ctn'!$C$8:$AG$31,'P&L TOTAL 150'!$A24,0) -> #REF! | CG24: =CG$16*HLOOKUP(CG$10,'P&L by Ctn'!$C$8:$AG$31,'P&L TOTAL 150'!$A24,0) -> #REF! | CH24: =CH$16*HLOOKUP(CH$10,'P&L by Ctn'!$C$8:$AG$31,'P&L TOTAL 150'!$A24,0) -> 0 | CI24: =CI$16*HLOOKUP(CI$10,'P&L by Ctn'!$C$8:$AG$31,'P&L TOTAL 150'!$A24,0) -> 0 | CJ24: =CJ$16*HLOOKUP(CJ$10,'P&L by Ctn'!$C$8:$AG$31,'P&L TOTAL 150'!$A24,0) -> 0 | CK24: =CK$16*HLOOKUP(CK$10,'P&L by Ctn'!$C$8:$AG$31,'P&L TOTAL 150'!$A24,0) -> 0 | CL24: =SUM(CE24:CK24) -> #REF! | CM24: =CM$16*HLOOKUP(CM$10,'P&L by Ctn'!$C$8:$AG$31,'P&L TOTAL 150'!$A24,0) -> #REF! | CN24: =CN$16*HLOOKUP(CN$10,'P&L by Ctn'!$C$8:$AG$31,'P&L TOTAL 150'!$A24,0) -> #REF! | CO24: =CO$16*HLOOKUP(CO$10,'P&L by Ctn'!$C$8:$AG$31,'P&L TOTAL 150'!$A24,0) -> #REF! | CP24: =CP$16*HLOOKUP(CP$10,'P&L by Ctn'!$C$8:$AG$31,'P&L TOTAL 150'!$A24,0) -> 0 | CQ24: =CQ$16*HLOOKUP(CQ$10,'P&L by Ctn'!$C$8:$AG$31,'P&L TOTAL 150'!$A24,0) -> 0 | CR24: =CR$16*HLOOKUP(CR$10,'P&L by Ctn'!$C$8:$AG$31,'P&L TOTAL 150'!$A24,0) -> 0 | CS24: =CS$16*HLOOKUP(CS$10,'P&L by Ctn'!$C$8:$AG$31,'P&L TOTAL 150'!$A24,0) -> 0 | CT24: =SUM(CM24:CS24) -> #REF! | CU24: =SUMIFS($C24:$CT24,$C$14:$CT$14,CU$14) -> #REF! | CV24: =SUMIFS($C24:$CT24,$C$14:$CT$14,CV$14) -> #REF! | CW24: =SUMIFS($C24:$CT24,$C$14:$CT$14,CW$14) -> #REF! | CX24: =SUMIFS($C24:$CT24,$C$14:$CT$14,CX$14) -> 0 | CY24: =SUMIFS($C24:$CT24,$C$14:$CT$14,CY$14) -> 0 | CZ24: =SUMIFS($C24:$CT24,$C$14:$CT$14,CZ$14) -> 0 | DA24: =SUMIFS($C24:$CT24,$C$14:$CT$14,DA$14) -> 0 | DB24: =SUM(CU24:DA24) -> #REF! | DC24: =SUM(J24,R24) -> 424631.88
B25: MF% | C25: =IFERROR(C24/C$18,0) -> 0.17494386 | D25: =IFERROR(D24/D$18,0) -> 0.091652671 | E25: =IFERROR(E24/E$18,0) -> 0 | F25: =IFERROR(F24/F$18,0) -> 0 | G25: =IFERROR(G24/G$18,0) -> 0 | H25: =IFERROR(H24/H$18,0) -> 0 | I25: =IFERROR(I24/I$18,0) -> 0 | J25: =IFERROR(J24/J$18,0) -> 0.10960007 | ... DC25: =IFERROR(DC24/DC$18,0) -> 0.093136419
A26: 15 | B26: VSE | C26: =C$16*HLOOKUP(C$10,'P&L by Ctn'!$C$8:$AG$31,'P&L TOTAL 150'!$A26,0) -> 35584.862 | D26: =D$16*HLOOKUP(D$10,'P&L by Ctn'!$C$8:$AG$31,'P&L TOTAL 150'!$A26,0) -> 6437.7614 | E26: =E$16*HLOOKUP(E$10,'P&L by Ctn'!$C$8:$AG$31,'P&L TOTAL 150'!$A26,0) -> 15543.483 | F26: =F$16*HLOOKUP(F$10,'P&L by Ctn'!$C$8:$AG$31,'P&L TOTAL 150'!$A26,0) -> 0 | G26: =G$16*HLOOKUP(G$10,'P&L by Ctn'!$C$8:$AG$31,'P&L TOTAL 150'!$A26,0) -> 0 | H26: =H$16*HLOOKUP(H$10,'P&L by Ctn'!$C$8:$AG$31,'P&L TOTAL 150'!$A26,0) -> 92.13921 | I26: =I$16*HLOOKUP(I$10,'P&L by Ctn'!$C$8:$AG$31,'P&L TOTAL 150'!$A26,0) -> 97.197933 | J26: =SUM(C26:I26) -> 57755.444 | K26: =K$16*HLOOKUP(K$10,'P&L by Ctn'!$C$8:$AG$31,'P&L TOTAL 150'!$A26,0) -> 17096.025 | L26: =L$16*HLOOKUP(L$10,'P&L by Ctn'!$C$8:$AG$31,'P&L TOTAL 150'!$A26,0) -> 5230.6811 | M26: =M$16*HLOOKUP(M$10,'P&L by Ctn'!$C$8:$AG$31,'P&L TOTAL 150'!$A26,0) -> 16341.849 | N26: =N$16*HLOOKUP(N$10,'P&L by Ctn'!$C$8:$AG$31,'P&L TOTAL 150'!$A26,0) -> 0 | O26: =O$16*HLOOKUP(O$10,'P&L by Ctn'!$C$8:$AG$31,'P&L TOTAL 150'!$A26,0) -> 41.821298 | P26: =P$16*HLOOKUP(P$10,'P&L by Ctn'!$C$8:$AG$31,'P&L TOTAL 150'!$A26,0) -> 91.179426 | Q26: =Q$16*HLOOKUP(Q$10,'P&L by Ctn'!$C$8:$AG$31,'P&L TOTAL 150'!$A26,0) -> 0 | R26: =SUM(K26:Q26) -> 38801.556 | S26: =S$16*HLOOKUP(S$10,'P&L by Ctn'!$C$8:$AG$31,'P&L TOTAL 150'!$A26,0) -> 25295.287 | T26: =T$16*HLOOKUP(T$10,'P&L by Ctn'!$C$8:$AG$31,'P&L TOTAL 150'!$A26,0) -> 4425.9609 | U26: =U$16*HLOOKUP(U$10,'P&L by Ctn'!$C$8:$AG$31,'P&L TOTAL 150'!$A26,0) -> 24298.671 | V26: =V$16*HLOOKUP(V$10,'P&L by Ctn'!$C$8:$AG$31,'P&L TOTAL 150'!$A26,0) -> 188.20147 | W26: =W$16*HLOOKUP(W$10,'P&L by Ctn'!$C$8:$AG$31,'P&L TOTAL 150'!$A26,0) -> 85.368321 | X26: =X$16*HLOOKUP(X$10,'P&L by Ctn'!$C$8:$AG$31,'P&L TOTAL 150'!$A26,0) -> 276.41763 | Y26: =Y$16*HLOOKUP(Y$10,'P&L by Ctn'!$C$8:$AG$31,'P&L TOTAL 150'!$A26,0) -> 198.36313 | Z26: =SUM(S26:Y26) -> 54768.269 | AA26: =AA$16*HLOOKUP(AA$10,'P&L by Ctn'!$C$8:$AG$31,'P&L TOTAL 150'!$A26,0) -> 19545.447 | AB26: =AB$16*HLOOKUP(AB$10,'P&L by Ctn'!$C$8:$AG$31,'P&L TOTAL 150'!$A26,0) -> 4023.6008 | AC26: =AC$16*HLOOKUP(AC$10,'P&L by Ctn'!$C$8:$AG$31,'P&L TOTAL 150'!$A26,0) -> 15162.371 | AD26: =AD$16*HLOOKUP(AD$10,'P&L by Ctn'!$C$8:$AG$31,'P&L TOTAL 150'!$A26,0) -> 0 | AE26: =AE$16*HLOOKUP(AE$10,'P&L by Ctn'!$C$8:$AG$31,'P&L TOTAL 150'!$A26,0) -> 44.061069 | AF26: =AF$16*HLOOKUP(AF$10,'P&L by Ctn'!$C$8:$AG$31,'P&L TOTAL 150'!$A26,0) -> 92.13921 | AG26: =AG$16*HLOOKUP(AG$10,'P&L by Ctn'!$C$8:$AG$31,'P&L TOTAL 150'!$A26,0) -> 99.181565 | AH26: =SUM(AA26:AG26) -> 38966.801 | AI26: =AI$16*HLOOKUP(AI$10,'P&L by Ctn'!$C$8:$AG$31,'P&L TOTAL 150'!$A26,0) -> 11578.687 | AJ26: =AJ$16*HLOOKUP(AJ$10,'P&L by Ctn'!$C$8:$AG$31,'P&L TOTAL 150'!$A26,0) -> 2414.1605 | AK26: =AK$16*HLOOKUP(AK$10,'P&L by Ctn'!$C$8:$AG$31,'P&L TOTAL 150'!$A26,0) -> 8553.1321 | AL26: =AL$16*HLOOKUP(AL$10,'P&L by Ctn'!$C$8:$AG$31,'P&L TOTAL 150'!$A26,0) -> 0 | AM26: =AM$16*HLOOKUP(AM$10,'P&L by Ctn'!$C$8:$AG$31,'P&L TOTAL 150'!$A26,0) -> 44.061069 | AN26: =AN$16*HLOOKUP(AN$10,'P&L by Ctn'!$C$8:$AG$31,'P&L TOTAL 150'!$A26,0) -> 92.13921 | AO26: =AO$16*HLOOKUP(AO$10,'P&L by Ctn'!$C$8:$AG$31,'P&L TOTAL 150'!$A26,0) -> 99.181565 | AP26: =SUM(AI26:AO26) -> 22781.362 | AQ26: =AQ$16*HLOOKUP(AQ$10,'P&L by Ctn'!$C$8:$AG$31,'P&L TOTAL 150'!$A26,0) -> 18323.548 | AR26: =AR$16*HLOOKUP(AR$10,'P&L by Ctn'!$C$8:$AG$31,'P&L TOTAL 150'!$A26,0) -> 4023.6008 | AS26: =AS$16*HLOOKUP(AS$10,'P&L by Ctn'!$C$8:$AG$31,'P&L TOTAL 150'!$A26,0) -> 13996.034 | AT26: =AT$16*HLOOKUP(AT$10,'P&L by Ctn'!$C$8:$AG$31,'P&L TOTAL 150'!$A26,0) -> 0 | AU26: =AU$16*HLOOKUP(AU$10,'P&L by Ctn'!$C$8:$AG$31,'P&L TOTAL 150'!$A26,0) -> 44.061069 | AV26: =AV$16*HLOOKUP(AV$10,'P&L by Ctn'!$C$8:$AG$31,'P&L TOTAL 150'!$A26,0) -> 184.27842 | AW26: =AW$16*HLOOKUP(AW$10,'P&L by Ctn'!$C$8:$AG$31,'P&L TOTAL 150'!$A26,0) -> 99.181565 | AX26: =SUM(AQ26:AW26) -> 36670.705 | AY26: =AY$16*HLOOKUP(AY$10,'P&L by Ctn'!$C$8:$AG$31,'P&L TOTAL 150'!$A26,0) -> #REF! | AZ26: =AZ$16*HLOOKUP(AZ$10,'P&L by Ctn'!$C$8:$AG$31,'P&L TOTAL 150'!$A26,0) -> #REF! | BA26: =BA$16*HLOOKUP(BA$10,'P&L by Ctn'!$C$8:$AG$31,'P&L TOTAL 150'!$A26,0) -> #REF! | BB26: =BB$16*HLOOKUP(BB$10,'P&L by Ctn'!$C$8:$AG$31,'P&L TOTAL 150'!$A26,0) -> 0 | BC26: =BC$16*HLOOKUP(BC$10,'P&L by Ctn'!$C$8:$AG$31,'P&L TOTAL 150'!$A26,0) -> 0 | BD26: =BD$16*HLOOKUP(BD$10,'P&L by Ctn'!$C$8:$AG$31,'P&L TOTAL 150'!$A26,0) -> 92.13921 | BE26: =BE$16*HLOOKUP(BE$10,'P&L by Ctn'!$C$8:$AG$31,'P&L TOTAL 150'!$A26,0) -> 0 | BF26: =SUM(AY26:BE26) -> #REF! | BG26: =BG$16*HLOOKUP(BG$10,'P&L by Ctn'!$C$8:$AG$31,'P&L TOTAL 150'!$A26,0) -> #REF! | BH26: =BH$16*HLOOKUP(BH$10,'P&L by Ctn'!$C$8:$AG$31,'P&L TOTAL 150'!$A26,0) -> #REF! | BI26: =BI$16*HLOOKUP(BI$10,'P&L by Ctn'!$C$8:$AG$31,'P&L TOTAL 150'!$A26,0) -> #REF! | BJ26: =BJ$16*HLOOKUP(BJ$10,'P&L by Ctn'!$C$8:$AG$31,'P&L TOTAL 150'!$A26,0) -> 0 | BK26: =BK$16*HLOOKUP(BK$10,'P&L by Ctn'!$C$8:$AG$31,'P&L TOTAL 150'!$A26,0) -> 44.061069 | BL26: =BL$16*HLOOKUP(BL$10,'P&L by Ctn'!$C$8:$AG$31,'P&L TOTAL 150'!$A26,0) -> 184.27842 | BM26: =BM$16*HLOOKUP(BM$10,'P&L by Ctn'!$C$8:$AG$31,'P&L TOTAL 150'!$A26,0) -> 99.181565 | BN26: =SUM(BG26:BM26) -> #REF! | BO26: =BO$16*HLOOKUP(BO$10,'P&L by Ctn'!$C$8:$AG$31,'P&L TOTAL 150'!$A26,0) -> #REF! | BP26: =BP$16*HLOOKUP(BP$10,'P&L by Ctn'!$C$8:$AG$31,'P&L TOTAL 150'!$A26,0) -> #REF! | BQ26: =BQ$16*HLOOKUP(BQ$10,'P&L by Ctn'!$C$8:$AG$31,'P&L TOTAL 150'!$A26,0) -> #REF! | BR26: =BR$16*HLOOKUP(BR$10,'P&L by Ctn'!$C$8:$AG$31,'P&L TOTAL 150'!$A26,0) -> 0 | BS26: =BS$16*HLOOKUP(BS$10,'P&L by Ctn'!$C$8:$AG$31,'P&L TOTAL 150'!$A26,0) -> 44.061069 | BT26: =BT$16*HLOOKUP(BT$10,'P&L by Ctn'!$C$8:$AG$31,'P&L TOTAL 150'!$A26,0) -> 92.13921 | BU26: =BU$16*HLOOKUP(BU$10,'P&L by Ctn'!$C$8:$AG$31,'P&L TOTAL 150'!$A26,0) -> 99.181565 | BV26: =SUM(BO26:BU26) -> #REF! | BW26: =BW$16*HLOOKUP(BW$10,'P&L by Ctn'!$C$8:$AG$31,'P&L TOTAL 150'!$A26,0) -> #REF! | BX26: =BX$16*HLOOKUP(BX$10,'P&L by Ctn'!$C$8:$AG$31,'P&L TOTAL 150'!$A26,0) -> #REF! | BY26: =BY$16*HLOOKUP(BY$10,'P&L by Ctn'!$C$8:$AG$31,'P&L TOTAL 150'!$A26,0) -> #REF! | BZ26: =BZ$16*HLOOKUP(BZ$10,'P&L by Ctn'!$C$8:$AG$31,'P&L TOTAL 150'!$A26,0) -> 0 | CA26: =CA$16*HLOOKUP(CA$10,'P&L by Ctn'!$C$8:$AG$31,'P&L TOTAL 150'!$A26,0) -> 44.061069 | CB26: =CB$16*HLOOKUP(CB$10,'P&L by Ctn'!$C$8:$AG$31,'P&L TOTAL 150'!$A26,0) -> 92.13921 | CC26: =CC$16*HLOOKUP(CC$10,'P&L by Ctn'!$C$8:$AG$31,'P&L TOTAL 150'!$A26,0) -> 0 | CD26: =SUM(BW26:CC26) -> #REF! | CE26: =CE$16*HLOOKUP(CE$10,'P&L by Ctn'!$C$8:$AG$31,'P&L TOTAL 150'!$A26,0) -> #REF! | CF26: =CF$16*HLOOKUP(CF$10,'P&L by Ctn'!$C$8:$AG$31,'P&L TOTAL 150'!$A26,0) -> #REF! | CG26: =CG$16*HLOOKUP(CG$10,'P&L by Ctn'!$C$8:$AG$31,'P&L TOTAL 150'!$A26,0) -> #REF! | CH26: =CH$16*HLOOKUP(CH$10,'P&L by Ctn'!$C$8:$AG$31,'P&L TOTAL 150'!$A26,0) -> 0 | CI26: =CI$16*HLOOKUP(CI$10,'P&L by Ctn'!$C$8:$AG$31,'P&L TOTAL 150'!$A26,0) -> 0 | CJ26: =CJ$16*HLOOKUP(CJ$10,'P&L by Ctn'!$C$8:$AG$31,'P&L TOTAL 150'!$A26,0) -> 92.13921 | CK26: =CK$16*HLOOKUP(CK$10,'P&L by Ctn'!$C$8:$AG$31,'P&L TOTAL 150'!$A26,0) -> 99.181565 | CL26: =SUM(CE26:CK26) -> #REF! | CM26: =CM$16*HLOOKUP(CM$10,'P&L by Ctn'!$C$8:$AG$31,'P&L TOTAL 150'!$A26,0) -> #REF! | CN26: =CN$16*HLOOKUP(CN$10,'P&L by Ctn'!$C$8:$AG$31,'P&L TOTAL 150'!$A26,0) -> #REF! | CO26: =CO$16*HLOOKUP(CO$10,'P&L by Ctn'!$C$8:$AG$31,'P&L TOTAL 150'!$A26,0) -> #REF! | CP26: =CP$16*HLOOKUP(CP$10,'P&L by Ctn'!$C$8:$AG$31,'P&L TOTAL 150'!$A26,0) -> 0 | CQ26: =CQ$16*HLOOKUP(CQ$10,'P&L by Ctn'!$C$8:$AG$31,'P&L TOTAL 150'!$A26,0) -> 44.061069 | CR26: =CR$16*HLOOKUP(CR$10,'P&L by Ctn'!$C$8:$AG$31,'P&L TOTAL 150'!$A26,0) -> 92.13921 | CS26: =CS$16*HLOOKUP(CS$10,'P&L by Ctn'!$C$8:$AG$31,'P&L TOTAL 150'!$A26,0) -> 99.181565 | CT26: =SUM(CM26:CS26) -> #REF! | CU26: =SUMIFS($C26:$CT26,$C$14:$CT$14,CU$14) -> #REF! | CV26: =SUMIFS($C26:$CT26,$C$14:$CT$14,CV$14) -> #REF! | CW26: =SUMIFS($C26:$CT26,$C$14:$CT$14,CW$14) -> #REF! | CX26: =SUMIFS($C26:$CT26,$C$14:$CT$14,CX$14) -> 188.20147 | CY26: =SUMIFS($C26:$CT26,$C$14:$CT$14,CY$14) -> 435.6171 | CZ26: =SUMIFS($C26:$CT26,$C$14:$CT$14,CZ$14) -> 1473.2676 | DA26: =SUMIFS($C26:$CT26,$C$14:$CT$14,DA$14) -> 989.83201 | DB26: =SUM(CU26:DA26) -> #REF! | DC26: =SUM(J26,R26) -> 96557
B27: GP2 | C27: =C20-C22-C24-C26 -> 65575.483 | D27: =D20-D22-D24-D26 -> 23008.533 | E27: =E20-E22-E24-E26 -> 35235.525 | F27: =F20-F22-F24-F26 -> 0 | G27: =G20-G22-G24-G26 -> 0 | H27: =H20-H22-H24-H26 -> 1107.8858 | I27: =I20-I22-I24-I26 -> 443.41709 | J27: =J20-J22-J24-J26 -> 125370.84 | ... DC27: =DC20-DC22-DC24-DC26 -> 149822.77
B28: GP2% | C28: =IFERROR(C27/C$18,0) -> 0.04408954 | D28: =IFERROR(D27/D$18,0) -> 0.06276171 | E28: =IFERROR(E27/E$18,0) -> 0.043517453 | F28: =IFERROR(F27/F$18,0) -> 0 | G28: =IFERROR(G27/G$18,0) -> 0 | H28: =IFERROR(H27/H$18,0) -> 0.11177218 | I28: =IFERROR(I27/I$18,0) -> 0.062323198 | J28: =IFERROR(J27/J$18,0) -> 0.046768986 | ... DC28: =IFERROR(DC27/DC$18,0) -> 0.032861301
A29: 18 | B29: A&P | C29: =C$16*HLOOKUP(C$10,'P&L by Ctn'!$C$8:$AG$31,'P&L TOTAL 150'!$A29,0) -> 0 | D29: =D$16*HLOOKUP(D$10,'P&L by Ctn'!$C$8:$AG$31,'P&L TOTAL 150'!$A29,0) -> 0 | E29: =E$16*HLOOKUP(E$10,'P&L by Ctn'!$C$8:$AG$31,'P&L TOTAL 150'!$A29,0) -> 0 | F29: =F$16*HLOOKUP(F$10,'P&L by Ctn'!$C$8:$AG$31,'P&L TOTAL 150'!$A29,0) -> 0 | G29: =G$16*HLOOKUP(G$10,'P&L by Ctn'!$C$8:$AG$31,'P&L TOTAL 150'!$A29,0) -> 0 | H29: =H$16*HLOOKUP(H$10,'P&L by Ctn'!$C$8:$AG$31,'P&L TOTAL 150'!$A29,0) -> 0 | I29: =I$16*HLOOKUP(I$10,'P&L by Ctn'!$C$8:$AG$31,'P&L TOTAL 150'!$A29,0) -> 0 | J29: =SUM(C29:I29) -> 0 | K29: =K$16*HLOOKUP(K$10,'P&L by Ctn'!$C$8:$AG$31,'P&L TOTAL 150'!$A29,0) -> 0 | L29: =L$16*HLOOKUP(L$10,'P&L by Ctn'!$C$8:$AG$31,'P&L TOTAL 150'!$A29,0) -> 0 | M29: =M$16*HLOOKUP(M$10,'P&L by Ctn'!$C$8:$AG$31,'P&L TOTAL 150'!$A29,0) -> 0 | N29: =N$16*HLOOKUP(N$10,'P&L by Ctn'!$C$8:$AG$31,'P&L TOTAL 150'!$A29,0) -> 0 | O29: =O$16*HLOOKUP(O$10,'P&L by Ctn'!$C$8:$AG$31,'P&L TOTAL 150'!$A29,0) -> 0 | P29: =P$16*HLOOKUP(P$10,'P&L by Ctn'!$C$8:$AG$31,'P&L TOTAL 150'!$A29,0) -> 0 | Q29: =Q$16*HLOOKUP(Q$10,'P&L by Ctn'!$C$8:$AG$31,'P&L TOTAL 150'!$A29,0) -> 0 | R29: =SUM(K29:Q29) -> 0 | S29: =S$16*HLOOKUP(S$10,'P&L by Ctn'!$C$8:$AG$31,'P&L TOTAL 150'!$A29,0) -> 0 | T29: =T$16*HLOOKUP(T$10,'P&L by Ctn'!$C$8:$AG$31,'P&L TOTAL 150'!$A29,0) -> 0 | U29: =U$16*HLOOKUP(U$10,'P&L by Ctn'!$C$8:$AG$31,'P&L TOTAL 150'!$A29,0) -> 0 | V29: =V$16*HLOOKUP(V$10,'P&L by Ctn'!$C$8:$AG$31,'P&L TOTAL 150'!$A29,0) -> 0 | W29: =W$16*HLOOKUP(W$10,'P&L by Ctn'!$C$8:$AG$31,'P&L TOTAL 150'!$A29,0) -> 0 | X29: =X$16*HLOOKUP(X$10,'P&L by Ctn'!$C$8:$AG$31,'P&L TOTAL 150'!$A29,0) -> 0 | Y29: =Y$16*HLOOKUP(Y$10,'P&L by Ctn'!$C$8:$AG$31,'P&L TOTAL 150'!$A29,0) -> 0 | Z29: =SUM(S29:Y29) -> 0 | AA29: =AA$16*HLOOKUP(AA$10,'P&L by Ctn'!$C$8:$AG$31,'P&L TOTAL 150'!$A29,0) -> 0 | AB29: =AB$16*HLOOKUP(AB$10,'P&L by Ctn'!$C$8:$AG$31,'P&L TOTAL 150'!$A29,0) -> 0 | AC29: =AC$16*HLOOKUP(AC$10,'P&L by Ctn'!$C$8:$AG$31,'P&L TOTAL 150'!$A29,0) -> 0 | AD29: =AD$16*HLOOKUP(AD$10,'P&L by Ctn'!$C$8:$AG$31,'P&L TOTAL 150'!$A29,0) -> 0 | AE29: =AE$16*HLOOKUP(AE$10,'P&L by Ctn'!$C$8:$AG$31,'P&L TOTAL 150'!$A29,0) -> 0 | AF29: =AF$16*HLOOKUP(AF$10,'P&L by Ctn'!$C$8:$AG$31,'P&L TOTAL 150'!$A29,0) -> 0 | AG29: =AG$16*HLOOKUP(AG$10,'P&L by Ctn'!$C$8:$AG$31,'P&L TOTAL 150'!$A29,0) -> 0 | AH29: =SUM(AA29:AG29) -> 0 | AI29: =AI$16*HLOOKUP(AI$10,'P&L by Ctn'!$C$8:$AG$31,'P&L TOTAL 150'!$A29,0) -> 0 | AJ29: =AJ$16*HLOOKUP(AJ$10,'P&L by Ctn'!$C$8:$AG$31,'P&L TOTAL 150'!$A29,0) -> 0 | AK29: =AK$16*HLOOKUP(AK$10,'P&L by Ctn'!$C$8:$AG$31,'P&L TOTAL 150'!$A29,0) -> 0 | AL29: =AL$16*HLOOKUP(AL$10,'P&L by Ctn'!$C$8:$AG$31,'P&L TOTAL 150'!$A29,0) -> 0 | AM29: =AM$16*HLOOKUP(AM$10,'P&L by Ctn'!$C$8:$AG$31,'P&L TOTAL 150'!$A29,0) -> 0 | AN29: =AN$16*HLOOKUP(AN$10,'P&L by Ctn'!$C$8:$AG$31,'P&L TOTAL 150'!$A29,0) -> 0 | AO29: =AO$16*HLOOKUP(AO$10,'P&L by Ctn'!$C$8:$AG$31,'P&L TOTAL 150'!$A29,0) -> 0 | AP29: =SUM(AI29:AO29) -> 0 | AQ29: =AQ$16*HLOOKUP(AQ$10,'P&L by Ctn'!$C$8:$AG$31,'P&L TOTAL 150'!$A29,0) -> 0 | AR29: =AR$16*HLOOKUP(AR$10,'P&L by Ctn'!$C$8:$AG$31,'P&L TOTAL 150'!$A29,0) -> 0 | AS29: =AS$16*HLOOKUP(AS$10,'P&L by Ctn'!$C$8:$AG$31,'P&L TOTAL 150'!$A29,0) -> 0 | AT29: =AT$16*HLOOKUP(AT$10,'P&L by Ctn'!$C$8:$AG$31,'P&L TOTAL 150'!$A29,0) -> 0 | AU29: =AU$16*HLOOKUP(AU$10,'P&L by Ctn'!$C$8:$AG$31,'P&L TOTAL 150'!$A29,0) -> 0 | AV29: =AV$16*HLOOKUP(AV$10,'P&L by Ctn'!$C$8:$AG$31,'P&L TOTAL 150'!$A29,0) -> 0 | AW29: =AW$16*HLOOKUP(AW$10,'P&L by Ctn'!$C$8:$AG$31,'P&L TOTAL 150'!$A29,0) -> 0 | AX29: =SUM(AQ29:AW29) -> 0 | AY29: =AY$16*HLOOKUP(AY$10,'P&L by Ctn'!$C$8:$AG$31,'P&L TOTAL 150'!$A29,0) -> 0 | AZ29: =AZ$16*HLOOKUP(AZ$10,'P&L by Ctn'!$C$8:$AG$31,'P&L TOTAL 150'!$A29,0) -> 0 | BA29: =BA$16*HLOOKUP(BA$10,'P&L by Ctn'!$C$8:$AG$31,'P&L TOTAL 150'!$A29,0) -> 0 | BB29: =BB$16*HLOOKUP(BB$10,'P&L by Ctn'!$C$8:$AG$31,'P&L TOTAL 150'!$A29,0) -> 0 | BC29: =BC$16*HLOOKUP(BC$10,'P&L by Ctn'!$C$8:$AG$31,'P&L TOTAL 150'!$A29,0) -> 0 | BD29: =BD$16*HLOOKUP(BD$10,'P&L by Ctn'!$C$8:$AG$31,'P&L TOTAL 150'!$A29,0) -> 0 | BE29: =BE$16*HLOOKUP(BE$10,'P&L by Ctn'!$C$8:$AG$31,'P&L TOTAL 150'!$A29,0) -> 0 | BF29: =SUM(AY29:BE29) -> 0 | BG29: =BG$16*HLOOKUP(BG$10,'P&L by Ctn'!$C$8:$AG$31,'P&L TOTAL 150'!$A29,0) -> 0 | BH29: =BH$16*HLOOKUP(BH$10,'P&L by Ctn'!$C$8:$AG$31,'P&L TOTAL 150'!$A29,0) -> 0 | BI29: =BI$16*HLOOKUP(BI$10,'P&L by Ctn'!$C$8:$AG$31,'P&L TOTAL 150'!$A29,0) -> 0 | BJ29: =BJ$16*HLOOKUP(BJ$10,'P&L by Ctn'!$C$8:$AG$31,'P&L TOTAL 150'!$A29,0) -> 0 | BK29: =BK$16*HLOOKUP(BK$10,'P&L by Ctn'!$C$8:$AG$31,'P&L TOTAL 150'!$A29,0) -> 0 | BL29: =BL$16*HLOOKUP(BL$10,'P&L by Ctn'!$C$8:$AG$31,'P&L TOTAL 150'!$A29,0) -> 0 | BM29: =BM$16*HLOOKUP(BM$10,'P&L by Ctn'!$C$8:$AG$31,'P&L TOTAL 150'!$A29,0) -> 0 | BN29: =SUM(BG29:BM29) -> 0 | BO29: =BO$16*HLOOKUP(BO$10,'P&L by Ctn'!$C$8:$AG$31,'P&L TOTAL 150'!$A29,0) -> 0 | BP29: =BP$16*HLOOKUP(BP$10,'P&L by Ctn'!$C$8:$AG$31,'P&L TOTAL 150'!$A29,0) -> 0 | BQ29: =BQ$16*HLOOKUP(BQ$10,'P&L by Ctn'!$C$8:$AG$31,'P&L TOTAL 150'!$A29,0) -> 0 | BR29: =BR$16*HLOOKUP(BR$10,'P&L by Ctn'!$C$8:$AG$31,'P&L TOTAL 150'!$A29,0) -> 0 | BS29: =BS$16*HLOOKUP(BS$10,'P&L by Ctn'!$C$8:$AG$31,'P&L TOTAL 150'!$A29,0) -> 0 | BT29: =BT$16*HLOOKUP(BT$10,'P&L by Ctn'!$C$8:$AG$31,'P&L TOTAL 150'!$A29,0) -> 0 | BU29: =BU$16*HLOOKUP(BU$10,'P&L by Ctn'!$C$8:$AG$31,'P&L TOTAL 150'!$A29,0) -> 0 | BV29: =SUM(BO29:BU29) -> 0 | BW29: =BW$16*HLOOKUP(BW$10,'P&L by Ctn'!$C$8:$AG$31,'P&L TOTAL 150'!$A29,0) -> 0 | BX29: =BX$16*HLOOKUP(BX$10,'P&L by Ctn'!$C$8:$AG$31,'P&L TOTAL 150'!$A29,0) -> 0 | BY29: =BY$16*HLOOKUP(BY$10,'P&L by Ctn'!$C$8:$AG$31,'P&L TOTAL 150'!$A29,0) -> 0 | BZ29: =BZ$16*HLOOKUP(BZ$10,'P&L by Ctn'!$C$8:$AG$31,'P&L TOTAL 150'!$A29,0) -> 0 | CA29: =CA$16*HLOOKUP(CA$10,'P&L by Ctn'!$C$8:$AG$31,'P&L TOTAL 150'!$A29,0) -> 0 | CB29: =CB$16*HLOOKUP(CB$10,'P&L by Ctn'!$C$8:$AG$31,'P&L TOTAL 150'!$A29,0) -> 0 | CC29: =CC$16*HLOOKUP(CC$10,'P&L by Ctn'!$C$8:$AG$31,'P&L TOTAL 150'!$A29,0) -> 0 | CD29: =SUM(BW29:CC29) -> 0 | CE29: =CE$16*HLOOKUP(CE$10,'P&L by Ctn'!$C$8:$AG$31,'P&L TOTAL 150'!$A29,0) -> 0 | CF29: =CF$16*HLOOKUP(CF$10,'P&L by Ctn'!$C$8:$AG$31,'P&L TOTAL 150'!$A29,0) -> 0 | CG29: =CG$16*HLOOKUP(CG$10,'P&L by Ctn'!$C$8:$AG$31,'P&L TOTAL 150'!$A29,0) -> 0 | CH29: =CH$16*HLOOKUP(CH$10,'P&L by Ctn'!$C$8:$AG$31,'P&L TOTAL 150'!$A29,0) -> 0 | CI29: =CI$16*HLOOKUP(CI$10,'P&L by Ctn'!$C$8:$AG$31,'P&L TOTAL 150'!$A29,0) -> 0 | CJ29: =CJ$16*HLOOKUP(CJ$10,'P&L by Ctn'!$C$8:$AG$31,'P&L TOTAL 150'!$A29,0) -> 0 | CK29: =CK$16*HLOOKUP(CK$10,'P&L by Ctn'!$C$8:$AG$31,'P&L TOTAL 150'!$A29,0) -> 0 | CL29: =SUM(CE29:CK29) -> 0 | CM29: =CM$16*HLOOKUP(CM$10,'P&L by Ctn'!$C$8:$AG$31,'P&L TOTAL 150'!$A29,0) -> 0 | CN29: =CN$16*HLOOKUP(CN$10,'P&L by Ctn'!$C$8:$AG$31,'P&L TOTAL 150'!$A29,0) -> 0 | CO29: =CO$16*HLOOKUP(CO$10,'P&L by Ctn'!$C$8:$AG$31,'P&L TOTAL 150'!$A29,0) -> 0 | CP29: =CP$16*HLOOKUP(CP$10,'P&L by Ctn'!$C$8:$AG$31,'P&L TOTAL 150'!$A29,0) -> 0 | CQ29: =CQ$16*HLOOKUP(CQ$10,'P&L by Ctn'!$C$8:$AG$31,'P&L TOTAL 150'!$A29,0) -> 0 | CR29: =CR$16*HLOOKUP(CR$10,'P&L by Ctn'!$C$8:$AG$31,'P&L TOTAL 150'!$A29,0) -> 0 | CS29: =CS$16*HLOOKUP(CS$10,'P&L by Ctn'!$C$8:$AG$31,'P&L TOTAL 150'!$A29,0) -> 0 | CT29: =SUM(CM29:CS29) -> 0 | CU29: =SUMIFS($C29:$CT29,$C$14:$CT$14,CU$14) -> 0 | CV29: =SUMIFS($C29:$CT29,$C$14:$CT$14,CV$14) -> 0 | CW29: =SUMIFS($C29:$CT29,$C$14:$CT$14,CW$14) -> 0 | CX29: =SUMIFS($C29:$CT29,$C$14:$CT$14,CX$14) -> 0 | CY29: =SUMIFS($C29:$CT29,$C$14:$CT$14,CY$14) -> 0 | CZ29: =SUMIFS($C29:$CT29,$C$14:$CT$14,CZ$14) -> 0 | DA29: =SUMIFS($C29:$CT29,$C$14:$CT$14,DA$14) -> 0 | DB29: =SUM(CU29:DA29) -> 0 | DC29: =SUM(J29,R29) -> 0
B30: GP3 | C30: =C27-C29 -> 65575.483 | D30: =D27-D29 -> 23008.533 | E30: =E27-E29 -> 35235.525 | F30: =F27-F29 -> 0 | G30: =G27-G29 -> 0 | H30: =H27-H29 -> 1107.8858 | I30: =I27-I29 -> 443.41709 | J30: =J27-J29 -> 125370.84 | ... DC30: =DC27-DC29 -> 149822.77
B31: GP3% | C31: =IFERROR(C30/C$18,0) -> 0.04408954 | D31: =IFERROR(D30/D$18,0) -> 0.06276171 | E31: =IFERROR(E30/E$18,0) -> 0.043517453 | F31: =IFERROR(F30/F$18,0) -> 0 | G31: =IFERROR(G30/G$18,0) -> 0 | H31: =IFERROR(H30/H$18,0) -> 0.11177218 | I31: =IFERROR(I30/I$18,0) -> 0.062323198 | J31: =IFERROR(J30/J$18,0) -> 0.046768986 | ... DC31: =IFERROR(DC30/DC$18,0) -> 0.032861301
A32: 21 | B32: Freight Difference | C32: =C$16*'Pricing Structure - GSS'!O96 -> 3627.0496 | D32: =D$16*'Pricing Structure - GSS'!O96 -> 894.79452 | E32: =E$16*'Pricing Structure - GSS'!O96 -> 1984.3467 | F32: =F$16*'Pricing Structure - GSS'!O96 -> 0 | G32: =G$16*'Pricing Structure - GSS'!O96 -> 0 | H32: =H$16*'Pricing Structure - GSS'!O96 -> 33.554795 | I32: =I$16*'Pricing Structure - GSS'!O96 -> 16.441849 | J32: =SUM(C32:I32) -> 6556.1874 | K32: =K$16*'Pricing Structure - GSS'!U96 -> 1604.2273 | L32: =L$16*'Pricing Structure - GSS'!U96 -> 669.31297 | M32: =M$16*'Pricing Structure - GSS'!U96 -> 1920.6708 | N32: =N$16*'Pricing Structure - GSS'!U96 -> 0 | O32: =O$16*'Pricing Structure - GSS'!U96 -> 14.660528 | P32: =P$16*'Pricing Structure - GSS'!U96 -> 30.569583 | Q32: =Q$16*'Pricing Structure - GSS'!U96 -> 0 | R32: =SUM(K32:Q32) -> 4239.4412 | S32: =S$16*HLOOKUP(S$10,'P&L by Ctn'!$C$8:$AG$31,'P&L TOTAL 150'!$A32,0) -> -831.61741 | T32: =T$16*HLOOKUP(T$10,'P&L by Ctn'!$C$8:$AG$31,'P&L TOTAL 150'!$A32,0) -> 1191.3549 | U32: =U$16*HLOOKUP(U$10,'P&L by Ctn'!$C$8:$AG$31,'P&L TOTAL 150'!$A32,0) -> -1994.0535 | V32: =V$16*HLOOKUP(V$10,'P&L by Ctn'!$C$8:$AG$31,'P&L TOTAL 150'!$A32,0) -> -10.643685 | W32: =W$16*HLOOKUP(W$10,'P&L by Ctn'!$C$8:$AG$31,'P&L TOTAL 150'!$A32,0) -> 61.866531 | X32: =X$16*HLOOKUP(X$10,'P&L by Ctn'!$C$8:$AG$31,'P&L TOTAL 150'!$A32,0) -> 59.141462 | Y32: =Y$16*HLOOKUP(Y$10,'P&L by Ctn'!$C$8:$AG$31,'P&L TOTAL 150'!$A32,0) -> -572.99458 | Z32: =SUM(S32:Y32) -> -2096.9464 | AA32: =AA$16*HLOOKUP(AA$10,'P&L by Ctn'!$C$8:$AG$31,'P&L TOTAL 150'!$A32,0) -> -642.58353 | AB32: =AB$16*HLOOKUP(AB$10,'P&L by Ctn'!$C$8:$AG$31,'P&L TOTAL 150'!$A32,0) -> 1083.0499 | AC32: =AC$16*HLOOKUP(AC$10,'P&L by Ctn'!$C$8:$AG$31,'P&L TOTAL 150'!$A32,0) -> -1244.2894 | AD32: =AD$16*HLOOKUP(AD$10,'P&L by Ctn'!$C$8:$AG$31,'P&L TOTAL 150'!$A32,0) -> 0 | AE32: =AE$16*HLOOKUP(AE$10,'P&L by Ctn'!$C$8:$AG$31,'P&L TOTAL 150'!$A32,0) -> 31.931113 | AF32: =AF$16*HLOOKUP(AF$10,'P&L by Ctn'!$C$8:$AG$31,'P&L TOTAL 150'!$A32,0) -> 19.713821 | AG32: =AG$16*HLOOKUP(AG$10,'P&L by Ctn'!$C$8:$AG$31,'P&L TOTAL 150'!$A32,0) -> -286.49729 | AH32: =SUM(AA32:AG32) -> -1038.6754 | AI32: =AI$16*HLOOKUP(AI$10,'P&L by Ctn'!$C$8:$AG$31,'P&L TOTAL 150'!$A32,0) -> -380.66531 | AJ32: =AJ$16*HLOOKUP(AJ$10,'P&L by Ctn'!$C$8:$AG$31,'P&L TOTAL 150'!$A32,0) -> 649.82992 | AK32: =AK$16*HLOOKUP(AK$10,'P&L by Ctn'!$C$8:$AG$31,'P&L TOTAL 150'!$A32,0) -> -701.90685 | AL32: =AL$16*HLOOKUP(AL$10,'P&L by Ctn'!$C$8:$AG$31,'P&L TOTAL 150'!$A32,0) -> 0 | AM32: =AM$16*HLOOKUP(AM$10,'P&L by Ctn'!$C$8:$AG$31,'P&L TOTAL 150'!$A32,0) -> 31.931113 | AN32: =AN$16*HLOOKUP(AN$10,'P&L by Ctn'!$C$8:$AG$31,'P&L TOTAL 150'!$A32,0) -> 19.713821 | AO32: =AO$16*HLOOKUP(AO$10,'P&L by Ctn'!$C$8:$AG$31,'P&L TOTAL 150'!$A32,0) -> -286.49729 | AP32: =SUM(AI32:AO32) -> -667.59458 | AQ32: =AQ$16*HLOOKUP(AQ$10,'P&L by Ctn'!$C$8:$AG$31,'P&L TOTAL 150'!$A32,0) -> -602.41191 | AR32: =AR$16*HLOOKUP(AR$10,'P&L by Ctn'!$C$8:$AG$31,'P&L TOTAL 150'!$A32,0) -> 1083.0499 | AS32: =AS$16*HLOOKUP(AS$10,'P&L by Ctn'!$C$8:$AG$31,'P&L TOTAL 150'!$A32,0) -> -1148.5748 | AT32: =AT$16*HLOOKUP(AT$10,'P&L by Ctn'!$C$8:$AG$31,'P&L TOTAL 150'!$A32,0) -> 0 | AU32: =AU$16*HLOOKUP(AU$10,'P&L by Ctn'!$C$8:$AG$31,'P&L TOTAL 150'!$A32,0) -> 31.931113 | AV32: =AV$16*HLOOKUP(AV$10,'P&L by Ctn'!$C$8:$AG$31,'P&L TOTAL 150'!$A32,0) -> 39.427641 | AW32: =AW$16*HLOOKUP(AW$10,'P&L by Ctn'!$C$8:$AG$31,'P&L TOTAL 150'!$A32,0) -> -286.49729 | AX32: =SUM(AQ32:AW32) -> -883.07541 | AY32: =AY$16*HLOOKUP(AY$10,'P&L by Ctn'!$C$8:$AG$31,'P&L TOTAL 150'!$A32,0) -> #REF! | AZ32: =AZ$16*HLOOKUP(AZ$10,'P&L by Ctn'!$C$8:$AG$31,'P&L TOTAL 150'!$A32,0) -> #REF! | BA32: =BA$16*HLOOKUP(BA$10,'P&L by Ctn'!$C$8:$AG$31,'P&L TOTAL 150'!$A32,0) -> #REF! | BB32: =BB$16*HLOOKUP(BB$10,'P&L by Ctn'!$C$8:$AG$31,'P&L TOTAL 150'!$A32,0) -> 0 | BC32: =BC$16*HLOOKUP(BC$10,'P&L by Ctn'!$C$8:$AG$31,'P&L TOTAL 150'!$A32,0) -> 0 | BD32: =BD$16*HLOOKUP(BD$10,'P&L by Ctn'!$C$8:$AG$31,'P&L TOTAL 150'!$A32,0) -> -150 | BE32: =BE$16*HLOOKUP(BE$10,'P&L by Ctn'!$C$8:$AG$31,'P&L TOTAL 150'!$A32,0) -> 0 | BF32: =SUM(AY32:BE32) -> #REF! | BG32: =BG$16*HLOOKUP(BG$10,'P&L by Ctn'!$C$8:$AG$31,'P&L TOTAL 150'!$A32,0) -> #REF! | BH32: =BH$16*HLOOKUP(BH$10,'P&L by Ctn'!$C$8:$AG$31,'P&L TOTAL 150'!$A32,0) -> #REF! | BI32: =BI$16*HLOOKUP(BI$10,'P&L by Ctn'!$C$8:$AG$31,'P&L TOTAL 150'!$A32,0) -> #REF! | BJ32: =BJ$16*HLOOKUP(BJ$10,'P&L by Ctn'!$C$8:$AG$31,'P&L TOTAL 150'!$A32,0) -> 0 | BK32: =BK$16*HLOOKUP(BK$10,'P&L by Ctn'!$C$8:$AG$31,'P&L TOTAL 150'!$A32,0) -> -72.874494 | BL32: =BL$16*HLOOKUP(BL$10,'P&L by Ctn'!$C$8:$AG$31,'P&L TOTAL 150'!$A32,0) -> -300 | BM32: =BM$16*HLOOKUP(BM$10,'P&L by Ctn'!$C$8:$AG$31,'P&L TOTAL 150'!$A32,0) -> -150 | BN32: =SUM(BG32:BM32) -> #REF! | BO32: =BO$16*HLOOKUP(BO$10,'P&L by Ctn'!$C$8:$AG$31,'P&L TOTAL 150'!$A32,0) -> #REF! | BP32: =BP$16*HLOOKUP(BP$10,'P&L by Ctn'!$C$8:$AG$31,'P&L TOTAL 150'!$A32,0) -> #REF! | BQ32: =BQ$16*HLOOKUP(BQ$10,'P&L by Ctn'!$C$8:$AG$31,'P&L TOTAL 150'!$A32,0) -> #REF! | BR32: =BR$16*HLOOKUP(BR$10,'P&L by Ctn'!$C$8:$AG$31,'P&L TOTAL 150'!$A32,0) -> 0 | BS32: =BS$16*HLOOKUP(BS$10,'P&L by Ctn'!$C$8:$AG$31,'P&L TOTAL 150'!$A32,0) -> -72.874494 | BT32: =BT$16*HLOOKUP(BT$10,'P&L by Ctn'!$C$8:$AG$31,'P&L TOTAL 150'!$A32,0) -> -150 | BU32: =BU$16*HLOOKUP(BU$10,'P&L by Ctn'!$C$8:$AG$31,'P&L TOTAL 150'!$A32,0) -> -150 | BV32: =SUM(BO32:BU32) -> #REF! | BW32: =BW$16*HLOOKUP(BW$10,'P&L by Ctn'!$C$8:$AG$31,'P&L TOTAL 150'!$A32,0) -> #REF! | BX32: =BX$16*HLOOKUP(BX$10,'P&L by Ctn'!$C$8:$AG$31,'P&L TOTAL 150'!$A32,0) -> #REF! | BY32: =BY$16*HLOOKUP(BY$10,'P&L by Ctn'!$C$8:$AG$31,'P&L TOTAL 150'!$A32,0) -> #REF! | BZ32: =BZ$16*HLOOKUP(BZ$10,'P&L by Ctn'!$C$8:$AG$31,'P&L TOTAL 150'!$A32,0) -> 0 | CA32: =CA$16*HLOOKUP(CA$10,'P&L by Ctn'!$C$8:$AG$31,'P&L TOTAL 150'!$A32,0) -> -72.874494 | CB32: =CB$16*HLOOKUP(CB$10,'P&L by Ctn'!$C$8:$AG$31,'P&L TOTAL 150'!$A32,0) -> -150 | CC32: =CC$16*HLOOKUP(CC$10,'P&L by Ctn'!$C$8:$AG$31,'P&L TOTAL 150'!$A32,0) -> 0 | CD32: =SUM(BW32:CC32) -> #REF! | CE32: =CE$16*HLOOKUP(CE$10,'P&L by Ctn'!$C$8:$AG$31,'P&L TOTAL 150'!$A32,0) -> #REF! | CF32: =CF$16*HLOOKUP(CF$10,'P&L by Ctn'!$C$8:$AG$31,'P&L TOTAL 150'!$A32,0) -> #REF! | CG32: =CG$16*HLOOKUP(CG$10,'P&L by Ctn'!$C$8:$AG$31,'P&L TOTAL 150'!$A32,0) -> #REF! | CH32: =CH$16*HLOOKUP(CH$10,'P&L by Ctn'!$C$8:$AG$31,'P&L TOTAL 150'!$A32,0) -> 0 | CI32: =CI$16*HLOOKUP(CI$10,'P&L by Ctn'!$C$8:$AG$31,'P&L TOTAL 150'!$A32,0) -> 0 | CJ32: =CJ$16*HLOOKUP(CJ$10,'P&L by Ctn'!$C$8:$AG$31,'P&L TOTAL 150'!$A32,0) -> -150 | CK32: =CK$16*HLOOKUP(CK$10,'P&L by Ctn'!$C$8:$AG$31,'P&L TOTAL 150'!$A32,0) -> -150 | CL32: =SUM(CE32:CK32) -> #REF! | CM32: =CM$16*HLOOKUP(CM$10,'P&L by Ctn'!$C$8:$AG$31,'P&L TOTAL 150'!$A32,0) -> #REF! | CN32: =CN$16*HLOOKUP(CN$10,'P&L by Ctn'!$C$8:$AG$31,'P&L TOTAL 150'!$A32,0) -> #REF! | CO32: =CO$16*HLOOKUP(CO$10,'P&L by Ctn'!$C$8:$AG$31,'P&L TOTAL 150'!$A32,0) -> #REF! | CP32: =CP$16*HLOOKUP(CP$10,'P&L by Ctn'!$C$8:$AG$31,'P&L TOTAL 150'!$A32,0) -> 0 | CQ32: =CQ$16*HLOOKUP(CQ$10,'P&L by Ctn'!$C$8:$AG$31,'P&L TOTAL 150'!$A32,0) -> -72.874494 | CR32: =CR$16*HLOOKUP(CR$10,'P&L by Ctn'!$C$8:$AG$31,'P&L TOTAL 150'!$A32,0) -> -150 | CS32: =CS$16*HLOOKUP(CS$10,'P&L by Ctn'!$C$8:$AG$31,'P&L TOTAL 150'!$A32,0) -> -150 | CT32: =SUM(CM32:CS32) -> #REF! | CU32: =SUMIFS($C32:$CT32,$C$14:$CT$14,CU$14) -> #REF! | CV32: =SUMIFS($C32:$CT32,$C$14:$CT$14,CV$14) -> #REF! | CW32: =SUMIFS($C32:$CT32,$C$14:$CT$14,CW$14) -> #REF! | CX32: =SUMIFS($C32:$CT32,$C$14:$CT$14,CX$14) -> -10.643685 | CY32: =SUMIFS($C32:$CT32,$C$14:$CT$14,CY$14) -> -119.17758 | CZ32: =SUMIFS($C32:$CT32,$C$14:$CT$14,CZ$14) -> -847.87888 | DA32: =SUMIFS($C32:$CT32,$C$14:$CT$14,DA$14) -> -2016.0446 | DB32: =SUM(CU32:DA32) -> #REF! | DC32: =SUM(J32,R32) -> 10795.629
B33: GP4 | C33: =C30-C32 -> 61948.433 | D33: =D30-D32 -> 22113.738 | E33: =E30-E32 -> 33251.178 | F33: =F30-F32 -> 0 | G33: =G30-G32 -> 0 | H33: =H30-H32 -> 1074.331 | I33: =I30-I32 -> 426.97524 | J33: =J30-J32 -> 118814.66 | ... DC33: =DC30-DC32 -> 139027.14
B34: GP4% | C34: =IFERROR(C33/C$18,0) -> 0.041650901 | D34: =IFERROR(D33/D$18,0) -> 0.060320927 | E34: =IFERROR(E33/E$18,0) -> 0.041066696 | F34: =IFERROR(F33/F$18,0) -> 0 | G34: =IFERROR(G33/G$18,0) -> 0 | H34: =IFERROR(H33/H$18,0) -> 0.10838691 | I34: =IFERROR(I33/I$18,0) -> 0.060012262 | J34: =IFERROR(J33/J$18,0) -> 0.044323232 | ... DC34: =IFERROR(DC33/DC$18,0) -> 0.030493448
A35: 23
A36: 24 | B36: Distributor Buying Value | C36: =C$16*'P&L by Ctn'!$E$33 -> 1692787.8 | D36: =D$16*'P&L by Ctn'!$K$33 -> 417370.07 | E36: =E$16*'P&L by Ctn'!$Q$33 -> 955099.29 | F36: =F$16*'P&L by Ctn'!$W$33 -> 0 | G36: =G$16*'P&L by Ctn'!$AC$33 -> 0 | H36: =H$16*'P&L by Ctn'!Z$33 -> 10186.2 | I36: =I$16*'P&L by Ctn'!AZ$33 -> 0 | J36: =SUM(C36:I36) -> 3075443.4 | K36: =K$16*'P&L by Ctn'!L$33 -> #REF! | L36: =L$16*'P&L by Ctn'!S$33 -> #REF! | M36: =M$16*'P&L by Ctn'!Y$33 -> 633326.98 | N36: =N$16*'P&L by Ctn'!AF$33 -> 0 | O36: =O$16*'P&L by Ctn'!AL$33 -> 0 | P36: =P$16*'P&L by Ctn'!AI$33 -> 0 | Q36: =Q$16*'P&L by Ctn'!AO$33 -> 0 | R36: =SUM(K36:Q36) -> #REF! | S36: =S$16*'P&L by Ctn'!T$33 -> #REF! | T36: =T$16*'P&L by Ctn'!AA$33 -> 202107.47 | U36: =U$16*'P&L by Ctn'!AG$33 -> 1473878.3 | V36: =V$16*'P&L by Ctn'!AN$33 -> 0 | W36: =W$16*'P&L by Ctn'!AT$33 -> 0 | X36: =X$16*'P&L by Ctn'!AQ$33 -> 0 | Y36: =Y$16*'P&L by Ctn'!AW$33 -> 0 | Z36: =SUM(S36:Y36) -> #REF! | AA36: =AA$16*'P&L by Ctn'!AB$33 -> 661339.47 | AB36: =AB$16*'P&L by Ctn'!AI$33 -> 0 | AC36: =AC$16*'P&L by Ctn'!AO$33 -> 0 | AD36: =AD$16*'P&L by Ctn'!AV$33 -> 0 | AE36: =AE$16*'P&L by Ctn'!BB$33 -> 0 | AF36: =AF$16*'P&L by Ctn'!AY$33 -> 0 | AG36: =AG$16*'P&L by Ctn'!BE$33 -> 0 | AH36: =SUM(AA36:AG36) -> 661339.47 | AI36: =AI$16*'P&L by Ctn'!AJ$33 -> 0 | AJ36: =AJ$16*'P&L by Ctn'!AQ$33 -> 0 | AK36: =AK$16*'P&L by Ctn'!AW$33 -> 0 | AL36: =AL$16*'P&L by Ctn'!BD$33 -> 0 | AM36: =AM$16*'P&L by Ctn'!BJ$33 -> 0 | AN36: =AN$16*'P&L by Ctn'!BG$33 -> 0 | AO36: =AO$16*'P&L by Ctn'!BM$33 -> 0 | AP36: =SUM(AI36:AO36) -> 0 | AQ36: =AQ$16*'P&L by Ctn'!AR$33 -> 0 | AR36: =AR$16*'P&L by Ctn'!AY$33 -> 0 | AS36: =AS$16*'P&L by Ctn'!BE$33 -> 0 | AT36: =AT$16*'P&L by Ctn'!BL$33 -> 0 | AU36: =AU$16*'P&L by Ctn'!BR$33 -> 0 | AV36: =AV$16*'P&L by Ctn'!BO$33 -> 0 | AW36: =AW$16*'P&L by Ctn'!BU$33 -> 0 | AX36: =SUM(AQ36:AW36) -> 0 | AY36: =AY$16*'P&L by Ctn'!AZ$33 -> 0 | AZ36: =AZ$16*'P&L by Ctn'!BG$33 -> 0 | BA36: =BA$16*'P&L by Ctn'!BM$33 -> 0 | BB36: =BB$16*'P&L by Ctn'!BT$33 -> 0 | BC36: =BC$16*'P&L by Ctn'!BZ$33 -> 0 | BD36: =BD$16*'P&L by Ctn'!BW$33 -> 0 | BE36: =BE$16*'P&L by Ctn'!CC$33 -> 0 | BF36: =SUM(AY36:BE36) -> 0 | BG36: =BG$16*'P&L by Ctn'!BH$33 -> 0 | BH36: =BH$16*'P&L by Ctn'!BO$33 -> 0 | BI36: =BI$16*'P&L by Ctn'!BU$33 -> 0 | BJ36: =BJ$16*'P&L by Ctn'!CB$33 -> 0 | BK36: =BK$16*'P&L by Ctn'!CH$33 -> 0 | BL36: =BL$16*'P&L by Ctn'!CE$33 -> 0 | BM36: =BM$16*'P&L by Ctn'!CK$33 -> 0 | BN36: =SUM(BG36:BM36) -> 0 | BO36: =BO$16*'P&L by Ctn'!BP$33 -> 0 | BP36: =BP$16*'P&L by Ctn'!BW$33 -> 0 | BQ36: =BQ$16*'P&L by Ctn'!CC$33 -> 0 | BR36: =BR$16*'P&L by Ctn'!CJ$33 -> 0 | BS36: =BS$16*'P&L by Ctn'!CP$33 -> 0 | BT36: =BT$16*'P&L by Ctn'!CM$33 -> 0 | BU36: =BU$16*'P&L by Ctn'!CS$33 -> 0 | BV36: =SUM(BO36:BU36) -> 0 | BW36: =BW$16*'P&L by Ctn'!BX$33 -> 0 | BX36: =BX$16*'P&L by Ctn'!CE$33 -> 0 | BY36: =BY$16*'P&L by Ctn'!CK$33 -> 0 | BZ36: =BZ$16*'P&L by Ctn'!CR$33 -> 0 | CA36: =CA$16*'P&L by Ctn'!CX$33 -> 0 | CB36: =CB$16*'P&L by Ctn'!CU$33 -> 0 | CC36: =CC$16*'P&L by Ctn'!DA$33 -> 0 | CD36: =SUM(BW36:CC36) -> 0 | CE36: =CE$16*'P&L by Ctn'!CF$33 -> 0 | CF36: =CF$16*'P&L by Ctn'!CM$33 -> 0 | CG36: =CG$16*'P&L by Ctn'!CS$33 -> 0 | CH36: =CH$16*'P&L by Ctn'!CZ$33 -> 0 | CI36: =CI$16*'P&L by Ctn'!DF$33 -> 0 | CJ36: =CJ$16*'P&L by Ctn'!DC$33 -> 0 | CK36: =CK$16*'P&L by Ctn'!DI$33 -> 0 | CL36: =SUM(CE36:CK36) -> 0 | CM36: =CM$16*'P&L by Ctn'!CN$33 -> 0 | CN36: =CN$16*'P&L by Ctn'!CU$33 -> 0 | CO36: =CO$16*'P&L by Ctn'!DA$33 -> 0 | CP36: =CP$16*'P&L by Ctn'!DH$33 -> 0 | CQ36: =CQ$16*'P&L by Ctn'!DN$33 -> 0 | CR36: =CR$16*'P&L by Ctn'!DK$33 -> 0 | CS36: =CS$16*'P&L by Ctn'!DQ$33 -> 0 | CT36: =SUM(CM36:CS36) -> 0 | CU36: =CU$16*'P&L by Ctn'!CV$33 -> 0 | CV36: =CV$16*'P&L by Ctn'!DC$33 -> 0 | CW36: =CW$16*'P&L by Ctn'!DI$33 -> 0 | CX36: =CX$16*'P&L by Ctn'!DP$33 -> 0 | CY36: =CY$16*'P&L by Ctn'!DV$33 -> 0 | CZ36: =CZ$16*'P&L by Ctn'!DS$33 -> 0 | DA36: =DA$16*'P&L by Ctn'!DY$33 -> 0 | DB36: =SUM(CU36:DA36) -> 0 | DC36: =SUM(CV36:DB36) -> 0
A37: 25 | B37: Distributor Selling Value | C37: =C$16*'P&L by Ctn'!$E$34 -> 1903587.7 | D37: =D$16*'P&L by Ctn'!$K$34 -> 469615.82 | E37: =E$16*'P&L by Ctn'!$Q$34 -> 1049517 | F37: =F$16*'P&L by Ctn'!$W$34 -> 0 | G37: =G$16*'P&L by Ctn'!$AC$34 -> 0 | H37: =H$16*'P&L by Ctn'!Z$34 -> 10363.636 | I37: =I$16*'P&L by Ctn'!AZ$34 -> 0 | J37: =SUM(C37:I37) -> 3433084.2 | K37: =K$16*'P&L by Ctn'!L$34 -> #REF! | L37: =L$16*'P&L by Ctn'!S$34 -> #REF! | M37: =M$16*'P&L by Ctn'!Y$34 -> 644359.09 | N37: =N$16*'P&L by Ctn'!AF$34 -> 0 | O37: =O$16*'P&L by Ctn'!AL$34 -> 0 | P37: =P$16*'P&L by Ctn'!AI$34 -> 0 | Q37: =Q$16*'P&L by Ctn'!AO$34 -> 0 | R37: =SUM(K37:Q37) -> #REF! | S37: =S$16*'P&L by Ctn'!T$34 -> #REF! | T37: =T$16*'P&L by Ctn'!AA$34 -> 208000 | U37: =U$16*'P&L by Ctn'!AG$34 -> 1755277.8 | V37: =V$16*'P&L by Ctn'!AN$34 -> 0 | W37: =W$16*'P&L by Ctn'!AT$34 -> 0 | X37: =X$16*'P&L by Ctn'!AQ$34 -> 0 | Y37: =Y$16*'P&L by Ctn'!AW$34 -> 0 | Z37: =SUM(S37:Y37) -> #REF! | AA37: =AA$16*'P&L by Ctn'!AB$34 -> 857334.89 | AB37: =AB$16*'P&L by Ctn'!AI$34 -> 0 | AC37: =AC$16*'P&L by Ctn'!AO$34 -> 0 | AD37: =AD$16*'P&L by Ctn'!AV$34 -> 0 | AE37: =AE$16*'P&L by Ctn'!BB$34 -> 0 | AF37: =AF$16*'P&L by Ctn'!AY$34 -> 0 | AG37: =AG$16*'P&L by Ctn'!BE$34 -> 0 | AH37: =SUM(AA37:AG37) -> 857334.89 | AI37: =AI$16*'P&L by Ctn'!AJ$34 -> 0 | AJ37: =AJ$16*'P&L by Ctn'!AQ$34 -> 0 | AK37: =AK$16*'P&L by Ctn'!AW$34 -> 0 | AL37: =AL$16*'P&L by Ctn'!BD$34 -> 0 | AM37: =AM$16*'P&L by Ctn'!BJ$34 -> 0 | AN37: =AN$16*'P&L by Ctn'!BG$34 -> 0 | AO37: =AO$16*'P&L by Ctn'!BM$34 -> 0 | AP37: =SUM(AI37:AO37) -> 0 | AQ37: =AQ$16*'P&L by Ctn'!AR$34 -> 0 | AR37: =AR$16*'P&L by Ctn'!AY$34 -> 0 | AS37: =AS$16*'P&L by Ctn'!BE$34 -> 0 | AT37: =AT$16*'P&L by Ctn'!BL$34 -> 0 | AU37: =AU$16*'P&L by Ctn'!BR$34 -> 0 | AV37: =AV$16*'P&L by Ctn'!BO$34 -> 0 | AW37: =AW$16*'P&L by Ctn'!BU$34 -> 0 | AX37: =SUM(AQ37:AW37) -> 0 | AY37: =AY$16*'P&L by Ctn'!AZ$34 -> 0 | AZ37: =AZ$16*'P&L by Ctn'!BG$34 -> 0 | BA37: =BA$16*'P&L by Ctn'!BM$34 -> 0 | BB37: =BB$16*'P&L by Ctn'!BT$34 -> 0 | BC37: =BC$16*'P&L by Ctn'!BZ$34 -> 0 | BD37: =BD$16*'P&L by Ctn'!BW$34 -> 0 | BE37: =BE$16*'P&L by Ctn'!CC$34 -> 0 | BF37: =SUM(AY37:BE37) -> 0 | BG37: =BG$16*'P&L by Ctn'!BH$34 -> 0 | BH37: =BH$16*'P&L by Ctn'!BO$34 -> 0 | BI37: =BI$16*'P&L by Ctn'!BU$34 -> 0 | BJ37: =BJ$16*'P&L by Ctn'!CB$34 -> 0 | BK37: =BK$16*'P&L by Ctn'!CH$34 -> 0 | BL37: =BL$16*'P&L by Ctn'!CE$34 -> 0 | BM37: =BM$16*'P&L by Ctn'!CK$34 -> 0 | BN37: =SUM(BG37:BM37) -> 0 | BO37: =BO$16*'P&L by Ctn'!BP$34 -> 0 | BP37: =BP$16*'P&L by Ctn'!BW$34 -> 0 | BQ37: =BQ$16*'P&L by Ctn'!CC$34 -> 0 | BR37: =BR$16*'P&L by Ctn'!CJ$34 -> 0 | BS37: =BS$16*'P&L by Ctn'!CP$34 -> 0 | BT37: =BT$16*'P&L by Ctn'!CM$34 -> 0 | BU37: =BU$16*'P&L by Ctn'!CS$34 -> 0 | BV37: =SUM(BO37:BU37) -> 0 | BW37: =BW$16*'P&L by Ctn'!BX$34 -> 0 | BX37: =BX$16*'P&L by Ctn'!CE$34 -> 0 | BY37: =BY$16*'P&L by Ctn'!CK$34 -> 0 | BZ37: =BZ$16*'P&L by Ctn'!CR$34 -> 0 | CA37: =CA$16*'P&L by Ctn'!CX$34 -> 0 | CB37: =CB$16*'P&L by Ctn'!CU$34 -> 0 | CC37: =CC$16*'P&L by Ctn'!DA$34 -> 0 | CD37: =SUM(BW37:CC37) -> 0 | CE37: =CE$16*'P&L by Ctn'!CF$34 -> 0 | CF37: =CF$16*'P&L by Ctn'!CM$34 -> 0 | CG37: =CG$16*'P&L by Ctn'!CS$34 -> 0 | CH37: =CH$16*'P&L by Ctn'!CZ$34 -> 0 | CI37: =CI$16*'P&L by Ctn'!DF$34 -> 0 | CJ37: =CJ$16*'P&L by Ctn'!DC$34 -> 0 | CK37: =CK$16*'P&L by Ctn'!DI$34 -> 0 | CL37: =SUM(CE37:CK37) -> 0 | CM37: =CM$16*'P&L by Ctn'!CN$34 -> 0 | CN37: =CN$16*'P&L by Ctn'!CU$34 -> 0 | CO37: =CO$16*'P&L by Ctn'!DA$34 -> 0 | CP37: =CP$16*'P&L by Ctn'!DH$34 -> 0 | CQ37: =CQ$16*'P&L by Ctn'!DN$34 -> 0 | CR37: =CR$16*'P&L by Ctn'!DK$34 -> 0 | CS37: =CS$16*'P&L by Ctn'!DQ$34 -> 0 | CT37: =SUM(CM37:CS37) -> 0 | CU37: =CU$16*'P&L by Ctn'!CV$34 -> 0 | CV37: =CV$16*'P&L by Ctn'!DC$34 -> 0 | CW37: =CW$16*'P&L by Ctn'!DI$34 -> 0 | CX37: =CX$16*'P&L by Ctn'!DP$34 -> 0 | CY37: =CY$16*'P&L by Ctn'!DV$34 -> 0 | CZ37: =CZ$16*'P&L by Ctn'!DS$34 -> 0 | DA37: =DA$16*'P&L by Ctn'!DY$34 -> 0 | DB37: =SUM(CU37:DA37) -> 0 | DC37: =SUM(CV37:DB37) -> 0
A38: 26 | B38: Distributor Margin | C38: =C$16*'P&L by Ctn'!$E$35 -> 180672.61 | D38: =D$16*'P&L by Ctn'!$K$35 -> 44791.405 | E38: =E$16*'P&L by Ctn'!$Q$35 -> 79292.031 | F38: =F$16*'P&L by Ctn'!$W$35 -> 0 | G38: =G$16*'P&L by Ctn'!$AC$35 -> 0 | H38: =H$16*'P&L by Ctn'!Z$35 -> 79.487603 | I38: =I$16*'P&L by Ctn'!AZ$35 -> 0 | J38: =SUM(C38:I38) -> 304835.53 | K38: =K$16*'P&L by Ctn'!L$35 -> #REF! | L38: =L$16*'P&L by Ctn'!S$35 -> #REF! | M38: =M$16*'P&L by Ctn'!Y$35 -> 4942.1417 | N38: =N$16*'P&L by Ctn'!AF$35 -> 0 | O38: =O$16*'P&L by Ctn'!AL$35 -> 0 | P38: =P$16*'P&L by Ctn'!AI$35 -> 0 | Q38: =Q$16*'P&L by Ctn'!AO$35 -> 0 | R38: =SUM(K38:Q38) -> #REF! | S38: =S$16*'P&L by Ctn'!T$35 -> #REF! | T38: =T$16*'P&L by Ctn'!AA$35 -> 3856.8436 | U38: =U$16*'P&L by Ctn'!AG$35 -> 240689.89 | V38: =V$16*'P&L by Ctn'!AN$35 -> 0 | W38: =W$16*'P&L by Ctn'!AT$35 -> 0 | X38: =X$16*'P&L by Ctn'!AQ$35 -> 0 | Y38: =Y$16*'P&L by Ctn'!AW$35 -> 0 | Z38: =SUM(S38:Y38) -> #REF! | AA38: =AA$16*'P&L by Ctn'!AB$35 -> 173457.64 | AB38: =AB$16*'P&L by Ctn'!AI$35 -> 0 | AC38: =AC$16*'P&L by Ctn'!AO$35 -> 0 | AD38: =AD$16*'P&L by Ctn'!AV$35 -> 0 | AE38: =AE$16*'P&L by Ctn'!BB$35 -> 0 | AF38: =AF$16*'P&L by Ctn'!AY$35 -> 0 | AG38: =AG$16*'P&L by Ctn'!BE$35 -> 0 | AH38: =SUM(AA38:AG38) -> 173457.64 | AI38: =AI$16*'P&L by Ctn'!AJ$35 -> 0 | AJ38: =AJ$16*'P&L by Ctn'!AQ$35 -> 0 | AK38: =AK$16*'P&L by Ctn'!AW$35 -> 0 | AL38: =AL$16*'P&L by Ctn'!BD$35 -> 0 | AM38: =AM$16*'P&L by Ctn'!BJ$35 -> 0 | AN38: =AN$16*'P&L by Ctn'!BG$35 -> 0 | AO38: =AO$16*'P&L by Ctn'!BM$35 -> 0 | AP38: =SUM(AI38:AO38) -> 0 | AQ38: =AQ$16*'P&L by Ctn'!AR$35 -> 0 | AR38: =AR$16*'P&L by Ctn'!AY$35 -> 0 | AS38: =AS$16*'P&L by Ctn'!BE$35 -> 0 | AT38: =AT$16*'P&L by Ctn'!BL$35 -> 0 | AU38: =AU$16*'P&L by Ctn'!BR$35 -> 0 | AV38: =AV$16*'P&L by Ctn'!BO$35 -> 0 | AW38: =AW$16*'P&L by Ctn'!BU$35 -> 0 | AX38: =SUM(AQ38:AW38) -> 0 | AY38: =AY$16*'P&L by Ctn'!AZ$35 -> 0 | AZ38: =AZ$16*'P&L by Ctn'!BG$35 -> 0 | BA38: =BA$16*'P&L by Ctn'!BM$35 -> 0 | BB38: =BB$16*'P&L by Ctn'!BT$35 -> 0 | BC38: =BC$16*'P&L by Ctn'!BZ$35 -> 0 | BD38: =BD$16*'P&L by Ctn'!BW$35 -> 0 | BE38: =BE$16*'P&L by Ctn'!CC$35 -> 0 | BF38: =SUM(AY38:BE38) -> 0 | BG38: =BG$16*'P&L by Ctn'!BH$35 -> 0 | BH38: =BH$16*'P&L by Ctn'!BO$35 -> 0 | BI38: =BI$16*'P&L by Ctn'!BU$35 -> 0 | BJ38: =BJ$16*'P&L by Ctn'!CB$35 -> 0 | BK38: =BK$16*'P&L by Ctn'!CH$35 -> 0 | BL38: =BL$16*'P&L by Ctn'!CE$35 -> 0 | BM38: =BM$16*'P&L by Ctn'!CK$35 -> 0 | BN38: =SUM(BG38:BM38) -> 0 | BO38: =BO$16*'P&L by Ctn'!BP$35 -> 0 | BP38: =BP$16*'P&L by Ctn'!BW$35 -> 0 | BQ38: =BQ$16*'P&L by Ctn'!CC$35 -> 0 | BR38: =BR$16*'P&L by Ctn'!CJ$35 -> 0 | BS38: =BS$16*'P&L by Ctn'!CP$35 -> 0 | BT38: =BT$16*'P&L by Ctn'!CM$35 -> 0 | BU38: =BU$16*'P&L by Ctn'!CS$35 -> 0 | BV38: =SUM(BO38:BU38) -> 0 | BW38: =BW$16*'P&L by Ctn'!BX$35 -> 0 | BX38: =BX$16*'P&L by Ctn'!CE$35 -> 0 | BY38: =BY$16*'P&L by Ctn'!CK$35 -> 0 | BZ38: =BZ$16*'P&L by Ctn'!CR$35 -> 0 | CA38: =CA$16*'P&L by Ctn'!CX$35 -> 0 | CB38: =CB$16*'P&L by Ctn'!CU$35 -> 0 | CC38: =CC$16*'P&L by Ctn'!DA$35 -> 0 | CD38: =SUM(BW38:CC38) -> 0 | CE38: =CE$16*'P&L by Ctn'!CF$35 -> 0 | CF38: =CF$16*'P&L by Ctn'!CM$35 -> 0 | CG38: =CG$16*'P&L by Ctn'!CS$35 -> 0 | CH38: =CH$16*'P&L by Ctn'!CZ$35 -> 0 | CI38: =CI$16*'P&L by Ctn'!DF$35 -> 0 | CJ38: =CJ$16*'P&L by Ctn'!DC$35 -> 0 | CK38: =CK$16*'P&L by Ctn'!DI$35 -> 0 | CL38: =SUM(CE38:CK38) -> 0 | CM38: =CM$16*'P&L by Ctn'!CN$35 -> 0 | CN38: =CN$16*'P&L by Ctn'!CU$35 -> 0 | CO38: =CO$16*'P&L by Ctn'!DA$35 -> 0 | CP38: =CP$16*'P&L by Ctn'!DH$35 -> 0 | CQ38: =CQ$16*'P&L by Ctn'!DN$35 -> 0 | CR38: =CR$16*'P&L by Ctn'!DK$35 -> 0 | CS38: =CS$16*'P&L by Ctn'!DQ$35 -> 0 | CT38: =SUM(CM38:CS38) -> 0 | CU38: =CU$16*'P&L by Ctn'!CV$35 -> 0 | CV38: =CV$16*'P&L by Ctn'!DC$35 -> 0 | CW38: =CW$16*'P&L by Ctn'!DI$35 -> 0 | CX38: =CX$16*'P&L by Ctn'!DP$35 -> 0 | CY38: =CY$16*'P&L by Ctn'!DV$35 -> 0 | CZ38: =CZ$16*'P&L by Ctn'!DS$35 -> 0 | DA38: =DA$16*'P&L by Ctn'!DY$35 -> 0 | DB38: =SUM(CU38:DA38) -> 0 | DC38: =SUM(CV38:DB38) -> 0
A39: 27 | B39: Distributor Margin % | C39: =IFERROR(C38/C$37,0) -> 0.094911629 | D39: =IFERROR(D38/D$37,0) -> 0.095378825 | E39: =IFERROR(E38/E$37,0) -> 0.075550976 | F39: =IFERROR(F38/F$37,0) -> 0 | G39: =IFERROR(G38/G$37,0) -> 0 | H39: =IFERROR(H38/H$37,0) -> 0.0076698565 | I39: =IFERROR(I38/I$37,0) -> 0 | J39: =IFERROR(J38/J$37,0) -> 0.088793493 | ... DC39: =IFERROR(DC38/DC$37,0) -> 0
A40: 28
A41: 29 | B41: GP1 - TP IOD | C41: =C20-C22 -> 361358.74 | D41: =D20-D22 -> 63046.294 | E41: =E20-E22 -> 50779.008 | F41: =F20-F22 -> 0 | G41: =G20-G22 -> 0 | H41: =H20-H22 -> 1200.025 | I41: =I20-I22 -> 540.61502 | J41: =J20-J22 -> 476924.69 | ... DC41: =DC20-DC22 -> 671011.65
A42: 30 | B42: GP1-TP IOD % | C42: =IFERROR(C41/C18,0) -> 0.24295881 | D42: =IFERROR(D41/D18,0) -> 0.17197504 | E42: =IFERROR(E41/E18,0) -> 0.062714352 | F42: =IFERROR(F41/F18,0) -> 0 | G42: =IFERROR(G41/G18,0) -> 0 | H42: =IFERROR(H41/H18,0) -> 0.1210679 | I42: =IFERROR(I41/I18,0) -> 0.075984571 | J42: =IFERROR(J41/J18,0) -> 0.17791445 | ... DC42: =IFERROR(DC41/DC18,0) -> 0.147176

Sheet P&L TOTAL
B2: Jan-Mar
B3: Jan-Mar | C3: GSS LOKAL 40 | D3: IIP LOKAL 40 | E3: IHAG LOKAL 40 | F3: GPD LOKAL 40 | G3: CGSS MA (NS) 12 | H3: PMAD LOKAL 12 | I3: PMAJ LOKAL 24 | J3: TOTAL
B4: Vol (pcs) | C4: ='STT STD - By SKU 150'!C78 -> 22738760 | D4: ='STT STD - By SKU 150'!D78 -> 6400000 | E4: ='STT STD - By SKU 150'!E78 -> 20521000 | F4: ='STT STD - By SKU 150'!F78 -> 64000 | G4: ='STT STD - By SKU 150'!G78 -> 41568 | H4: ='STT STD - By SKU 150'!H78 -> 143700 | I4: ='STT STD - By SKU 150'!I78 -> 85824 | J4: =SUM(C4:I4) -> 49994852
B5: Vol (ctn) | C5: =C4/RIGHT(C3,2) -> 568469 | D5: =D4/RIGHT(D3,2) -> 160000 | E5: =E4/RIGHT(E3,2) -> 513025 | F5: =F4/RIGHT(F3,2) -> 1600 | G5: =G4/RIGHT(G3,2) -> 3464 | H5: =H4/RIGHT(H3,2) -> 11975 | I5: =I4/RIGHT(I3,2) -> 3576 | J5: =SUM(C5:I5) -> 1262109
B6: CIF | C6: =C$5*'P&L by Ctn'!E$12 -> 3435239.1 | D6: =D$5*'P&L by Ctn'!K$12 -> 966005.05 | E6: =E$5*'P&L by Ctn'!Q$12 -> 3101028.1 | F6: =F$5*'P&L by Ctn'!X$12 -> 9683.5398 | G6: =G$5*'P&L by Ctn'!AD$12 -> 17493.715 | H6: =H$5*'P&L by Ctn'!AA$12 -> 54513.224 | I6: =I$5*'P&L by Ctn'!AG$12 -> 23430.019 | J6: =SUM(C6:I6) -> 7607392.8
B7: FOB | C7: =C$5*'P&L by Ctn'!E$13 -> 3259136.6 | D7: =D$5*'P&L by Ctn'!K$13 -> 916503.57 | E7: =E$5*'P&L by Ctn'!Q$13 -> 2926722.9 | F7: =F$5*'P&L by Ctn'!X$13 -> 9184 | G7: =G$5*'P&L by Ctn'!AD$13 -> 16627.2 | H7: =H$5*'P&L by Ctn'!AA$13 -> 51492.5 | I7: =I$5*'P&L by Ctn'!AG$13 -> 21634.8 | J7: =SUM(C7:I7) -> 7201301.5
B8: COGS | C8: =C$5*'P&L by Ctn'!E$14 -> 2196449.4 | D8: =D$5*'P&L by Ctn'!K$14 -> 686314.21 | E8: =E$5*'P&L by Ctn'!Q$14 -> 2603618.7 | F8: =F$5*'P&L by Ctn'!X$14 -> 6486.4865 | G8: =G$5*'P&L by Ctn'!AD$14 -> 9830.2703 | H8: =H$5*'P&L by Ctn'!AA$14 -> 35925 | I8: =I$5*'P&L by Ctn'!AG$14 -> 15077.189 | J8: =SUM(C8:I8) -> 5553701.3
B9: GP1 | C9: =C7-C8 -> 1062687.1 | D9: =D7-D8 -> 230189.36 | E9: =E7-E8 -> 323104.17 | F9: =F7-F8 -> 2697.5135 | G9: =G7-G8 -> 6796.9297 | H9: =H7-H8 -> 15567.5 | I9: =I7-I8 -> 6557.6108 | J9: =J7-J8 -> 1647600.2
B10: GP1% | C10: =IFERROR(C9/C$7,0) -> 0.32606401 | D10: =IFERROR(D9/D$7,0) -> 0.25116035 | E10: =IFERROR(E9/E$7,0) -> 0.11039794 | F10: =IFERROR(F9/F$7,0) -> 0.29371881 | G10: =IFERROR(G9/G$7,0) -> 0.40878378 | H10: =IFERROR(H9/H$7,0) -> 0.30232558 | I10: =IFERROR(I9/I$7,0) -> 0.30310476 | J10: =IFERROR(J9/J$7,0) -> 0.22879201
B11: TP | C11: =C$5*'P&L by Ctn'!E$17 -> 451252.03 | D11: =D$5*'P&L by Ctn'!K$17 -> 126235.88 | E11: =E$5*'P&L by Ctn'!Q$17 -> 331925.62 | F11: =F$5*'P&L by Ctn'!X$17 -> 1280 | G11: =G$5*'P&L by Ctn'!AD$17 -> 3464 | H11: =H$5*'P&L by Ctn'!AA$17 -> 10777.5 | I11: =I$5*'P&L by Ctn'!AG$17 -> 5185.2 | J11: =SUM(C11:I11) -> 930120.22
B12: TP% | C12: =IFERROR(C11/C$7,0) -> 0.13845754 | D12: =IFERROR(D11/D$7,0) -> 0.13773637 | E12: =IFERROR(E11/E$7,0) -> 0.11341204 | F12: =IFERROR(F11/F$7,0) -> 0.13937282 | G12: =IFERROR(G11/G$7,0) -> 0.20833333 | H12: =IFERROR(H11/H$7,0) -> 0.20930233 | I12: =IFERROR(I11/I$7,0) -> 0.23966942 | J12: =IFERROR(J11/J$7,0) -> 0.12916002
B13: MF | C13: =C$5*'P&L by Ctn'!E$20 -> 503159.25 | D13: =D$5*'P&L by Ctn'!K$20 -> 63130.562 | E13: =E$5*'P&L by Ctn'!Q$20 -> 0 | F13: =F$5*'P&L by Ctn'!X$20 -> 0 | G13: =G$5*'P&L by Ctn'!AD$20 -> 0 | H13: =H$5*'P&L by Ctn'!AA$20 -> 0 | I13: =I$5*'P&L by Ctn'!AG$20 -> 0 | J13: =SUM(C13:I13) -> 566289.81
B14: MF% | C14: =IFERROR(C13/C$7,0) -> 0.15438422 | D14: =IFERROR(D13/D$7,0) -> 0.06888196 | E14: =IFERROR(E13/E$7,0) -> 0 | F14: =IFERROR(F13/F$7,0) -> 0 | G14: =IFERROR(G13/G$7,0) -> 0 | H14: =IFERROR(H13/H$7,0) -> 0 | I14: =IFERROR(I13/I$7,0) -> 0 | J14: =IFERROR(J13/J$7,0) -> 0.078637148
B15: VSE | C15: =C$5*'P&L by Ctn'!E$22 -> 77976.174 | D15: =D$5*'P&L by Ctn'!K$22 -> 16094.403 | E15: =E$5*'P&L by Ctn'!Q$22 -> 56184.003 | F15: =F$5*'P&L by Ctn'!X$22 -> 184.28635 | G15: =G$5*'P&L by Ctn'!AD$22 -> 127.18962 | H15: =H$5*'P&L by Ctn'!AA$22 -> 459.73626 | I15: =I$5*'P&L by Ctn'!AG$22 -> 295.56106 | J15: =SUM(C15:I15) -> 151321.35
B16: GP2 | C16: =C9-C11-C13-C15 -> 30299.684 | D16: =D9-D11-D13-D15 -> 24728.514 | E16: =E9-E11-E13-E15 -> -65005.448 | F16: =F9-F11-F13-F15 -> 1233.2272 | G16: =G9-G11-G13-G15 -> 3205.7401 | H16: =H9-H11-H13-H15 -> 4330.2637 | I16: =I9-I11-I13-I15 -> 1076.8497 | J16: =J9-J11-J13-J15 -> -131.16912
B17: GP2% | C17: =IFERROR(C16/C$7,0) -> 0.0092968438 | D17: =IFERROR(D16/D$7,0) -> 0.026981362 | E17: =IFERROR(E16/E$7,0) -> -0.022211002 | F17: =IFERROR(F16/F$7,0) -> 0.13427996 | G17: =IFERROR(G16/G$7,0) -> 0.19280096 | H17: =IFERROR(H16/H$7,0) -> 0.084095038 | I17: =IFERROR(I16/I$7,0) -> 0.049773964 | J17: =IFERROR(J16/J$7,0) -> -1.8214641e-05
B18: A&P | C18: =C$5*'P&L by Ctn'!E$25 -> 0 | D18: =D$5*'P&L by Ctn'!K$25 -> 0 | E18: =E$5*'P&L by Ctn'!Q$25 -> 0 | F18: =F$5*'P&L by Ctn'!X$25 -> 0 | G18: =G$5*'P&L by Ctn'!AD$25 -> 0 | H18: =H$5*'P&L by Ctn'!AA$25 -> 0 | I18: =I$5*'P&L by Ctn'!AG$25 -> 0 | J18: =SUM(C18:I18) -> 0
B19: GP3 | C19: =C16-C18 -> 30299.684 | D19: =D16-D18 -> 24728.514 | E19: =E16-E18 -> -65005.448 | F19: =F16-F18 -> 1233.2272 | G19: =G16-G18 -> 3205.7401 | H19: =H16-H18 -> 4330.2637 | I19: =I16-I18 -> 1076.8497 | J19: =J16-J18 -> -131.16912
B20: GP3% | C20: =IFERROR(C19/C$7,0) -> 0.0092968438 | D20: =IFERROR(D19/D$7,0) -> 0.026981362 | E20: =IFERROR(E19/E$7,0) -> -0.022211002 | F20: =IFERROR(F19/F$7,0) -> 0.13427996 | G20: =IFERROR(G19/G$7,0) -> 0.19280096 | H20: =IFERROR(H19/H$7,0) -> 0.084095038 | I20: =IFERROR(I19/I$7,0) -> 0.049773964 | J20: =IFERROR(J19/J$7,0) -> -1.8214641e-05
B21: Freight Difference | C21: =C$5*'P&L by Ctn'!E$28 -> -2563.5742 | D21: =D$5*'P&L by Ctn'!K$28 -> 4332.1995 | E21: =E$5*'P&L by Ctn'!Q$28 -> -4610.7011 | F21: =F$5*'P&L by Ctn'!X$28 -> -123.96694 | G21: =G$5*'P&L by Ctn'!AD$28 -> -210.36437 | H21: =H$5*'P&L by Ctn'!AA$28 -> -748.4375 | I21: =I$5*'P&L by Ctn'!AG$28 -> -447 | J21: =SUM(C21:I21) -> -4371.8447
B22: GP4 | C22: =C19-C21 -> 32863.258 | D22: =D19-D21 -> 20396.315 | E22: =E19-E21 -> -60394.747 | F22: =F19-F21 -> 1357.1941 | G22: =G19-G21 -> 3416.1045 | H22: =H19-H21 -> 5078.7012 | I22: =I19-I21 -> 1523.8497 | J22: =J19-J21 -> 4240.6756
B23: GP4% | C23: =IFERROR(C22/C$7,0) -> 0.010083425 | D23: =IFERROR(D22/D$7,0) -> 0.022254485 | E23: =IFERROR(E22/E$7,0) -> -0.020635622 | F23: =IFERROR(F22/F$7,0) -> 0.1477781 | G23: =IFERROR(G22/G$7,0) -> 0.20545278 | H23: =IFERROR(H22/H$7,0) -> 0.098629922 | I23: =IFERROR(I22/I$7,0) -> 0.070435121 | J23: =IFERROR(J22/J$7,0) -> 0.00058887627
B25: Distributor Buying Value | C25: =C$5*'P&L by Ctn'!E$33 -> 3709361.6 | D25: =D$5*'P&L by Ctn'!K$33 -> 1043425.2 | E25: =E$5*'P&L by Ctn'!Q$33 -> 3452334.3 | F25: =F$5*'P&L by Ctn'!X$33 -> 10449.89 | G25: =G$5*'P&L by Ctn'!AD$33 -> 17466.507 | H25: =H$5*'P&L by Ctn'!AA$33 -> 55005.386 | I25: =I$5*'P&L by Ctn'!AG$33 -> 23754.766 | J25: =SUM(C25:I25) -> 8311797.6
B26: Distributor Selling Value | C26: =C$5*'P&L by Ctn'!E$34 -> 4171281.8 | D26: =D$5*'P&L by Ctn'!K$34 -> 1174039.5 | E26: =E$5*'P&L by Ctn'!Q$34 -> 3793619.7 | F26: =F$5*'P&L by Ctn'!X$34 -> 11740.395 | G26: =G$5*'P&L by Ctn'!AD$34 -> 21130.4 | H26: =H$5*'P&L by Ctn'!AA$34 -> 56609.091 | I26: =I$5*'P&L by Ctn'!AG$34 -> 28290.133 | J26: =SUM(C26:I26) -> 9256711.1
B27: Distributor Margin | C27: =C$5*'P&L by Ctn'!E$35 -> 395903.15 | D27: =D$5*'P&L by Ctn'!K$35 -> 111978.51 | E27: =E$5*'P&L by Ctn'!Q$35 -> 286611.67 | F27: =F$5*'P&L by Ctn'!X$35 -> 1105.5684 | G27: =G$5*'P&L by Ctn'!AD$35 -> 3216.0673 | H27: =H$5*'P&L by Ctn'!AA$35 -> 1049.675 | I27: =I$5*'P&L by Ctn'!AG$35 -> 3879.243 | J27: =SUM(C27:I27) -> 803743.88
B28: Distributor Margin % | C28: =IFERROR(C27/C$26,0) -> 0.094911629 | D28: =IFERROR(D27/D$26,0) -> 0.095378825 | E28: =IFERROR(E27/E$26,0) -> 0.075550976 | F28: =IFERROR(F27/F$26,0) -> 0.094167899 | G28: =IFERROR(G27/G$26,0) -> 0.15220097 | H28: =IFERROR(H27/H$26,0) -> 0.018542517 | I28: =IFERROR(I27/I$26,0) -> 0.13712353 | J28: =IFERROR(J27/J$26,0) -> 0.086828235
B30: GP1 - TP IOD | C30: =C9-C11 -> 611435.11 | D30: =D9-D11 -> 103953.48 | E30: =E9-E11 -> -8821.4451 | F30: =F9-F11 -> 1417.5135 | G30: =G9-G11 -> 3332.9297 | H30: =H9-H11 -> 4790 | I30: =I9-I11 -> 1372.4108 | J30: =J9-J11 -> 717479.99
B31: GP1-TP IOD % | C31: =IFERROR(C30/C7,0) -> 0.18760647 | D31: =IFERROR(D30/D7,0) -> 0.11342398 | E31: =IFERROR(E30/E7,0) -> -0.0030141033 | F31: =IFERROR(F30/F7,0) -> 0.15434598 | G31: =IFERROR(G30/G7,0) -> 0.20045045 | H31: =IFERROR(H30/H7,0) -> 0.093023256 | I31: =IFERROR(I30/I7,0) -> 0.063435336 | J31: =IFERROR(J30/J7,0) -> 0.099631989
B33: COGS Apr-May Scenario 3 | L33: COGS Apr-May Scenario +15%
B34: Apr-May | C34: GSS LOKAL 40 | D34: IIP LOKAL 40 | E34: IHAG LOKAL 40 | F34: GPD LOKAL 40 | G34: CGSS MA (NS) 12 | H34: PMAD LOKAL 12 | I34: PMAJ LOKAL 24 | J34: TOTAL | L34: Apr-May | M34: GSS LOKAL 40 | N34: IIP LOKAL 40 | O34: IHAG LOKAL 40 | P34: GPD LOKAL 40 | Q34: CGSS MA (NS) 12 | R34: PMAD LOKAL 12 | S34: PMAJ LOKAL 24 | T34: TOTAL
B35: Vol (pcs) | C35: =SUM('STT STD - By SKU 150'!$C8:$C9) -> 9076160 | D35: =SUM('STT STD - By SKU 150'!$D8:$D9) -> 2560000 | E35: =SUM('STT STD - By SKU 150'!$E8:$E9) -> 8662000 | F35: =SUM('STT STD - By SKU 150'!$F8:$F9) -> 0 | G35: =SUM('STT STD - By SKU 150'!$G8:$G9) -> 28800 | H35: =SUM('STT STD - By SKU 150'!$H8:$H9) -> 57600 | I35: =SUM('STT STD - By SKU 150'!$I8:$I9) -> 57600 | J35: =SUM(C35:I35) -> 20442160 | L35: Vol (pcs) | M35: =SUM('STT STD - By SKU 150'!$C8:$C9) -> 9076160 | N35: =SUM('STT STD - By SKU 150'!$D8:$D9) -> 2560000 | O35: =SUM('STT STD - By SKU 150'!$E8:$E9) -> 8662000 | P35: =SUM('STT STD - By SKU 150'!$F8:$F9) -> 0 | Q35: =SUM('STT STD - By SKU 150'!$G8:$G9) -> 28800 | R35: =SUM('STT STD - By SKU 150'!$H8:$H9) -> 57600 | S35: =SUM('STT STD - By SKU 150'!$I8:$I9) -> 57600 | T35: =SUM(M35:S35) -> 20442160
B36: Vol (ctn) | C36: =C35/RIGHT(C34,2) -> 226904 | D36: =D35/RIGHT(D34,2) -> 64000 | E36: =E35/RIGHT(E34,2) -> 216550 | F36: =F35/RIGHT(F34,2) -> 0 | G36: =G35/RIGHT(G34,2) -> 2400 | H36: =H35/RIGHT(H34,2) -> 4800 | I36: =I35/RIGHT(I34,2) -> 2400 | J36: =SUM(C36:I36) -> 517054 | L36: Vol (ctn) | M36: =M35/RIGHT(M34,2) -> 226904 | N36: =N35/RIGHT(N34,2) -> 64000 | O36: =O35/RIGHT(O34,2) -> 216550 | P36: =P35/RIGHT(P34,2) -> 0 | Q36: =Q35/RIGHT(Q34,2) -> 2400 | R36: =R35/RIGHT(R34,2) -> 4800 | S36: =S35/RIGHT(S34,2) -> 2400 | T36: =SUM(M36:S36) -> 517054
B37: CIF | C37: =SUM($C36:$C36)*'P&L by Ctn'!$E$12 -> 1371173.3 | D37: =SUM($D36:$D36)*'P&L by Ctn'!$K$12 -> 386402.02 | E37: =SUM($E36:$E36)*'P&L by Ctn'!$Q$12 -> 1308956.9 | F37: =SUM($F36:$F36)*'P&L by Ctn'!$X$12 -> 0 | G37: =SUM($G36:$G36)*'P&L by Ctn'!$AD$12 -> 12120.357 | H37: =SUM($H36:$H36)*'P&L by Ctn'!$AA$12 -> 21850.812 | I37: =SUM($I36:$I36)*'P&L by Ctn'!$AG$12 -> 15724.845 | J37: =SUM(C37:I37) -> 3116228.2 | L37: CIF | M37: =SUM($C36:$C36)*'P&L by Ctn'!$E$12 -> 1371173.3 | N37: =SUM($D36:$D36)*'P&L by Ctn'!$K$12 -> 386402.02 | O37: =SUM($E36:$E36)*'P&L by Ctn'!$Q$12 -> 1308956.9 | P37: =SUM($F36:$F36)*'P&L by Ctn'!$X$12 -> 0 | Q37: =SUM($G36:$G36)*'P&L by Ctn'!$AD$12 -> 12120.357 | R37: =SUM($H36:$H36)*'P&L by Ctn'!$AA$12 -> 21850.812 | S37: =SUM($I36:$I36)*'P&L by Ctn'!$AG$12 -> 15724.845 | T37: =SUM(M37:S37) -> 3116228.2
B38: FOB | C38: =SUM($C36:$C36)*'P&L by Ctn'!$E$13 -> 1300882.1 | D38: =SUM($D36:$D36)*'P&L by Ctn'!$K$13 -> 366601.43 | E38: =SUM($E36:$E36)*'P&L by Ctn'!$Q$13 -> 1235382 | F38: =SUM($F36:$F36)*'P&L by Ctn'!$X$13 -> 0 | G38: =SUM($G36:$G36)*'P&L by Ctn'!$AD$13 -> 11520 | H38: =SUM($H36:$H36)*'P&L by Ctn'!$AA$13 -> 20640 | I38: =SUM($I36:$I36)*'P&L by Ctn'!$AG$13 -> 14520 | J38: =SUM(C38:I38) -> 2949545.5 | L38: FOB | M38: =SUM($C36:$C36)*'P&L by Ctn'!$E$13 -> 1300882.1 | N38: =SUM($D36:$D36)*'P&L by Ctn'!$K$13 -> 366601.43 | O38: =SUM($E36:$E36)*'P&L by Ctn'!$Q$13 -> 1235382 | P38: =SUM($F36:$F36)*'P&L by Ctn'!$X$13 -> 0 | Q38: =SUM($G36:$G36)*'P&L by Ctn'!$AD$13 -> 11520 | R38: =SUM($H36:$H36)*'P&L by Ctn'!$AA$13 -> 20640 | S38: =SUM($I36:$I36)*'P&L by Ctn'!$AG$13 -> 14520 | T38: =SUM(M38:S38) -> 2949545.5
B39: COGS | C39: =SUM($C36:$C36)*'P&L by Ctn'!$F$14 -> #REF! | D39: =SUM($D36:$D36)*'P&L by Ctn'!$L$14 -> #REF! | E39: =SUM($E36:$E36)*'P&L by Ctn'!$S$14 -> #REF! | F39: =SUM($F36:$F36)*'P&L by Ctn'!$X$14 -> 0 | G39: =SUM($G36:$G36)*'P&L by Ctn'!$AD$14 -> 6810.8108 | H39: =SUM($H36:$H36)*'P&L by Ctn'!$AA$14 -> 14400 | I39: =SUM($I36:$I36)*'P&L by Ctn'!$AG$14 -> 10118.919 | J39: =SUM(C39:I39) -> #REF! | L39: COGS | M39: =SUM($C36:$C36)*'P&L by Ctn'!$H$14 -> #REF! | N39: =SUM($D36:$D36)*'P&L by Ctn'!$N$14 -> #REF! | O39: =SUM($E36:$E36)*'P&L by Ctn'!$U$14 -> #REF! | P39: =SUM($F36:$F36)*'P&L by Ctn'!$X$14 -> 0 | Q39: =SUM($G36:$G36)*'P&L by Ctn'!$AD$14 -> 6810.8108 | R39: =SUM($H36:$H36)*'P&L by Ctn'!$AA$14 -> 14400 | S39: =SUM($I36:$I36)*'P&L by Ctn'!$AG$14 -> 10118.919 | T39: =SUM(M39:S39) -> #REF!
B40: GP1 | C40: =C38-C39 -> #REF! | D40: =D38-D39 -> #REF! | E40: =E38-E39 -> #REF! | F40: =F38-F39 -> 0 | G40: =G38-G39 -> 4709.1892 | H40: =H38-H39 -> 6240 | I40: =I38-I39 -> 4401.0811 | J40: =SUM(C40:I40) -> #REF! | L40: GP1 | M40: =M38-M39 -> #REF! | N40: =N38-N39 -> #REF! | O40: =O38-O39 -> #REF! | P40: =P38-P39 -> 0 | Q40: =Q38-Q39 -> 4709.1892 | R40: =R38-R39 -> 6240 | S40: =S38-S39 -> 4401.0811 | T40: =SUM(M40:S40) -> #REF!
B41: GP1% | C41: =IFERROR($C40/$C$38,0) -> 0 | D41: =IFERROR($D40/$D$38,0) -> 0 | E41: =IFERROR($E40/$E$38,0) -> 0 | F41: =IFERROR($F40/$F$38,0) -> 0 | G41: =IFERROR($G40/$G$38,0) -> 0.40878378 | H41: =IFERROR($H40/$H$38,0) -> 0.30232558 | I41: =IFERROR($I40/$I$38,0) -> 0.30310476 | J41: =IFERROR(J40/J$38,0) -> 0 | L41: GP1% | M41: =IFERROR(M40/M$38,0) -> 0 | N41: =IFERROR(N40/N$38,0) -> 0 | O41: =IFERROR(O40/O$38,0) -> 0 | P41: =IFERROR(P40/P$38,0) -> 0 | Q41: =IFERROR(Q40/Q$38,0) -> 0.40878378 | R41: =IFERROR(R40/R$38,0) -> 0.30232558 | S41: =IFERROR(S40/S$38,0) -> 0.30310476 | T41: =IFERROR(T40/T$38,0) -> 0
B42: TP | C42: =SUM($C36:$C36)*'P&L by Ctn'!$E$17 -> 180116.93 | D42: =SUM($D36:$D36)*'P&L by Ctn'!$K$17 -> 50494.35 | E42: =SUM($E36:$E36)*'P&L by Ctn'!$Q$17 -> 140107.19 | F42: =SUM($F36:$F36)*'P&L by Ctn'!$X$17 -> 0 | G42: =SUM($G36:$G36)*'P&L by Ctn'!$AD$17 -> 2400 | H42: =SUM($H36:$H36)*'P&L by Ctn'!$AA$17 -> 4320 | I42: =SUM($I36:$I36)*'P&L by Ctn'!$AG$17 -> 3480 | J42: =SUM(C42:I42) -> 380918.47 | L42: TP | M42: =SUM($C36:$C36)*'P&L by Ctn'!$E$17 -> 180116.93 | N42: =SUM($D36:$D36)*'P&L by Ctn'!$K$17 -> 50494.35 | O42: =SUM($E36:$E36)*'P&L by Ctn'!$Q$17 -> 140107.19 | P42: =SUM($F36:$F36)*'P&L by Ctn'!$X$17 -> 0 | Q42: =SUM($G36:$G36)*'P&L by Ctn'!$AD$17 -> 2400 | R42: =SUM($H36:$H36)*'P&L by Ctn'!$AA$17 -> 4320 | S42: =SUM($I36:$I36)*'P&L by Ctn'!$AG$17 -> 3480 | T42: =SUM(M42:S42) -> 380918.47
B43: TP% | C43: =IFERROR($C42/$C$38,0) -> 0.13845754 | D43: =IFERROR($D42/$D$38,0) -> 0.13773637 | E43: =IFERROR($E42/$E$38,0) -> 0.11341204 | F43: =IFERROR($F42/$F$38,0) -> 0 | G43: =IFERROR($G42/$G$38,0) -> 0.20833333 | H43: =IFERROR($H42/$H$38,0) -> 0.20930233 | I43: =IFERROR($I42/$I$38,0) -> 0.23966942 | J43: =IFERROR(J42/J$38,0) -> 0.1291448 | L43: TP% | M43: =IFERROR(M42/M$38,0) -> 0.13845754 | N43: =IFERROR(N42/N$38,0) -> 0.13773637 | O43: =IFERROR(O42/O$38,0) -> 0.11341204 | P43: =IFERROR(P42/P$38,0) -> 0 | Q43: =IFERROR(Q42/Q$38,0) -> 0.20833333 | R43: =IFERROR(R42/R$38,0) -> 0.20930233 | S43: =IFERROR(S42/S$38,0) -> 0.23966942 | T43: =IFERROR(T42/T$38,0) -> 0.1291448
B44: MF | C44: =SUM($C36:$C36)*'P&L by Ctn'!$E$20 -> 200835.66 | D44: =SUM($D36:$D36)*'P&L by Ctn'!$K$20 -> 25252.225 | E44: =SUM($E36:$E36)*'P&L by Ctn'!$Q$20 -> 0 | F44: =SUM($F36:$F36)*'P&L by Ctn'!$X$20 -> 0 | G44: =SUM($G36:$G36)*'P&L by Ctn'!$AD$20 -> 0 | H44: =SUM($H36:$H36)*'P&L by Ctn'!$AA$20 -> 0 | I44: =SUM($I36:$I36)*'P&L by Ctn'!$AG$20 -> 0 | J44: =SUM(C44:I44) -> 226087.88 | L44: MF | M44: =SUM($C36:$C36)*'P&L by Ctn'!$E$20 -> 200835.66 | N44: =SUM($D36:$D36)*'P&L by Ctn'!$K$20 -> 25252.225 | O44: =SUM($E36:$E36)*'P&L by Ctn'!$Q$20 -> 0 | P44: =SUM($F36:$F36)*'P&L by Ctn'!$X$20 -> 0 | Q44: =SUM($G36:$G36)*'P&L by Ctn'!$AD$20 -> 0 | R44: =SUM($H36:$H36)*'P&L by Ctn'!$AA$20 -> 0 | S44: =SUM($I36:$I36)*'P&L by Ctn'!$AG$20 -> 0 | T44: =SUM(M44:S44) -> 226087.88
B45: MF% | C45: =IFERROR($C44/$C$38,0) -> 0.15438422 | D45: =IFERROR($D44/$D$38,0) -> 0.06888196 | E45: =IFERROR($E44/$E$38,0) -> 0 | F45: =IFERROR($F44/$F$38,0) -> 0 | G45: =IFERROR($G44/$G$38,0) -> 0 | H45: =IFERROR($H44/$H$38,0) -> 0 | I45: =IFERROR($I44/$I$38,0) -> 0 | J45: =IFERROR(J44/J$38,0) -> 0.076651771 | L45: MF% | M45: =IFERROR(M44/M$38,0) -> 0.15438422 | N45: =IFERROR(N44/N$38,0) -> 0.06888196 | O45: =IFERROR(O44/O$38,0) -> 0 | P45: =IFERROR(P44/P$38,0) -> 0 | Q45: =IFERROR(Q44/Q$38,0) -> 0 | R45: =IFERROR(R44/R$38,0) -> 0 | S45: =IFERROR(S44/S$38,0) -> 0 | T45: =IFERROR(T44/T$38,0) -> 0.076651771
B46: VSE | C46: =SUM($C36:$C36)*'P&L by Ctn'!$E$22 -> 31124.135 | D46: =SUM($D36:$D36)*'P&L by Ctn'!$K$22 -> 6437.7614 | E46: =SUM($E36:$E36)*'P&L by Ctn'!$Q$22 -> 23715.503 | F46: =SUM($F36:$F36)*'P&L by Ctn'!$X$22 -> 0 | G46: =SUM($G36:$G36)*'P&L by Ctn'!$AD$22 -> 88.122138 | H46: =SUM($H36:$H36)*'P&L by Ctn'!$AA$22 -> 184.27842 | I46: =SUM($I36:$I36)*'P&L by Ctn'!$AG$22 -> 198.36313 | J46: =SUM(C46:I46) -> 61748.163 | L46: VSE | M46: =SUM($C36:$C36)*'P&L by Ctn'!$E$22 -> 31124.135 | N46: =SUM($D36:$D36)*'P&L by Ctn'!$K$22 -> 6437.7614 | O46: =SUM($E36:$E36)*'P&L by Ctn'!$Q$22 -> 23715.503 | P46: =SUM($F36:$F36)*'P&L by Ctn'!$X$22 -> 0 | Q46: =SUM($G36:$G36)*'P&L by Ctn'!$AD$22 -> 88.122138 | R46: =SUM($H36:$H36)*'P&L by Ctn'!$AA$22 -> 184.27842 | S46: =SUM($I36:$I36)*'P&L by Ctn'!$AG$22 -> 198.36313 | T46: =SUM(M46:S46) -> 61748.163
B47: GP2 | C47: =C40-C42-C44-C46 -> #REF! | D47: =D40-D42-D44-D46 -> #REF! | E47: =E40-E42-E44-E46 -> #REF! | F47: =F40-F42-F44-F46 -> 0 | G47: =G40-G42-G44-G46 -> 2221.0671 | H47: =H40-H42-H44-H46 -> 1735.7216 | I47: =I40-I42-I44-I46 -> 722.71795 | J47: =J40-J42-J44-J46 -> #REF! | L47: GP2 | M47: =M40-M42-M44-M46 -> #REF! | N47: =N40-N42-N44-N46 -> #REF! | O47: =O40-O42-O44-O46 -> #REF! | P47: =P40-P42-P44-P46 -> 0 | Q47: =Q40-Q42-Q44-Q46 -> 2221.0671 | R47: =R40-R42-R44-R46 -> 1735.7216 | S47: =S40-S42-S44-S46 -> 722.71795 | T47: =T40-T42-T44-T46 -> #REF!
